Workbook

Sheet 汇总
A1: 序号 | B1: 年度 | C1: 月度 | D1: 账户 | E1: 收入 | F1: 支出 | G1: 结算金额 | H1: 备注
A2: 1 | B2: 2024 | C2: 11 | D2: MERCURY | E2: =SUM(Mercury2024!F2:F97) -> 6438.05 | F2: =SUM(Mercury2024!G2:G97) -> 4848.6 | G2: =E2-F2 -> 1589.45
A3: 2 | B3: 2024 | C3: 11 | D3: PayPal | E3: =SUM(PayPal2024!M2:M119) -> 1128.18 | F3: =SUM(PayPal2024!N2:N119) -> 518.94 | G3: =E3-F3 -> 609.24
A4: 3 | B4: 2024 | C4: 11 | D4: USDT | E4: =SUM(USDT2024!G2:G34) -> 2721.4654 | F4: =SUM(USDT2024!H2:H34) -> 4709.26 | G4: =E4-F4 -> -1987.7946
A5: 4 | B5: 2024 | C5: 11 | D5: WISE | E5: =SUM(Wise2024!N2:N5) -> 743.17 | F5: =SUM(Wise2024!O2:O5) -> 743 | G5: =E5-F5 -> 0.17
A6: 5 | B6: 2024 | C6: 11 | D6: TUTU | E6: =SUM(TUTU账目!E2:E8) -> 2336.08 | F6: =SUM(TUTU账目!G2:G8) -> 2738.76 | G6: =E6-F6 -> -402.68
A7: 6 | B7: 2024 | C7: 12 | D7: MERCURY | E7: =SUM(Mercury2024!F98:F106) -> 637.7 | F7: =SUM(Mercury2024!G98:G106) -> 906.77 | G7: =E7-F7 -> -269.07
A8: 7 | B8: 2024 | C8: 12 | D8: PayPal | E8: =SUM(PayPal2024!M120:M194) -> 833.34 | F8: =SUM(PayPal2024!N120:N194) -> 646.97 | G8: =E8-F8 -> 186.37
A9: 8 | B9: 2024 | C9: 12 | D9: USDT | G9: =E9-F9 -> 0
A10: 9 | B10: 2024 | C10: 12 | D10: WISE | E10: =SUM(Wise2024!N6:N25) -> 2049.86 | F10: =SUM(Wise2024!O6:O25) -> 453.11 | G10: =E10-F10 -> 1596.75
A11: 10 | B11: 2024 | C11: 12 | D11: TUTU | E11: =SUM(TUTU账目!E9) -> 0 | F11: =SUM(TUTU账目!G9) -> 409.14 | G11: =E11-F11 -> -409.14
A12: 11 | B12: 2025 | C12: 1 | D12: MERCURY | E12: =SUM(Mercury2025!F2:F7) -> 0 | F12: =SUM(Mercury2025!G2:G7) -> 1059.52 | G12: =E12-F12 -> -1059.52
A13: 12 | B13: 2025 | C13: 1 | D13: PayPal | E13: =SUM(PayPal2025!M2:M43) -> 316.52 | F13: =SUM(PayPal2025!N2:N43) -> 566.77 | G13: =E13-F13 -> -250.25
A14: 13 | B14: 2025 | C14: 1 | D14: USDT | E14: =SUM(USDT2025!H20:H33) -> 819.1751 | F14: =SUM(USDT2025!I20:I33) -> 1493.7251 | G14: =E14-F14 -> -674.55
A15: 14 | B15: 2025 | C15: 1 | D15: WISE | E15: =SUM(Wise2025!N2:N26) -> 2992.47 | F15: =SUM(Wise2025!O2:O26) -> 2000.77 | G15: =E15-F15 -> 991.7
A16: 15 | B16: 2025 | C16: 1 | D16: TUTU | E16: =SUM(TUTU账目!E10) -> 0 | F16: =SUM(TUTU账目!G10) -> 411.8 | G16: =E16-F16 -> -411.8
A17: 16 | B17: 2025 | C17: 1 | D17: 其它流水 | E17: =SUM(其它流水2025!J2) -> 0 | F17: =SUM(其它流水2025!L2)*-1 -> 375.56 | G17: =E17-F17 -> -375.56
A18: 17 | B18: 2025 | C18: 2 | D18: MERCURY | E18: =SUM(Mercury2025!F8:F16) -> 3325.31 | F18: =SUM(Mercury2025!G8:G16) -> 1430.77 | G18: =E18-F18 -> 1894.54
A19: 18 | B19: 2025 | C19: 2 | D19: PayPal | E19: =SUM(PayPal2025!M44:M80) -> 567.2 | F19: =SUM(PayPal2025!N44:N80) -> 604.21 | G19: =E19-F19 -> -37.01
A20: 19 | B20: 2025 | C20: 2 | D20: USDT | E20: =SUM(USDT2025!H34:H39) -> 882.0941 | F20: =SUM(USDT2025!I34:I35) -> 0 | G20: =E20-F20 -> 882.0941
A21: 20 | B21: 2025 | C21: 2 | D21: WISE | E21: =SUM(Wise2025!N27:N46) -> 1332.58 | F21: =SUM(Wise2025!O27:O46) -> 3979.77 | G21: =E21-F21 -> -2647.19
A22: 21 | B22: 2025 | C22: 2 | D22: TUTU | E22: =SUM(TUTU账目!E11) -> 0 | F22: =SUM(TUTU账目!G11) -> 409.9 | G22: =E22-F22 -> -409.9
A23: 22 | B23: 2025 | C23: 2 | D23: 其它流水 | E23: 0 | F23: 0 | G23: 0
A24: 23 | B24: 2025 | C24: 3 | D24: MERCURY | E24: =SUM(Mercury2025!F17:F41) -> 1672.78 | F24: =SUM(Mercury2025!G17:G41) -> 1328.56 | G24: =E24-F24 -> 344.22
A25: 24 | B25: 2025 | C25: 3 | D25: PayPal | E25: =SUM(PayPal2025!M81:M99) -> 78.47 | F25: =SUM(PayPal2025!N81:N99) -> 34.27 | G25: =E25-F25 -> 44.2
A26: 25 | B26: 2025 | C26: 3 | D26: USDT | E26: =SUM(USDT2025!H39:H59) -> 1573.9828 | F26: =SUM(USDT2025!I36) -> 0 | G26: =E26-F26 -> 1573.9828
A27: 26 | B27: 2025 | C27: 3 | D27: WISE | E27: 0 | F27: 0 | G27: =E27-F27 -> 0
A28: 27 | B28: 2025 | C28: 3 | D28: TUTU | E28: =SUM(TUTU账目!E12) -> 0 | F28: =SUM(TUTU账目!G12) -> 401.4 | G28: =E28-F28 -> -401.4
A29: 28 | B29: 2025 | C29: 3 | D29: 其它流水 | E29: 0 | F29: 0 | G29: =E29-F29 -> 0
A30: 29 | B30: 2025 | C30: 4 | D30: MERCURY | E30: =SUM(Mercury2025!F42:F58) -> 3106.11 | F30: =SUM(Mercury2025!G42:G58) -> 3860.84 | G30: =E30-F30 -> -754.73
A31: 30 | B31: 2025 | C31: 4 | D31: PayPal | E31: =SUM(PayPal2025!M100:M125) -> 128.82 | F31: =SUM(PayPal2025!N100:N125) -> 10.91 | G31: =E31-F31 -> 117.91
A32: 31 | B32: 2025 | C32: 4 | D32: USDT | E32: =SUM(USDT2025!H60:H84) -> 2330.4374 | F32: 0 | G32: =E32-F32 -> 2330.4374
A33: 32 | B33: 2025 | C33: 4 | D33: WISE | E33: =SUM(Wise2025!N47:N48) -> 1262.5 | F33: 0 | G33: =E33-F33 -> 1262.5
A34: 33 | B34: 2025 | C34: 4 | D34: TUTU | E34: =SUM(TUTU账目!E28) -> 0 | F34: =SUM(TUTU账目!G13) -> 400.12 | G34: =E34-F34 -> -400.12
A35: 34 | B35: 2025 | C35: 4 | D35: 支付宝 | E35: =SUM(支付宝!H2) -> 836 | F35: 0 | G35: =E35-F35 -> 836
A36: 35 | B36: 2025 | C36: 4 | D36: 其它流水 | E36: 0 | F36: 0 | G36: =E36-F36 -> 0
A37: 36 | B37: 2025 | C37: 5 | D37: MERCURY | E37: =SUM(Mercury2025!F59:F62) -> 864.9 | F37: =SUM(Mercury2025!G59:G62) -> 1945.5 | G37: =E37-F37 -> -1080.6
A38: 37 | B38: 2025 | C38: 5 | D38: PayPal | E38: =SUM(PayPal2025!M126:M155) -> 293.3 | F38: =SUM(PayPal2025!N126:N155) -> 20.82 | G38: =E38-F38 -> 272.48
A39: 38 | B39: 2025 | C39: 5 | D39: USDT | E39: =SUM(USDT2025!H85:H110) -> 2415.27 | F39: 0 | G39: =E39-F39 -> 2415.27
A40: 39 | B40: 2025 | C40: 5 | D40: WISE | E40: =SUM(Wise2025!N49:N52) -> 2090.55 | F40: 0 | G40: =E40-F40 -> 2090.55
A41: 40 | B41: 2025 | C41: 5 | D41: TUTU | E41: =SUM(TUTU账目!E35) -> 0 | F41: =SUM(TUTU账目!G35) -> 0 | G41: =E41-F41 -> 0
A42: 41 | B42: 2025 | C42: 5 | D42: 支付宝 | E42: =SUM(支付宝!H3) -> 300 | F42: 0 | G42: =E42-F42 -> 300
A43: 42 | B43: 2025 | C43: 5 | D43: 其它流水 | E43: 0 | F43: 0 | G43: =E43-F43 -> 0
A44: 43 | B44: 2025 | C44: 6 | D44: MERCURY | E44: =SUM(Mercury2025!F63:F68) -> 2138.99 | F44: =SUM(Mercury2025!G63:G68) -> 1412.75 | G44: =E44-F44 -> 726.24
A45: 44 | B45: 2025 | C45: 6 | D45: PayPal | E45: =SUM(PayPal2025!M156:M187) -> 102.82 | F45: =SUM(PayPal2025!N156:N187) -> 348.54 | G45: =E45-F45 -> -245.72
A46: 45 | B46: 2025 | C46: 6 | D46: USDT | E46: =SUM(USDT2025!H111:H142) -> 2241.6001 | F46: =SUM(USDT2025!I110:I142) -> 126.4675 | G46: =E46-F46 -> 2115.1326
A47: 46 | B47: 2025 | C47: 6 | D47: WISE | E47: =SUM(Wise2025!N53:N59) -> 4141.65 | F47: =SUM(Wise2025!O53:O59) -> 2264.08 | G47: =E47-F47 -> 1877.57
A48: 47 | B48: 2025 | C48: 6 | D48: TUTU | E48: 0 | F48: 395.1 | G48: =E48-F48 -> -395.1
A49: 48 | B49: 2025 | C49: 6 | D49: 支付宝 | E49: 0 | F49: 0 | G49: =E49-F49 -> 0
A50: 49 | B50: 2025 | C50: 6 | D50: Payssion | E50: =SUM(Payssion!J2:J65) -> 545.51 | F50: 0 | G50: =E50-F50 -> 545.51
A51: 50 | B51: 2025 | C51: 6 | D51: 其它流水 | E51: 0 | F51: 0 | G51: =E51-F51 -> 0
A52: 51 | B52: 2025 | C52: 6 | D52: 工资 | E52: 0 | F52: =SUM(工资表!H2:H3) -> 3424 | G52: =E52-F52 -> -3424
A53: 52 | B53: 2025 | C53: 7 | D53: MERCURY | E53: =SUM(Mercury2025!F69:F71) -> 2562.49 | F53: =SUM(Mercury2025!G69:G71) -> 34 | G53: =E53-F53 -> 2528.49
A54: 53 | B54: 2025 | C54: 7 | D54: PayPal | E54: =SUM(PayPal2025!M188:M208) -> 118.74 | F54: =SUM(PayPal2025!N188:N208) -> 15.67 | G54: =E54-F54 -> 103.07
A55: 54 | B55: 2025 | C55: 7 | D55: USDT | E55: =SUM(USDT2025!H149:H184) -> 5515.2838 | F55: =SUM(USDT2025!I143:I184) -> 1500.21 | G55: =E55-F55 -> 4015.0738
A56: 55 | B56: 2025 | C56: 7 | D56: WISE | E56: =SUM(Wise2025!N60:N65) -> 2649.77 | F56: =SUM(Wise2025!O60:O65) -> 2787.65 | G56: =E56-F56 -> -137.88
A57: 56 | B57: 2025 | C57: 7 | D57: TUTU | E57: 0 | F57: 374.7 | G57: =E57-F57 -> -374.7
A58: 57 | B58: 2025 | C58: 7 | D58: 支付宝 | E58: 0 | F58: 0 | G58: =E58-F58 -> 0
A59: 58 | B59: 2025 | C59: 7 | D59: Payssion | E59: =SUM(Payssion!J66:J124) -> 627.15 | F59: 1500 | G59: =E59-F59 -> -872.85
A60: 59 | B60: 2025 | C60: 7 | D60: 其它流水 | E60: 0 | F60: 0 | G60: =E60-F60 -> 0
A61: 60 | B61: 2025 | C61: 7 | D61: 工资 | E61: 0 | F61: 0 | G61: =E61-F61 -> 0
A62: 61 | B62: 2025 | C62: 8 | D62: MERCURY | E62: =SUM(Mercury2025!F72:F78) -> 2037.5 | F62: =SUM(Mercury2025!G72:G78) -> 4292.49 | G62: =E62-F62 -> -2254.99
A63: 62 | B63: 2025 | C63: 8 | D63: PayPal | E63: =SUM(PayPal2025!M209:M223) -> 77.76 | F63: =SUM(PayPal2025!N209:N223) -> 20.44 | G63: =E63-F63 -> 57.32
A64: 63 | B64: 2025 | C64: 8 | D64: USDT | E64: =SUM(USDT2025!H185:H211) -> 12768.354 | F64: =SUM(USDT2025!I185:I211) -> 12955.93 | G64: =E64-F64 -> -187.57624
A65: 64 | B65: 2025 | C65: 8 | D65: WISE | E65: =SUM(Wise2025!N66:N71) -> 2044.04 | F65: =SUM(Wise2025!O66:O71) -> 3978 | G65: =E65-F65 -> -1933.96
A66: 65 | B66: 2025 | C66: 8 | D66: TUTU | E66: 0 | F66: 374.76 | G66: =E66-F66 -> -374.76
A67: 66 | B67: 2025 | C67: 8 | D67: 支付宝 | E67: 0 | F67: 0 | G67: =E67-F67 -> 0
A68: 67 | B68: 2025 | C68: 8 | D68: Payssion | E68: =SUM(Payssion!J125:J142) -> -674.8 | F68: 1000 | G68: =E68-F68 -> -1674.8
A69: 68 | B69: 2025 | C69: 8 | D69: 其它流水 | E69: 0 | F69: =SUM(其它流水2025!L3:L5)*-1 -> 953.38 | G69: =E69-F69 -> -953.38
A70: 69 | B70: 2025 | C70: 8 | D70: 工资 | E70: 0 | F70: 0 | G70: =E70-F70 -> 0
A71: 70 | B71: 2025 | C71: 9 | D71: MERCURY | E71: =SUM(Mercury2025!F79:F93) -> 1058 | F71: =SUM(Mercury2025!G79:G93) -> 2790.01 | G71: =E71-F71 -> -1732.01
A72: 71 | B72: 2025 | C72: 9 | D72: PayPal | E72: =SUM(PayPal2025!M224:M238) -> 275.33 | F72: =SUM(PayPal2025!N224:N238) -> 23.78 | G72: =E72-F72 -> 251.55
A73: 72 | B73: 2025 | C73: 9 | D73: USDT | E73: =SUM(USDT2025!H212:H240) -> 7885.9106 | F73: =SUM(USDT2025!I212:I240) -> 3348.4328 | G73: =E73-F73 -> 4537.4778
A74: 73 | B74: 2025 | C74: 9 | D74: WISE | E74: =SUM(Wise2025!N72:N78) -> 1453.02 | F74: =SUM(Wise2025!O72:O78) -> 3861.13 | G74: =E74-F74 -> -2408.11
A75: 74 | B75: 2025 | C75: 9 | D75: TUTU | E75: 0 | F75: 374.758 | G75: =E75-F75 -> -374.758
A76: 75 | B76: 2025 | C76: 9 | D76: 支付宝 | E76: 0 | F76: 0 | G76: =E76-F76 -> 0
A77: 76 | B77: 2025 | C77: 9 | D77: Payssion | E77: =SUM(Payssion!J143:J216) -> -73.07 | F77: 0 | G77: =E77-F77 -> -73.07
A78: 77 | B78: 2025 | C78: 9 | D78: 其它流水 | E78: 0 | F78: =SUM(其它流水2025!L6:L11)*-1 -> 1322.93 | G78: =E78-F78 -> -1322.93
A79: 78 | B79: 2025 | C79: 9 | D79: 工资 | E79: 0 | F79: 0 | G79: =E79-F79 -> 0
A80: 79 | B80: 2025 | C80: 10 | D80: MERCURY | E80: =SUM(Mercury2025!F94:F102) -> 2046.57 | F80: =SUM(Mercury2025!G94:G102) -> 1635.26 | G80: =E80-F80 -> 411.31
A81: 80 | B81: 2025 | C81: 10 | D81: PayPal | E81: =SUM(PayPal2025!M239:M262) -> 142.05 | F81: =SUM(PayPal2025!N239:N262) -> 756.22 | G81: =E81-F81 -> -614.17
A82: 81 | B82: 2025 | C82: 10 | D82: USDT | E82: =SUM(USDT2025!H241:H272) -> 9058.8329 | F82: =SUM(USDT2025!I241:I272) -> 7261.6949 | G82: =E82-F82 -> 1797.138
A83: 82 | B83: 2025 | C83: 10 | D83: WISE | E83: =SUM(Wise2025!N79:N85) -> 1537.55 | F83: =SUM(Wise2025!O79:O85) -> 966.5 | G83: =E83-F83 -> 571.05
A84: 83 | B84: 2025 | C84: 10 | D84: TUTU | E84: 0 | F84: 374.758 | G84: =E84-F84 -> -374.758
A85: 84 | B85: 2025 | C85: 10 | D85: 支付宝 | E85: 0 | F85: 0 | G85: =E85-F85 -> 0
A86: 85 | B86: 2025 | C86: 10 | D86: Payssion | E86: =SUM(Payssion!J217:J310,Payssion!J311) -> 331.33 | F86: 0 | G86: =E86-F86 -> 331.33
A87: 86 | B87: 2025 | C87: 10 | D87: 其它流水 | E87: 0 | F87: =SUM(其它流水2025!L12)*-1 -> 670 | G87: =E87-F87 -> -670
A88: 87 | B88: 2025 | C88: 10 | D88: 工资 | E88: 0 | F88: 0 | G88: =E88-F88 -> 0
A89: 88 | B89: 2025 | C89: 11 | D89: MERCURY | E89: =SUM(Mercury2025!F103:F112) -> 4887.66 | F89: =SUM(Mercury2025!G103:G112) -> 38.98 | G89: =E89-F89 -> 4848.68
A90: 89 | B90: 2025 | C90: 11 | D90: PayPal | E90: =SUM(PayPal2025!M263:M304) -> 372 | F90: =SUM(PayPal2025!N263:N304) -> 77.19 | G90: =E90-F90 -> 294.81
A91: 90 | B91: 2025 | C91: 11 | D91: USDT | E91: =SUM(USDT2025!H273:H320) -> 6391.3873 | F91: =SUM(USDT2025!I273:I320) -> 18238.845 | G91: =E91-F91 -> -11847.458
A92: 91 | B92: 2025 | C92: 11 | D92: WISE | E92: =SUM(Wise2025!N86:N91) -> 2473.01 | F92: =SUM(Wise2025!O86:O91) -> 1420 | G92: =E92-F92 -> 1053.01
A93: 92 | B93: 2025 | C93: 11 | D93: TUTU | E93: 0 | F93: 374.787 | G93: =E93-F93 -> -374.787
A94: 93 | B94: 2025 | C94: 11 | D94: 支付宝 | E94: =SUM(支付宝!H4) -> 460 | F94: 0 | G94: =E94-F94 -> 460
A95: 94 | B95: 2025 | C95: 11 | D95: Payssion | E95: =SUM(Payssion!J312:J429) -> 81.21 | F95: 0 | G95: =E95-F95 -> 81.21
A96: 95 | B96: 2025 | C96: 11 | D96: 其它流水 | E96: 0 | F96: =SUM(其它流水2025!L13:L14)*-1 -> 760 | G96: =E96-F96 -> -760
A97: 96 | B97: 2025 | C97: 11 | D97: 工资 | E97: 0 | F97: 0 | G97: =E97-F97 -> 0
A98: 97 | B98: 2025 | C98: 12 | D98: MERCURY | E98: =SUM(Mercury2025!F113:F123) -> 3287.52 | F98: =SUM(Mercury2025!G113:G123) -> 1438.26 | G98: =E98-F98 -> 1849.26
A99: 98 | B99: 2025 | C99: 12 | D99: PayPal | E99: =SUM(PayPal2025!M305:M350) -> 588.13 | F99: =SUM(PayPal2025!N305:N350) -> 167.09 | G99: =E99-F99 -> 421.04
A100: 99 | B100: 2025 | C100: 12 | D100: USDT | E100: =SUM(USDT2025!H320:H347) -> 3021.7641 | F100: =SUM(USDT2025!I320:I347) -> 7536.3 | G100: =E100-F100 -> -4514.5359
...

Sheet Mercury2025
A1: Date (UTC) | B1: Y | C1: M | D1: Description | E1: Amount | F1: IN | G1: OUT | H1: Status | I1: Source Account | J1: Bank Description | K1: Reference | L1: Note | M1: Last Four Digits | N1: Name On Card | O1: Category | P1: GL Code | Q1: Timestamp | R1: Original Currency | S1: Check Number
A2: 01-30-2025 | B2: 2025 | C2: 1 | D2: Cloudflare | E2: -11.84 | F2: =IF(E2>0,E2*1,0) -> 0 | G2: =IF(E2<0,E2*-1,0) -> 11.84 | H2: Sent | I2: Mercury Checking xx9768 | J2: CLOUDFLARE | M2: 5180 | N2: XIANG JIAO | O2: Software | Q2: 01-30-2025 02:43:10 | R2: USD
A3: 01-22-2025 | B3: 2025 | C3: 1 | D3: Alibaba | E3: -10.8 | F3: =IF(E3>0,E3*1,0) -> 0 | G3: =IF(E3<0,E3*-1,0) -> 10.8 | H3: Sent | I3: Mercury Checking xx9768 | J3: Alibaba.com Europe Lim | M3: 5180 | N3: XIANG JIAO | O3: Retail | Q3: 01-22-2025 04:58:09 | R3: USD
A4: 01-18-2025 | B4: 2025 | C4: 1 | D4: Nodehatch | E4: -46.39 | F4: =IF(E4>0,E4*1,0) -> 0 | G4: =IF(E4<0,E4*-1,0) -> 46.39 | H4: Sent | I4: Mercury Checking xx9768 | J4: NODEHATCH | M4: 5180 | N4: XIANG JIAO | O4: Software | Q4: 01-18-2025 09:20:06 | R4: GBP
A5: 01-18-2025 | B5: 2025 | C5: 1 | D5: Intl. Transaction Fee | E5: -1.39 | F5: =IF(E5>0,E5*1,0) -> 0 | G5: =IF(E5<0,E5*-1,0) -> 1.39 | H5: Sent | I5: Mercury Checking xx9768 | O5: FinancialInstitutionsAndFees | Q5: 01-18-2025 09:20:06
A6: 45839 | B6: 2025 | C6: 1 | D6: O2 Network Limited | E6: -955.1 | F6: =IF(E6>0,E6*1,0) -> 0 | G6: =IF(E6<0,E6*-1,0) -> 955.1 | H6: Sent | I6: Mercury Checking xx9768 | J6: Send Money transaction initiated on Mercury | K6: From Stars Flying Inc via mercury.com | L6: Server Hardware Fees | Q6: 45839.65
A7: 45689 | B7: 2025 | C7: 1 | D7: OVHcloud | E7: -34 | F7: =IF(E7>0,E7*1,0) -> 0 | G7: =IF(E7<0,E7*-1,0) -> 34 | H7: Sent | I7: Mercury Checking xx9768 | J7: OVHcloud | M7: 4422 | N7: Ovise Case | O7: Software | Q7: 45689.086 | R7: USD
A8: 02-28-2025 | B8: 2025 | C8: 2 | D8: STRIPE | E8: 40.84 | F8: =IF(E8>0,E8*1,0) -> 40.84 | G8: =IF(E8<0,E8*-1,0) -> 0 | H8: Sent | I8: Mercury Checking xx9768 | J8: STRIPE; TRANSFER; STARS FLYING INC | Q8: 02-28-2025 13:39:30
A9: 02-27-2025 | B9: 2025 | C9: 2 | D9: STRIPE | E9: 24.55 | F9: =IF(E9>0,E9*1,0) -> 24.55 | G9: =IF(E9<0,E9*-1,0) -> 0 | H9: Sent | I9: Mercury Checking xx9768 | J9: STRIPE; TRANSFER; STARS FLYING INC | Q9: 02-27-2025 13:34:07
A10: 02-26-2025 | B10: 2025 | C10: 2 | D10: WISE US INC | E10: 1782.62 | F10: =IF(E10>0,E10*1,0) -> 1782.62 | G10: =IF(E10<0,E10*-1,0) -> 0 | H10: Sent | I10: Mercury Checking xx9768 | J10: WISE US INC; STARS FLYI; Stars Flying Inc | K10: From Stars Flying Inc Via WISE | Q10: 02-26-2025 23:00:40
A11: 02-26-2025 | B11: 2025 | C11: 2 | D11: GOOGLE | E11: 26.21 | F11: =IF(E11>0,E11*1,0) -> 26.21 | G11: =IF(E11<0,E11*-1,0) -> 0 | H11: Sent | I11: Mercury Checking xx9768 | J11: GOOGLE; ADWORDS:12; Stars Flying Inc | Q11: 02-26-2025 20:00:19
A12: 02-22-2025 | B12: 2025 | C12: 2 | D12: Alibaba | E12: -10.8 | F12: =IF(E12>0,E12*1,0) -> 0 | G12: =IF(E12<0,E12*-1,0) -> 10.8 | H12: Sent | I12: Mercury Checking xx9768 | J12: Alibaba.com Europe Lim | M12: 5180 | N12: XIANG JIAO | O12: Retail | Q12: 02-22-2025 04:28:04 | R12: USD
A13: 02-21-2025 | B13: 2025 | C13: 2 | D13: American Registry For In | E13: -50 | F13: =IF(E13>0,E13*1,0) -> 0 | G13: =IF(E13<0,E13*-1,0) -> 50 | H13: Sent | I13: Mercury Checking xx9768 | J13: ARIN | M13: 5180 | N13: XIANG JIAO | O13: Other | Q13: 02-21-2025 13:20:07 | R13: USD
A14: 45779 | B14: 2025 | C14: 2 | D14: O2 Network Limited | E14: -1335.97 | F14: =IF(E14>0,E14*1,0) -> 0 | G14: =IF(E14<0,E14*-1,0) -> 1335.97 | H14: Sent | I14: Mercury Checking xx9768 | J14: Send Money transaction initiated on Mercury | K14: From Stars Flying Inc via mercury.com | L14: Network fees | Q14: 45779.65
A15: 45749 | B15: 2025 | C15: 2 | D15: WISE US INC | E15: 1451.09 | F15: =IF(E15>0,E15*1,0) -> 1451.09 | G15: =IF(E15<0,E15*-1,0) -> 0 | H15: Sent | I15: Mercury Checking xx9768 | J15: WISE US INC; idc NESSBI; Stars Flying Inc | K15: From NESSBIT INC Via WISE | Q15: 45749.966
A16: 45690 | B16: 2025 | C16: 2 | D16: OVHcloud | E16: -34 | F16: =IF(E16>0,E16*1,0) -> 0 | G16: =IF(E16<0,E16*-1,0) -> 34 | H16: Sent | I16: Mercury Checking xx9768 | J16: OVHcloud | M16: 4422 | N16: Ovise Case | O16: Software | Q16: 45690.576 | R16: USD
A17: 3/31/2025 | B17: 2025 | C17: 3 | D17: O2 Network Limited | E17: -500 | F17: =IF(E17>0,E17*1,0) -> 0 | G17: =IF(E17<0,E17*-1,0) -> 500 | H17: Sent | I17: Mercury Checking xx9768 | J17: Send Money transaction initiated on Mercury | K17: From Stars Flying Inc via mercury.com, network fee. | Q17: 3/31/2025 14:35
A18: 3/31/2025 | B18: 2025 | C18: 3 | D18: STRIPE | E18: 50.95 | F18: =IF(E18>0,E18*1,0) -> 50.95 | G18: =IF(E18<0,E18*-1,0) -> 0 | H18: Sent | I18: Mercury Checking xx9768 | J18: STRIPE; TRANSFER; STARS FLYING INC | Q18: 3/31/2025 13:55
A19: 3/28/2025 | B19: 2025 | C19: 3 | D19: STRIPE | E19: 26.25 | F19: =IF(E19>0,E19*1,0) -> 26.25 | G19: =IF(E19<0,E19*-1,0) -> 0 | H19: Sent | I19: Mercury Checking xx9768 | J19: STRIPE; TRANSFER; STARS FLYING INC | Q19: 3/28/2025 12:42
A20: 3/26/2025 | B20: 2025 | C20: 3 | D20: STRIPE | E20: 320.8 | F20: =IF(E20>0,E20*1,0) -> 320.8 | G20: =IF(E20<0,E20*-1,0) -> 0 | H20: Sent | I20: Mercury Checking xx9768 | J20: STRIPE; TRANSFER; STARS FLYING INC | Q20: 3/26/2025 12:39
A21: 3/25/2025 | B21: 2025 | C21: 3 | D21: STRIPE | E21: 13.63 | F21: =IF(E21>0,E21*1,0) -> 13.63 | G21: =IF(E21<0,E21*-1,0) -> 0 | H21: Sent | I21: Mercury Checking xx9768 | J21: STRIPE; TRANSFER; STARS FLYING INC | Q21: 3/25/2025 12:58
A22: 3/24/2025 | B22: 2025 | C22: 3 | D22: STRIPE | E22: 133.53 | F22: =IF(E22>0,E22*1,0) -> 133.53 | G22: =IF(E22<0,E22*-1,0) -> 0 | H22: Sent | I22: Mercury Checking xx9768 | J22: STRIPE; TRANSFER; STARS FLYING INC | Q22: 3/24/2025 13:58
A23: 3/22/2025 | B23: 2025 | C23: 3 | D23: Alibaba | E23: -10.8 | F23: =IF(E23>0,E23*1,0) -> 0 | G23: =IF(E23<0,E23*-1,0) -> 10.8 | H23: Sent | I23: Mercury Checking xx9768 | J23: Alibaba.com Europe Lim | M23: 5180 | N23: XIANG JIAO | O23: Retail | Q23: 3/22/2025 8:39 | R23: USD
A24: 3/21/2025 | B24: 2025 | C24: 3 | D24: STRIPE | E24: 39.6 | F24: =IF(E24>0,E24*1,0) -> 39.6 | G24: =IF(E24<0,E24*-1,0) -> 0 | H24: Sent | I24: Mercury Checking xx9768 | J24: STRIPE; TRANSFER; STARS FLYING INC | Q24: 3/21/2025 13:02
A25: 3/20/2025 | B25: 2025 | C25: 3 | D25: STRIPE | E25: 214.59 | F25: =IF(E25>0,E25*1,0) -> 214.59 | G25: =IF(E25<0,E25*-1,0) -> 0 | H25: Sent | I25: Mercury Checking xx9768 | J25: STRIPE; TRANSFER; STARS FLYING INC | Q25: 3/20/2025 12:42
A26: 3/19/2025 | B26: 2025 | C26: 3 | D26: STRIPE | E26: 351.02 | F26: =IF(E26>0,E26*1,0) -> 351.02 | G26: =IF(E26<0,E26*-1,0) -> 0 | H26: Sent | I26: Mercury Checking xx9768 | J26: STRIPE; TRANSFER; STARS FLYING INC | Q26: 3/19/2025 12:59
A27: 3/18/2025 | B27: 2025 | C27: 3 | D27: STRIPE | E27: 72.81 | F27: =IF(E27>0,E27*1,0) -> 72.81 | G27: =IF(E27<0,E27*-1,0) -> 0 | H27: Sent | I27: Mercury Checking xx9768 | J27: STRIPE; TRANSFER; STARS FLYING INC | Q27: 3/18/2025 13:04
A28: 3/17/2025 | B28: 2025 | C28: 3 | D28: STRIPE | E28: 15.5 | F28: =IF(E28>0,E28*1,0) -> 15.5 | G28: =IF(E28<0,E28*-1,0) -> 0 | H28: Sent | I28: Mercury Checking xx9768 | J28: STRIPE; TRANSFER; STARS FLYING INC | Q28: 3/17/2025 13:14
A29: 3/14/2025 | B29: 2025 | C29: 3 | D29: STRIPE | E29: 55.48 | F29: =IF(E29>0,E29*1,0) -> 55.48 | G29: =IF(E29<0,E29*-1,0) -> 0 | H29: Sent | I29: Mercury Checking xx9768 | J29: STRIPE; TRANSFER; STARS FLYING INC | Q29: 3/14/2025 12:33
A30: 3/13/2025 | B30: 2025 | C30: 3 | D30: STRIPE | E30: 38.34 | F30: =IF(E30>0,E30*1,0) -> 38.34 | G30: =IF(E30<0,E30*-1,0) -> 0 | H30: Sent | I30: Mercury Checking xx9768 | J30: STRIPE; TRANSFER; STARS FLYING INC | Q30: 3/13/2025 13:13
A31: 45994 | B31: 2025 | C31: 3 | D31: STRIPE | E31: 20.06 | F31: =IF(E31>0,E31*1,0) -> 20.06 | G31: =IF(E31<0,E31*-1,0) -> 0 | H31: Sent | I31: Mercury Checking xx9768 | J31: STRIPE; TRANSFER; STARS FLYING INC | Q31: 45994.521
A32: 45964 | B32: 2025 | C32: 3 | D32: STRIPE | E32: 1.63 | F32: =IF(E32>0,E32*1,0) -> 1.63 | G32: =IF(E32<0,E32*-1,0) -> 0 | H32: Sent | I32: Mercury Checking xx9768 | J32: STRIPE; TRANSFER; STARS FLYING INC | Q32: 45964.531
A33: 45933 | B33: 2025 | C33: 3 | D33: STRIPE | E33: 13.97 | F33: =IF(E33>0,E33*1,0) -> 13.97 | G33: =IF(E33<0,E33*-1,0) -> 0 | H33: Sent | I33: Mercury Checking xx9768 | J33: STRIPE; TRANSFER; STARS FLYING INC | Q33: 45933.787
A34: 45841 | B34: 2025 | C34: 3 | D34: STRIPE | E34: 60.96 | F34: =IF(E34>0,E34*1,0) -> 60.96 | G34: =IF(E34<0,E34*-1,0) -> 0 | H34: Sent | I34: Mercury Checking xx9768 | J34: STRIPE; TRANSFER; STARS FLYING INC | Q34: 45841.667
A35: 45811 | B35: 2025 | C35: 3 | D35: O2 Network Limited | E35: -380 | F35: =IF(E35>0,E35*1,0) -> 0 | G35: =IF(E35<0,E35*-1,0) -> 380 | H35: Sent | I35: Mercury Checking xx9768 | J35: Send Money transaction initiated on Mercury | K35: From Stars Flying Inc via mercury.com, network fee. | Q35: 45811.649
A36: 45811 | B36: 2025 | C36: 3 | D36: STRIPE | E36: 83.96 | F36: =IF(E36>0,E36*1,0) -> 83.96 | G36: =IF(E36<0,E36*-1,0) -> 0 | H36: Sent | I36: Mercury Checking xx9768 | J36: STRIPE; TRANSFER; STARS FLYING INC | Q36: 45811.583
A37: 45780 | B37: 2025 | C37: 3 | D37: STRIPE | E37: 99.47 | F37: =IF(E37>0,E37*1,0) -> 99.47 | G37: =IF(E37<0,E37*-1,0) -> 0 | H37: Sent | I37: Mercury Checking xx9768 | J37: STRIPE; TRANSFER; STARS FLYING INC | Q37: 45780.608
A38: 45750 | B38: 2025 | C38: 3 | D38: O2 Network Limited | E38: -403.76 | F38: =IF(E38>0,E38*1,0) -> 0 | G38: =IF(E38<0,E38*-1,0) -> 403.76 | H38: Sent | I38: Mercury Checking xx9768 | J38: Send Money transaction initiated on Mercury | K38: From Stars Flying Inc via mercury.com. Network fee. | Q38: 45750.649
A39: 45750 | B39: 2025 | C39: 3 | D39: STRIPE | E39: 53.58 | F39: =IF(E39>0,E39*1,0) -> 53.58 | G39: =IF(E39<0,E39*-1,0) -> 0 | H39: Sent | I39: Mercury Checking xx9768 | J39: STRIPE; TRANSFER; STARS FLYING INC | Q39: 45750.631
A40: 45719 | B40: 2025 | C40: 3 | D40: STRIPE | E40: 6.65 | F40: =IF(E40>0,E40*1,0) -> 6.65 | G40: =IF(E40<0,E40*-1,0) -> 0 | H40: Sent | I40: Mercury Checking xx9768 | J40: STRIPE; TRANSFER; STARS FLYING INC | Q40: 45719.583
A41: 45691 | B41: 2025 | C41: 3 | D41: OVHcloud | E41: -34 | F41: =IF(E41>0,E41*1,0) -> 0 | G41: =IF(E41<0,E41*-1,0) -> 34 | H41: Sent | I41: Mercury Checking xx9768 | J41: OVHcloud | M41: 4422 | N41: Ovise Case | O41: Software | Q41: 45691.606 | R41: USD
A42: 4/30/2025 | B42: 2025 | C42: 4 | D42: O2 Network Limited | E42: -1156.57 | F42: =IF(E42>0,E42*1,0) -> 0 | G42: =IF(E42<0,E42*-1,0) -> 1156.57 | H42: Sent | I42: Mercury Checking xx9768 | J42: Send Money transaction initiated on Mercury | K42: From Stars Flying Inc via mercury.com, Network fee. | R42: 4/30/2025 14:35
A43: 4/26/2025 | B43: 2025 | C43: 4 | D43: Amazon Prime | E43: 0 | F43: =IF(E43>0,E43*1,0) -> 0 | G43: =IF(E43<0,E43*-1,0) -> 0 | H43: Failed | I43: Mercury Checking xx9768 | J43: AMAZON PRIME PMTS | M43: 3866 | N43: Andrew Reed | O43: Retail | R43: 4/26/2025 23:41 | S43: USD
A44: 4/22/2025 | B44: 2025 | C44: 4 | D44: Alibaba | E44: -10.8 | F44: =IF(E44>0,E44*1,0) -> 0 | G44: =IF(E44<0,E44*-1,0) -> 10.8 | H44: Sent | I44: Mercury Checking xx9768 | J44: Alibaba.com Europe Lim | M44: 5180 | N44: XIANG JIAO | O44: Retail | R44: 4/22/2025 7:19 | S44: USD
A45: 4/14/2025 | B45: 2025 | C45: 4 | D45: STRIPE | E45: 64.78 | F45: =IF(E45>0,E45*1,0) -> 64.78 | G45: =IF(E45<0,E45*-1,0) -> 0 | H45: Sent | I45: Mercury Checking xx9768 | J45: STRIPE; TRANSFER; STARS FLYING INC | R45: 4/14/2025 14:48
A46: 45965 | B46: 2025 | C46: 4 | D46: STRIPE | E46: 4.29 | F46: =IF(E46>0,E46*1,0) -> 4.29 | G46: =IF(E46<0,E46*-1,0) -> 0 | H46: Sent | I46: Mercury Checking xx9768 | J46: STRIPE; TRANSFER; STARS FLYING INC | R46: 45965.549
A47: 45934 | B47: 2025 | C47: 4 | D47: STRIPE | E47: 72.04 | F47: =IF(E47>0,E47*1,0) -> 72.04 | G47: =IF(E47<0,E47*-1,0) -> 0 | H47: Sent | I47: Mercury Checking xx9768 | J47: STRIPE; TRANSFER; STARS FLYING INC | R47: 45934.526
A48: 45904 | B48: 2025 | C48: 4 | D48: STRIPE | E48: 219.22 | F48: =IF(E48>0,E48*1,0) -> 219.22 | G48: =IF(E48<0,E48*-1,0) -> 0 | H48: Sent | I48: Mercury Checking xx9768 | J48: STRIPE; TRANSFER; STARS FLYING INC | R48: 45904.546
A49: 45873 | B49: 2025 | C49: 4 | D49: STRIPE | E49: 7.79 | F49: =IF(E49>0,E49*1,0) -> 7.79 | G49: =IF(E49<0,E49*-1,0) -> 0 | H49: Sent | I49: Mercury Checking xx9768 | J49: STRIPE; TRANSFER; STARS FLYING INC | R49: 45873.557
A50: 45842 | B50: 2025 | C50: 4 | D50: O2 Network Limited | E50: -956.21 | F50: =IF(E50>0,E50*1,0) -> 0 | G50: =IF(E50<0,E50*-1,0) -> 956.21 | H50: Sent | I50: Mercury Checking xx9768 | J50: Send Money transaction initiated on Mercury | K50: From Stars Flying Inc via mercury.com, network fee. | R50: 45842.608
A51: 45812 | B51: 2025 | C51: 4 | D51: AMAZON WEB SERVICES | E51: 0 | F51: =IF(E51>0,E51*1,0) -> 0 | G51: =IF(E51<0,E51*-1,0) -> 0 | H51: Failed | I51: Mercury Checking xx9768 | J51: AMAZON WEB SERVICES | M51: 4422 | N51: Ovise Case | R51: 45812.697 | S51: USD
A52: 45751 | B52: 2025 | C52: 4 | D52: PAYONEER INC | E52: 2120.64 | F52: =IF(E52>0,E52*1,0) -> 2120.64 | G52: =IF(E52<0,E52*-1,0) -> 0 | H52: Sent | I52: Mercury Checking xx9768 | J52: PAYONEER INC; 821115524; Stars Flying Inc | K52: Idc Fee | R52: 45751.757
A53: 45751 | B53: 2025 | C53: 4 | D53: STRIPE | E53: 68.29 | F53: =IF(E53>0,E53*1,0) -> 68.29 | G53: =IF(E53<0,E53*-1,0) -> 0 | H53: Sent | I53: Mercury Checking xx9768 | J53: STRIPE; TRANSFER; STARS FLYING INC | R53: 45751.537
A54: 45720 | B54: 2025 | C54: 4 | D54: STRIPE | E54: 40.04 | F54: =IF(E54>0,E54*1,0) -> 40.04 | G54: =IF(E54<0,E54*-1,0) -> 0 | H54: Sent | I54: Mercury Checking xx9768 | J54: STRIPE; TRANSFER; STARS FLYING INC | R54: 45720.522
A55: 45692 | B55: 2025 | C55: 4 | D55: O2 Network Limited | E55: -1703.26 | F55: =IF(E55>0,E55*1,0) -> 0 | G55: =IF(E55<0,E55*-1,0) -> 1703.26 | H55: Sent | I55: Mercury Checking xx9768 | J55: Send Money transaction initiated on Mercury | K55: From Stars Flying Inc via mercury.com, network fee. | R55: 45692.608
A56: 45692 | B56: 2025 | C56: 4 | D56: STRIPE | E56: 410.89 | F56: =IF(E56>0,E56*1,0) -> 410.89 | G56: =IF(E56<0,E56*-1,0) -> 0 | H56: Sent | I56: Mercury Checking xx9768 | J56: STRIPE; TRANSFER; STARS FLYING INC | R56: 45692.547
A57: 45692 | B57: 2025 | C57: 4 | D57: OVHcloud | E57: -34 | F57: =IF(E57>0,E57*1,0) -> 0 | G57: =IF(E57<0,E57*-1,0) -> 34 | H57: Sent | I57: Mercury Checking xx9768 | J57: OVHcloud | M57: 4422 | N57: Ovise Case | O57: Software | R57: 45692.098 | S57: USD
A58: 45661 | B58: 2025 | C58: 4 | D58: STRIPE | E58: 98.13 | F58: =IF(E58>0,E58*1,0) -> 98.13 | G58: =IF(E58<0,E58*-1,0) -> 0 | H58: Sent | I58: Mercury Checking xx9768 | J58: STRIPE; TRANSFER; STARS FLYING INC | R58: 45661.535
A59: 5/22/2025 | B59: 2025 | C59: 5 | D59: Alibaba | E59: -10.8 | F59: =IF(E59>0,E59*1,0) -> 0 | G59: =IF(E59<0,E59*-1,0) -> 10.8 | H59: Sent | I59: Mercury Checking xx9768 | J59: Alibaba.com Europe Lim | M59: 5180 | N59: XIANG JIAO | O59: Retail | R59: 5/22/2025 8:18 | S59: USD
A60: 45843 | B60: 2025 | C60: 5 | D60: PAYONEER 7362 | E60: 864.9 | F60: =IF(E60>0,E60*1,0) -> 864.9 | G60: =IF(E60<0,E60*-1,0) -> 0 | H60: Sent | I60: Mercury Checking xx9768 | J60: PAYONEER 7362; EDI PAYMNT; Stars Flying Inc | K60: REF*TN*3661850030*idc fee\ | R60: 45843.708
A61: 45782 | B61: 2025 | C61: 5 | D61: O2 Network Limited | E61: -1900.7 | F61: =IF(E61>0,E61*1,0) -> 0 | G61: =IF(E61<0,E61*-1,0) -> 1900.7 | H61: Sent | I61: Mercury Checking xx9768 | J61: Send Money transaction initiated on Mercury | K61: From Stars Flying Inc via mercury.com, Network fee. | R61: 45782.608
A62: 45693 | B62: 2025 | C62: 5 | D62: OVHcloud | E62: -34 | F62: =IF(E62>0,E62*1,0) -> 0 | G62: =IF(E62<0,E62*-1,0) -> 34 | H62: Sent | I62: Mercury Checking xx9768 | J62: OVHcloud | M62: 4422 | N62: Ovise Case | O62: Software | R62: 45693.101 | S62: USD
A63: 45936 | B63: 2025 | C63: 6 | D63: PAYONEER INC | E63: 1160.5 | F63: =IF(E63>0,E63*1,0) -> 1160.5 | G63: =IF(E63<0,E63*-1,0) -> 0 | H63: Sent | I63: Mercury Checking xx9122 | J63: PAYONEER INC; 848672294; Stars Flying Inc | K63: Payment via Payoneer | R63: 45936.715
A64: 45783 | B64: 2025 | C64: 6 | D64: O2 Network Limited | E64: -395.1 | F64: =IF(E64>0,E64*1,0) -> 0 | G64: =IF(E64<0,E64*-1,0) -> 395.1 | H64: Sent | I64: Mercury Checking xx9122 | J64: Send Money transaction initiated on Mercury | K64: From Stars Flying Inc via mercury.com, IDC fee. | R64: 45783.172
A65: 45753 | B65: 2025 | C65: 6 | D65: Mercury Checking xx9768 | E65: 978.49 | F65: =IF(E65>0,E65*1,0) -> 978.49 | G65: =IF(E65<0,E65*-1,0) -> 0 | H65: Sent | I65: Mercury Checking xx9122 | J65: Transfer to your new Mercury account | R65: 45753.882
A66: 45753 | B66: 2025 | C66: 6 | D66: Mercury Checking xx9122 | E66: -978.49 | F66: =IF(E66>0,E66*1,0) -> 0 | G66: =IF(E66<0,E66*-1,0) -> 978.49 | H66: Sent | I66: Mercury Checking xx9768 | J66: Transfer to your new Mercury account | R66: 45753.608
A67: 45722 | B67: 2025 | C67: 6 | D67: Cloudflare | E67: -5.16 | F67: =IF(E67>0,E67*1,0) -> 0 | G67: =IF(E67<0,E67*-1,0) -> 5.16 | H67: Sent | I67: Mercury Checking xx9768 | J67: CLOUDFLARE | M67: 5180 | N67: XIANG JIAO | O67: Software | R67: 45722.447 | S67: USD
A68: 45694 | B68: 2025 | C68: 6 | D68: OVHcloud | E68: -34 | F68: =IF(E68>0,E68*1,0) -> 0 | G68: =IF(E68<0,E68*-1,0) -> 34 | H68: Sent | I68: Mercury Checking xx9768 | J68: OVHcloud | M68: 4422 | N68: Ovise Case | O68: Software | R68: 45694.523 | S68: USD
A69: 7/16/2025 | B69: 2025 | C69: 7 | D69: PAYONEER 7362 | E69: 1082.49 | F69: =IF(E69>0,E69*1,0) -> 1082.49 | G69: =IF(E69<0,E69*-1,0) -> 0 | H69: Sent | I69: Mercury Checking xx9122 | J69: PAYONEER 7362; EDI PAYMNT; Stars Flying Inc | K69: REF*TN*3661851101*Payment via Payoneer\ | R69: 7/16/2025 17:10
A70: 45937 | B70: 2025 | C70: 7 | D70: AUS MERCHANT SERVICES, INC | E70: 1480 | F70: =IF(E70>0,E70*1,0) -> 1480 | G70: =IF(E70<0,E70*-1,0) -> 0 | H70: Sent | I70: Mercury Checking xx9122 | K70: PAYING OVERSEAS SUPPLIERS | R70: 45937.501
A71: 45695 | B71: 2025 | C71: 7 | D71: OVHcloud | E71: -34 | F71: =IF(E71>0,E71*1,0) -> 0 | G71: =IF(E71<0,E71*-1,0) -> 34 | H71: Sent | I71: Mercury Checking xx9122 | J71: OVHcloud | M71: 9884 | N71: Ovise Case | O71: Software | R71: 45695.088 | S71: USD
A72: 8/30/2025 | B72: 2025 | C72: 8 | D72: Amazon | E72: -18.38 | F72: =IF(E72>0,E72*1,0) -> 0 | G72: =IF(E72<0,E72*-1,0) -> 18.38 | H72: Pending | I72: Mercury Checking xx9122 | J72: AMAZON MKTPLACE PMTS | M72: 8690 | N72: XIANG JIAO | O72: Retail | R72: ####### | S72: USD
A73: 8/29/2025 | B73: 2025 | C73: 8 | D73: AUS MERCHANT SERVICES, INC | E73: 980 | F73: =IF(E73>0,E73*1,0) -> 980 | G73: =IF(E73<0,E73*-1,0) -> 0 | H73: Sent | I73: Mercury Checking xx9122 | K73: PAYING OVERSEAS SUPPLIERS | R73: #######
A74: 8/27/2025 | B74: 2025 | C74: 8 | D74: Visible | E74: -275 | F74: =IF(E74>0,E74*1,0) -> 0 | G74: =IF(E74<0,E74*-1,0) -> 275 | H74: Sent | I74: Mercury Checking xx9122 | J74: VISIBLE | M74: 8690 | N74: XIANG JIAO | O74: InternetAndTelephone | R74: ####### | S74: USD
A75: 8/18/2025 | B75: 2025 | C75: 8 | D75: Cloudflare | E75: -5.16 | F75: =IF(E75>0,E75*1,0) -> 0 | G75: =IF(E75<0,E75*-1,0) -> 5.16 | H75: Sent | I75: Mercury Checking xx9122 | J75: CLOUDFLARE | M75: 8690 | N75: XIANG JIAO | O75: Software | R75: ####### | S75: USD
A76: 8/13/2025 | B76: 2025 | C76: 8 | D76: O2 Network Limited | E76: -3959.95 | F76: =IF(E76>0,E76*1,0) -> 0 | G76: =IF(E76<0,E76*-1,0) -> 3959.95 | H76: Sent | I76: Mercury Checking xx9122 | J76: Send Money transaction initiated on Mercury | K76: From Stars Flying Inc via mercury.com | L76: IDC FEE | R76: #######
A77: 45846 | B77: 2025 | C77: 8 | D77: PAYONEER INC | E77: 1057.5 | F77: =IF(E77>0,E77*1,0) -> 1057.5 | G77: =IF(E77<0,E77*-1,0) -> 0 | H77: Sent | I77: Mercury Checking xx9122 | J77: PAYONEER INC; 873474283; Stars Flying Inc | K77: idc fee | R77: #######
A78: 45696 | B78: 2025 | C78: 8 | D78: Ovhcloud | E78: -34 | F78: =IF(E78>0,E78*1,0) -> 0 | G78: =IF(E78<0,E78*-1,0) -> 34 | H78: Sent | I78: Mercury Checking xx9122 | J78: OVHcloud | M78: 9884 | N78: Ovise Case | O78: Software | R78: ####### | S78: USD
A79: 9/30/2025 | B79: 2025 | C79: 9 | D79: O2 Network Limited | E79: -453.91 | F79: =IF(E79>0,E79*1,0) -> 0 | G79: =IF(E79<0,E79*-1,0) -> 453.91 | H79: Sent | I79: Mercury Checking xx9122 | J79: Send Money transaction initiated on Mercury | K79: From Stars Flying Inc via mercury.com network fee | R79: 9/30/2025 15:01
A80: 9/26/2025 | B80: 2025 | C80: 9 | D80: Walmart | E80: -59.53 | F80: =IF(E80>0,E80*1,0) -> 0 | G80: =IF(E80<0,E80*-1,0) -> 59.53 | H80: Sent | I80: Mercury Checking xx9122 | J80: WALMART.COM 8009256278 | M80: 8690 | N80: XIANG JIAO | O80: Retail | R80: 9/26/2025 14:29 | S80: USD
A81: 9/26/2025 | B81: 2025 | C81: 9 | D81: Amazon | E81: -7.57 | F81: =IF(E81>0,E81*1,0) -> 0 | G81: =IF(E81<0,E81*-1,0) -> 7.57 | H81: Sent | I81: Mercury Checking xx9122 | J81: AMAZON MKTPLACE PMTS | M81: 8690 | N81: XIANG JIAO | O81: Retail | R81: 9/26/2025 6:54 | S81: USD
A82: 9/26/2025 | B82: 2025 | C82: 9 | D82: Amazon | E82: -7.57 | F82: =IF(E82>0,E82*1,0) -> 0 | G82: =IF(E82<0,E82*-1,0) -> 7.57 | H82: Sent | I82: Mercury Checking xx9122 | J82: AMAZON MKTPLACE PMTS | M82: 8690 | N82: XIANG JIAO | O82: Retail | R82: 9/26/2025 3:56 | S82: USD
A83: 9/25/2025 | B83: 2025 | C83: 9 | D83: PITTQIAO NETWORK INFORMATION CO., LTD. | E83: -673.01 | F83: =IF(E83>0,E83*1,0) -> 0 | G83: =IF(E83<0,E83*-1,0) -> 673.01 | H83: Sent | I83: Mercury Checking xx9122 | J83: Send Money transaction initiated on Mercury | K83: From Stars Flying Inc network fee | R83: 9/25/2025 4:14
A84: 9/23/2025 | B84: 2025 | C84: 9 | D84: eBay | E84: -11.9 | F84: =IF(E84>0,E84*1,0) -> 0 | G84: =IF(E84<0,E84*-1,0) -> 11.9 | H84: Sent | I84: Mercury Checking xx9122 | J84: eBay O*01-13625-50498 | M84: 8690 | N84: XIANG JIAO | O84: Retail | R84: 9/23/2025 12:10 | S84: USD
A85: 9/21/2025 | B85: 2025 | C85: 9 | D85: eBay | E85: -17.14 | F85: =IF(E85>0,E85*1,0) -> 0 | G85: =IF(E85<0,E85*-1,0) -> 17.14 | H85: Sent | I85: Mercury Checking xx9122 | J85: eBay O*12-13601-64159 | M85: 8690 | N85: XIANG JIAO | O85: Retail | R85: 9/21/2025 12:19 | S85: USD
A86: 9/20/2025 | B86: 2025 | C86: 9 | D86: Walmart | E86: -50.08 | F86: =IF(E86>0,E86*1,0) -> 0 | G86: =IF(E86<0,E86*-1,0) -> 50.08 | H86: Sent | I86: Mercury Checking xx9122 | J86: WALMART.COM | M86: 8690 | N86: XIANG JIAO | O86: Retail | R86: 9/20/2025 1:14 | S86: USD
A87: 9/17/2025 | B87: 2025 | C87: 9 | D87: PAYONEER INC | E87: 1058 | F87: =IF(E87>0,E87*1,0) -> 1058 | G87: =IF(E87<0,E87*-1,0) -> 0 | H87: Sent | I87: Mercury Checking xx9122 | J87: PAYONEER INC; 890104990; Stars Flying Inc | K87: idc fee | R87: 9/17/2025 17:10
A88: 9/16/2025 | B88: 2025 | C88: 9 | D88: Qwaaq | E88: -39.07 | F88: =IF(E88>0,E88*1,0) -> 0 | G88: =IF(E88<0,E88*-1,0) -> 39.07 | H88: Sent | I88: Mercury Checking xx9122 | J88: Qwaaq, LLC | M88: 8690 | N88: XIANG JIAO | O88: Retail | R88: 9/16/2025 14:50 | S88: USD
A89: 45878 | B89: 2025 | C89: 9 | D89: O2 Network Limited | E89: -1412.87 | F89: =IF(E89>0,E89*1,0) -> 0 | G89: =IF(E89<0,E89*-1,0) -> 1412.87 | H89: Sent | I89: Mercury Checking xx9122 | J89: Send Money transaction initiated on Mercury | K89: From Stars Flying Inc via mercury.com Network Fee | R89: 45878.128
A90: 45697 | B90: 2025 | C90: 9 | D90: Amazon | E90: -18.38 | F90: =IF(E90>0,E90*1,0) -> 0 | G90: =IF(E90<0,E90*-1,0) -> 18.38 | H90: Sent | I90: Mercury Checking xx9122 | J90: AMAZON MKTPLACE PMTS | M90: 8690 | N90: XIANG JIAO | O90: Retail | R90: 45697.069 | S90: USD
A91: 45697 | B91: 2025 | C91: 9 | D91: Ovhcloud | E91: -34 | F91: =IF(E91>0,E91*1,0) -> 0 | G91: =IF(E91<0,E91*-1,0) -> 34 | H91: Sent | I91: Mercury Checking xx9122 | J91: OVHcloud | M91: 9884 | N91: Ovise Case | O91: Software | R91: 45697.058 | S91: USD
A92: 45666 | B92: 2025 | C92: 9 | D92: Tencent | E92: -2.52 | F92: =IF(E92>0,E92*1,0) -> 0 | G92: =IF(E92<0,E92*-1,0) -> 2.52 | H92: Sent | I92: Mercury Checking xx9122 | J92: Tencent Cloud | M92: 8690 | N92: XIANG JIAO | O92: Electronics | R92: 45666.042 | S92: USD
A93: 45666 | B93: 2025 | C93: 9 | D93: Tencent | E93: -2.46 | F93: =IF(E93>0,E93*1,0) -> 0 | G93: =IF(E93<0,E93*-1,0) -> 2.46 | H93: Sent | I93: Mercury Checking xx9122 | J93: Tencent Cloud | M93: 8690 | N93: XIANG JIAO | O93: Electronics | R93: 45666.038 | S93: USD
A94: 10/21/2025 | B94: 2025 | C94: 10 | D94: PITTQIAO NETWORK INFORMATION CO., LTD. | E94: -674.18 | F94: =IF(E94>0,E94*1,0) -> 0 | G94: =IF(E94<0,E94*-1,0) -> 674.18 | H94: Sent | I94: Mercury Checking xx9122 | J94: Send Money transaction initiated on Mercury | K94: From Stars Flying Inc | R94: 10/21/2025 4:04
A95: 10/17/2025 | B95: 2025 | C95: 10 | D95: Amazon | E95: 7.57 | F95: =IF(E95>0,E95*1,0) -> 7.57 | G95: =IF(E95<0,E95*-1,0) -> 0 | H95: Sent | I95: Mercury Checking xx9122 | J95: AMAZON MKTPLACE PMTS | M95: 8690 | N95: XIANG JIAO | O95: Retail | R95: 10/17/2025 1:09 | S95: USD
A96: 45940 | B96: 2025 | C96: 10 | D96: PAYONEER INC | E96: 1059 | F96: =IF(E96>0,E96*1,0) -> 1059 | G96: =IF(E96<0,E96*-1,0) -> 0 | H96: Sent | I96: Mercury Checking xx9122 | J96: PAYONEER INC; 899529579; Stars Flying Inc | K96: idc fee | R96: 45940.882
A97: 45910 | B97: 2025 | C97: 10 | D97: O2 Network Limited | E97: -922.25 | F97: =IF(E97>0,E97*1,0) -> 0 | G97: =IF(E97<0,E97*-1,0) -> 922.25 | H97: Sent | I97: Mercury Checking xx9122 | J97: Send Money transaction initiated on Mercury | K97: From Stars Flying Inc via mercury.com IDC FEE | L97: IDC FEE | R97: 45910.524
A98: 45910 | B98: 2025 | C98: 10 | D98: AUS MERCHANT SERVICES, INC | E98: 980 | F98: =IF(E98>0,E98*1,0) -> 980 | G98: =IF(E98<0,E98*-1,0) -> 0 | H98: Sent | I98: Mercury Checking xx9122 | K98: PAYING OVERSEAS SUPPLIERS | R98: 45910.501
A99: 45698 | B99: 2025 | C99: 10 | D99: Ovhcloud | E99: -34 | F99: =IF(E99>0,E99*1,0) -> 0 | G99: =IF(E99<0,E99*-1,0) -> 34 | H99: Sent | I99: Mercury Checking xx9122 | J99: OVHcloud | M99: 9884 | N99: Ovise Case | O99: Software | R99: 45698.082 | S99: USD
A100: 45667 | B100: 2025 | C100: 10 | D100: Tencent | E100: -0.01 | F100: =IF(E100>0,E100*1,0) -> 0 | G100: =IF(E100<0,E100*-1,0) -> 0.01 | H100: Sent | I100: Mercury Checking xx9122 | J100: Tencent Cloud | M100: 8690 | N100: XIANG JIAO | O100: Electronics | R100: 45667.142 | S100: USD
...

Sheet PayPal2025
A1: Date | B1: Y | C1: M | D1: Time | E1: TimeZone | F1: Name | G1: Type | H1: Status | I1: Currency | J1: Gross | K1: Fee | L1: Net | M1: IN | N1: OUT | O1: Transaction ID | P1: Balance
A2: 45658 | B2: 2025 | C2: 1 | D2: 0.1406713 | E2: PST | F2: Lustig Jessy | G2: 网站付款 | H2: 已完成 | I2: USD | J2: 20.25 | K2: -1.5 | L2: 18.75 | M2: =IF(L2>0,L2,0) -> 18.75 | N2: =IF(L2<0,L2,0)*-1 -> 0 | O2: 5NN567791J961805J | P2: 824.79
A3: 45658 | B3: 2025 | C3: 1 | D3: 0.24979167 | E3: PST | F3: 明杰 盛 | G3: 定期付款 | H3: 已完成 | I3: USD | J3: 20.25 | K3: -1.5 | L3: 18.75 | M3: =IF(L3>0,L3,0) -> 18.75 | N3: =IF(L3<0,L3,0)*-1 -> 0 | O3: 7GU22998TH945710T | P3: 843.54
A4: 45658 | B4: 2025 | C4: 1 | D4: 0.42976852 | E4: PST | F4: Shengche Lin | G4: 网站付款 | H4: 已完成 | I4: USD | J4: 20.25 | K4: -1.2 | L4: 19.05 | M4: =IF(L4>0,L4,0) -> 19.05 | N4: =IF(L4<0,L4,0)*-1 -> 0 | O4: 0D416666A9629534V | P4: 862.59
A5: 45658 | B5: 2025 | C5: 1 | D5: 0.61780093 | E5: PST | F5: shu sheng | G5: 网站付款 | H5: 已完成 | I5: USD | J5: 20.25 | K5: -1.5 | L5: 18.75 | M5: =IF(L5>0,L5,0) -> 18.75 | N5: =IF(L5<0,L5,0)*-1 -> 0 | O5: 6DN09443A2395982X | P5: 881.34
A6: 45661 | B6: 2025 | C6: 1 | D6: 0.15452546 | E6: PST | F6: Coa Pac | G6: 定期付款 | H6: 已完成 | I6: USD | J6: 11.99 | K6: -0.91 | L6: 11.08 | M6: =IF(L6>0,L6,0) -> 11.08 | N6: =IF(L6<0,L6,0)*-1 -> 0 | O6: 6RY063221M9508732 | P6: 892.42
A7: 45661 | B7: 2025 | C7: 1 | D7: 0.20732639 | E7: PST | F7: zhuang wang | G7: 定期付款 | H7: 已完成 | I7: USD | J7: 23.99 | K7: -1.33 | L7: 22.66 | M7: =IF(L7>0,L7,0) -> 22.66 | N7: =IF(L7<0,L7,0)*-1 -> 0 | O7: 2JC26621MR463905F | P7: 915.08
A8: 45662 | B8: 2025 | C8: 1 | D8: 0.14756944 | E8: PST | F8: Ryan Kim | G8: 定期付款 | H8: 已完成 | I8: USD | J8: 4.99 | K8: -0.66 | L8: 4.33 | M8: =IF(L8>0,L8,0) -> 4.33 | N8: =IF(L8<0,L8,0)*-1 -> 0 | O8: 0S46609254646530E | P8: 919.41
A9: 45662 | B9: 2025 | C9: 1 | D9: 0.37520833 | E9: PST | G9: 用户发起的收款 | H9: 已完成 | I9: USD | J9: -500 | K9: 0 | L9: -500 | M9: =IF(L9>0,L9,0) -> 0 | N9: =IF(L9<0,L9,0)*-1 -> 500 | O9: 11918658BA516522P | P9: 419.41
A10: 45663 | B10: 2025 | C10: 1 | D10: 0.13030093 | E10: PST | F10: 宇 陈 | G10: 定期付款 | H10: 已完成 | I10: USD | J10: 4.99 | K10: -0.74 | L10: 4.25 | M10: =IF(L10>0,L10,0) -> 4.25 | N10: =IF(L10<0,L10,0)*-1 -> 0 | O10: 7FC79867RW773361X | P10: 423.66
A11: 45663 | B11: 2025 | C11: 1 | D11: 0.14759259 | E11: PST | F11: JIANWEN PENG | G11: 定期付款 | H11: 已完成 | I11: USD | J11: 2.99 | K11: -0.64 | L11: 2.35 | M11: =IF(L11>0,L11,0) -> 2.35 | N11: =IF(L11<0,L11,0)*-1 -> 0 | O11: 47W20796YF363925D | P11: 426.01
A12: 45663 | B12: 2025 | C12: 1 | D12: 0.33469907 | E12: PST | F12: PayPal | G12: 冻结余额以调查争议 | H12: 待处理 | I12: USD | J12: -2.35 | K12: 0 | L12: -2.35 | M12: =IF(L12>0,L12,0) -> 0 | N12: =IF(L12<0,L12,0)*-1 -> 2.35 | O12: 4R026402SJ4863157 | P12: 423.66
A13: 45663 | B13: 2025 | C13: 1 | D13: 0.34497685 | E13: PST | F13: PayPal | G13: 退单 | H13: 已完成 | I13: USD | J13: -2.99 | K13: 0 | L13: -2.99 | M13: =IF(L13>0,L13,0) -> 0 | N13: =IF(L13<0,L13,0)*-1 -> 2.99 | O13: 01F45106WR374003K | P13: 420.67
A14: 45663 | B14: 2025 | C14: 1 | D14: 0.34497685 | E14: PST | F14: PayPal | G14: 取消冻结以解决争议 | H14: 被拒绝 | I14: USD | J14: 2.35 | K14: 0 | L14: 2.35 | M14: =IF(L14>0,L14,0) -> 2.35 | N14: =IF(L14<0,L14,0)*-1 -> 0 | O14: 4R026402SJ4863157 | P14: 423.02
A15: 45663 | B15: 2025 | C15: 1 | D15: 0.71525463 | E15: PST | F15: PayPal | G15: 冻结余额以调查争议 | H15: 待处理 | I15: USD | J15: -4.25 | K15: 0 | L15: -4.25 | M15: =IF(L15>0,L15,0) -> 0 | N15: =IF(L15<0,L15,0)*-1 -> 4.25 | O15: 73509792698077259 | P15: 418.77
A16: 45663 | B16: 2025 | C16: 1 | D16: 0.85825231 | E16: PST | F16: chong yang | G16: 定期付款 | H16: 已完成 | I16: USD | J16: 1.09 | K16: -0.53 | L16: 0.56 | M16: =IF(L16>0,L16,0) -> 0.56 | N16: =IF(L16<0,L16,0)*-1 -> 0 | O16: 0A845910FC111801M | P16: 419.33
A17: 45663 | B17: 2025 | C17: 1 | D17: 0.86299769 | E17: PST | F17: PayPal | G17: 退单 | H17: 已完成 | I17: USD | J17: -4.99 | K17: 0 | L17: -4.99 | M17: =IF(L17>0,L17,0) -> 0 | N17: =IF(L17<0,L17,0)*-1 -> 4.99 | O17: 5U414574VP812392T | P17: 414.34
A18: 45663 | B18: 2025 | C18: 1 | D18: 0.86299769 | E18: PST | F18: PayPal | G18: 取消冻结以解决争议 | H18: 被拒绝 | I18: USD | J18: 4.25 | K18: 0 | L18: 4.25 | M18: =IF(L18>0,L18,0) -> 4.25 | N18: =IF(L18<0,L18,0)*-1 -> 0 | O18: 73509792698077259 | P18: 418.59
A19: 45664 | B19: 2025 | C19: 1 | D19: 0.85465278 | E19: PST | F19: Ryan Kim | G19: 付款退款 | H19: 已完成 | I19: USD | J19: -4.99 | K19: 0.17 | L19: -4.82 | M19: =IF(L19>0,L19,0) -> 0 | N19: =IF(L19<0,L19,0)*-1 -> 4.82 | O19: 5NK3273144414422F | P19: 413.77
A20: 45665 | B20: 2025 | C20: 1 | D20: 0.96483796 | E20: PST | F20: 枝光 真優 | G20: 网站付款 | H20: 已完成 | I20: USD | J20: 2.49 | K20: -0.61 | L20: 1.88 | M20: =IF(L20>0,L20,0) -> 1.88 | N20: =IF(L20<0,L20,0)*-1 -> 0 | O20: 2NF44876692074450 | P20: 415.65
A21: 45665 | B21: 2025 | C21: 1 | D21: 0.99644676 | E21: PST | F21: 枝光 真優 | G21: 付款退款 | H21: 已完成 | I21: USD | J21: -2.49 | K21: 0.12 | L21: -2.37 | M21: =IF(L21>0,L21,0) -> 0 | N21: =IF(L21<0,L21,0)*-1 -> 2.37 | O21: 4T260464W89374408 | P21: 413.28
... A57: 45696 | B57: 2025 | C57: 2 | D57: 0.9265625 | E57: PST | F57: Ryan Kim | G57: 付款退款 | H57: 已完成 | I57: USD | J57: -4.99 | K57: 0.17 | L57: -4.82 | M57: =IF(L57>0,L57,0) -> 0 | N57: =IF(L57<0,L57,0)*-1 -> 4.82 | O57: 7LY15274FN919084H | P57: 784.56
A58: 45696 | B58: 2025 | C58: 2 | D58: 0.96342593 | E58: PST | G58: 争议费 | H58: 已完成 | I58: USD | J58: -15 | K58: 0 | L58: -15 | M58: =IF(L58>0,L58,0) -> 0 | N58: =IF(L58<0,L58,0)*-1 -> 15 | O58: 9CA59849X66857532 | P58: 769.56
A59: 45696 | B59: 2025 | C59: 2 | D59: 0.9634375 | E59: PST | F59: PayPal | G59: 退单 | H59: 已完成 | I59: USD | J59: -35.99 | K59: 0 | L59: -35.99 | M59: =IF(L59>0,L59,0) -> 0 | N59: =IF(L59<0,L59,0)*-1 -> 35.99 | O59: 79K953502H018482H | P59: 733.57
A60: 45696 | B60: 2025 | C60: 2 | D60: 0.9634375 | E60: PST | F60: PayPal | G60: 取消冻结以解决争议 | H60: 被拒绝 | I60: USD | J60: 34.24 | K60: 0 | L60: 34.24 | M60: =IF(L60>0,L60,0) -> 34.24 | N60: =IF(L60<0,L60,0)*-1 -> 0 | O60: 5KT7877346451643R | P60: 767.81
A61: 45698 | B61: 2025 | C61: 2 | D61: 0.38609954 | E61: PST | F61: 程 常 | G61: 定期付款 | H61: 已完成 | I61: USD | J61: 20.25 | K61: -1.5 | L61: 18.75 | M61: =IF(L61>0,L61,0) -> 18.75 | N61: =IF(L61<0,L61,0)*-1 -> 0 | O61: 05H76178LW7354158 | P61: 786.56
A62: 45698 | B62: 2025 | C62: 2 | D62: 0.9737037 | E62: PST | F62: YIFAN SHI | G62: 网站付款 | H62: 已完成 | I62: USD | J62: 23.99 | K62: -1.69 | L62: 22.3 | M62: =IF(L62>0,L62,0) -> 22.3 | N62: =IF(L62<0,L62,0)*-1 -> 0 | O62: 87875665PT1232259 | P62: 808.86
A63: 45699 | B63: 2025 | C63: 2 | D63: 0.43604167 | E63: PST | G63: 用户发起的收款 | H63: 已完成 | I63: USD | J63: -500 | K63: 0 | L63: -500 | M63: =IF(L63>0,L63,0) -> 0 | N63: =IF(L63<0,L63,0)*-1 -> 500 | O63: 76Y52904PY775982W | P63: 308.86
A64: 45700 | B64: 2025 | C64: 2 | D64: 0.88635417 | E64: PST | F64: Zhenyu Qiao | G64: 网站付款 | H64: 已完成 | I64: USD | J64: 20.25 | K64: -1.2 | L64: 19.05 | M64: =IF(L64>0,L64,0) -> 19.05 | N64: =IF(L64<0,L64,0)*-1 -> 0 | O64: 13X24647AK328224V | P64: 327.91
A65: 45701 | B65: 2025 | C65: 2 | D65: 0.98634259 | E65: PST | F65: 广生 林 | G65: 定期付款 | H65: 已完成 | I65: USD | J65: 0.93 | K65: -0.54 | L65: 0.39 | M65: =IF(L65>0,L65,0) -> 0.39 | N65: =IF(L65<0,L65,0)*-1 -> 0 | O65: 0H290001XG6149442 | P65: 328.3
A66: 45702 | B66: 2025 | C66: 2 | D66: 0.040162037 | E66: PST | F66: 广生 林 | G66: 定期付款 | H66: 已完成 | I66: USD | J66: 3.99 | K66: -0.69 | L66: 3.3 | M66: =IF(L66>0,L66,0) -> 3.3 | N66: =IF(L66<0,L66,0)*-1 -> 0 | O66: 73T8750287591393R | P66: 331.6
A67: 45702 | B67: 2025 | C67: 2 | D67: 0.041493056 | E67: PST | F67: Namecheap, Inc | G67: 快速结账付款 | H67: 已完成 | I67: USD | J67: -11.66 | K67: 0 | L67: -11.66 | M67: =IF(L67>0,L67,0) -> 0 | N67: =IF(L67<0,L67,0)*-1 -> 11.66 | O67: 3K1926827D397541B | P67: 319.94
A68: 45704 | B68: 2025 | C68: 2 | D68: 0.14650463 | E68: PST | F68: Junjie Xiao | G68: 定期付款 | H68: 已完成 | I68: USD | J68: 1.09 | K68: -0.54 | L68: 0.55 | M68: =IF(L68>0,L68,0) -> 0.55 | N68: =IF(L68<0,L68,0)*-1 -> 0 | O68: 24Y40503T0285030A | P68: 320.49
A69: 45705 | B69: 2025 | C69: 2 | D69: 0.85055556 | E69: PST | F69: Tuchman Aridia | G69: 定期付款 | H69: 已完成 | I69: USD | J69: 20.25 | K69: -1.5 | L69: 18.75 | M69: =IF(L69>0,L69,0) -> 18.75 | N69: =IF(L69<0,L69,0)*-1 -> 0 | O69: 5PT170152T050554W | P69: 339.24
A70: 45707 | B70: 2025 | C70: 2 | D70: 0.030601852 | E70: PST | F70: Jugran Sureka | G70: 网站付款 | H70: 已完成 | I70: USD | J70: 115.19 | K70: -6.24 | L70: 108.95 | M70: =IF(L70>0,L70,0) -> 108.95 | N70: =IF(L70<0,L70,0)*-1 -> 0 | O70: 3XP526149C9025608 | P70: 448.19
A71: 45708 | B71: 2025 | C71: 2 | D71: 0.22570602 | E71: PST | F71: 翔 梁 | G71: 网站付款 | H71: 已完成 | I71: USD | J71: 8.39 | K71: -0.91 | L71: 7.48 | M71: =IF(L71>0,L71,0) -> 7.48 | N71: =IF(L71<0,L71,0)*-1 -> 0 | O71: 8BH27129SJ672351V | P71: 455.67
A72: 45708 | B72: 2025 | C72: 2 | D72: 0.42359954 | E72: PST | F72: junwu chen | G72: 定期付款 | H72: 已完成 | I72: USD | J72: 8.4 | K72: -0.78 | L72: 7.62 | M72: =IF(L72>0,L72,0) -> 7.62 | N72: =IF(L72<0,L72,0)*-1 -> 0 | O72: 8SA15316EE6282820 | P72: 463.29
A73: 45709 | B73: 2025 | C73: 2 | D73: 0.14020833 | E73: PST | F73: SHENG CHUANLONG | G73: 定期付款 | H73: 已完成 | I73: USD | J73: 4.99 | K73: -0.74 | L73: 4.25 | M73: =IF(L73>0,L73,0) -> 4.25 | N73: =IF(L73<0,L73,0)*-1 -> 0 | O73: 8BJ206916B618903T | P73: 467.54
A74: 45709 | B74: 2025 | C74: 2 | D74: 0.28217593 | E74: PST | F74: 广生 林 | G74: 网站付款 | H74: 已完成 | I74: USD | J74: 4 | K74: -0.69 | L74: 3.31 | M74: =IF(L74>0,L74,0) -> 3.31 | N74: =IF(L74<0,L74,0)*-1 -> 0 | O74: 8CT65871LH383173E | P74: 470.85
A75: 45709 | B75: 2025 | C75: 2 | D75: 0.36858796 | E75: PST | F75: tof dao | G75: 网站付款 | H75: 已完成 | I75: USD | J75: 8.39 | K75: -0.91 | L75: 7.48 | M75: =IF(L75>0,L75,0) -> 7.48 | N75: =IF(L75<0,L75,0)*-1 -> 0 | O75: 3US37306AT524140B | P75: 478.33
... A88: 45994 | B88: 2025 | C88: 3 | D88: 0.33708333 | E88: PDT | F88: Namecheap, Inc | G88: 快速结账付款 | H88: 已完成 | I88: USD | J88: -7.98 | K88: 0 | L88: -7.98 | M88: =IF(L88>0,L88,0) -> 0 | N88: =IF(L88<0,L88,0)*-1 -> 7.98 | O88: 0V151768RJ692201B | P88: 529.86
A89: 3/14/2025 | B89: 2025 | C89: 3 | D89: 0.12450231 | E89: PDT | F89: TVIMI | G89: 网站付款 | H89: 已完成 | I89: USD | J89: 2.99 | K89: -0.64 | L89: 2.35 | M89: =IF(L89>0,L89,0) -> 2.35 | N89: =IF(L89<0,L89,0)*-1 -> 0 | O89: 6DT033823H173751B | P89: 532.21
A90: 3/16/2025 | B90: 2025 | C90: 3 | D90: 0.15543981 | E90: PDT | F90: Junjie Xiao | G90: 定期付款 | H90: 已完成 | I90: USD | J90: 1.09 | K90: -0.54 | L90: 0.55 | M90: =IF(L90>0,L90,0) -> 0.55 | N90: =IF(L90<0,L90,0)*-1 -> 0 | O90: 0TG651076G025183G | P90: 532.76
A91: 3/16/2025 | B91: 2025 | C91: 3 | D91: 0.35859954 | E91: PDT | F91: TENG WEI JIE | G91: 定期付款 | H91: 已完成 | I91: USD | J91: 4.79 | K91: -0.66 | L91: 4.13 | M91: =IF(L91>0,L91,0) -> 4.13 | N91: =IF(L91<0,L91,0)*-1 -> 0 | O91: 30H22762JF9716011 | P91: 536.89
A92: 3/17/2025 | B92: 2025 | C92: 3 | D92: 0.084791667 | E92: PDT | F92: Jianji Ren | G92: 网站付款 | H92: 已完成 | I92: USD | J92: 20.25 | K92: -1.2 | L92: 19.05 | M92: =IF(L92>0,L92,0) -> 19.05 | N92: =IF(L92<0,L92,0)*-1 -> 0 | O92: 52F64606DC091081C | P92: 555.94
A93: 3/17/2025 | B93: 2025 | C93: 3 | D93: 0.30180556 | E93: PDT | F93: TENG WEI JIE | G93: 定期付款 | H93: 已完成 | I93: USD | J93: 15.46 | K93: -1.03 | L93: 14.43 | M93: =IF(L93>0,L93,0) -> 14.43 | N93: =IF(L93<0,L93,0)*-1 -> 0 | O93: 31234934HD782321G | P93: 570.37
A94: 3/17/2025 | B94: 2025 | C94: 3 | D94: 0.30990741 | E94: PDT | F94: Jianji Ren | G94: 付款退款 | H94: 已完成 | I94: USD | J94: -19.25 | K94: 0.68 | L94: -18.57 | M94: =IF(L94>0,L94,0) -> 0 | N94: =IF(L94<0,L94,0)*-1 -> 18.57 | O94: 6PN08508HT241354J | P94: 551.8
A95: 3/21/2025 | B95: 2025 | C95: 3 | D95: 0.19188657 | E95: PDT | F95: SHENG CHUANLONG | G95: 定期付款 | H95: 已完成 | I95: USD | J95: 4.99 | K95: -0.74 | L95: 4.25 | M95: =IF(L95>0,L95,0) -> 4.25 | N95: =IF(L95<0,L95,0)*-1 -> 0 | O95: 2FR74113NP315884H | P95: 556.05
A96: 3/22/2025 | B96: 2025 | C96: 3 | D96: 0.073541667 | E96: PDT | F96: ZOHO DISTRIBUTION CORP | G96: 预先批准付款账单用户付款 | H96: 已完成 | I96: USD | J96: -2.5 | K96: 0 | L96: -2.5 | M96: =IF(L96>0,L96,0) -> 0 | N96: =IF(L96<0,L96,0)*-1 -> 2.5 | O96: 6474368707715852V | P96: 553.55
A97: 3/23/2025 | B97: 2025 | C97: 3 | D97: 0.18055556 | E97: PDT | F97: Pengfei Li | G97: 网站付款 | H97: 已完成 | I97: USD | J97: 8.39 | K97: -0.91 | L97: 7.48 | M97: =IF(L97>0,L97,0) -> 7.48 | N97: =IF(L97<0,L97,0)*-1 -> 0 | O97: 46431410JC712672X | P97: 561.03
A98: 3/23/2025 | B98: 2025 | C98: 3 | D98: 0.18203704 | E98: PDT | F98: 广生 林 | G98: 定期付款 | H98: 已完成 | I98: USD | J98: 1.99 | K98: -0.59 | L98: 1.4 | M98: =IF(L98>0,L98,0) -> 1.4 | N98: =IF(L98<0,L98,0)*-1 -> 0 | O98: 7HX361560M700900K | P98: 562.43
A99: 3/30/2025 | B99: 2025 | C99: 3 | D99: 0.15340278 | E99: PDT | F99: 梓豪 李 | G99: 定期付款 | H99: 已完成 | I99: USD | J99: 1.09 | K99: -0.54 | L99: 0.55 | M99: =IF(L99>0,L99,0) -> 0.55 | N99: =IF(L99<0,L99,0)*-1 -> 0 | O99: 92U962487A035740G | P99: 562.98
A100: 45661 | B100: 2025 | C100: 4 | D100: 0.24883102 | E100: PDT | F100: 海波 梅 | G100: 网站付款 | H100: 已完成 | I100: USD | J100: 1.19 | K100: -0.55 | L100: 0.64 | M100: =IF(L100>0,L100,0) -> 0.64 | N100: =IF(L100<0,L100,0)*-1 -> 0 | O100: 35E52896SR812432F | P100: 563.62
A101: 45661 | B101: 2025 | C101: 4 | D101: 0.46396991 | E101: PDT | F101: Shengche Lin | G101: 网站付款 | H101: 已完成 | I101: USD | J101: 25.25 | K101: -1.37 | L101: 23.88 | M101: =IF(L101>0,L101,0) -> 23.88 | N101: =IF(L101<0,L101,0)*-1 -> 0 | O101: 2LN92175R88870431 | P101: 587.5
A102: 45692 | B102: 2025 | C102: 4 | D102: 0.75805556 | E102: PDT | F102: Jack Ma | G102: 网站付款 | H102: 已完成 | I102: USD | J102: 5.99 | K102: -0.7 | L102: 5.29 | M102: =IF(L102>0,L102,0) -> 5.29 | N102: =IF(L102<0,L102,0)*-1 -> 0 | O102: 4XR62373PJ534752X | P102: 592.79
A103: 45751 | B103: 2025 | C103: 4 | D103: 0.17488426 | E103: PDT | F103: Coa Pac | G103: 定期付款 | H103: 已完成 | I103: USD | J103: 11.99 | K103: -0.91 | L103: 11.08 | M103: =IF(L103>0,L103,0) -> 11.08 | N103: =IF(L103<0,L103,0)*-1 -> 0 | O103: 1VM32948GV9286159 | P103: 603.87
A104: 45781 | B104: 2025 | C104: 4 | D104: 0.17167824 | E104: PDT | F104: Wang Hin Wong | G104: 定期付款 | H104: 已完成 | I104: USD | J104: 1.09 | K104: -0.54 | L104: 0.55 | M104: =IF(L104>0,L104,0) -> 0.55 | N104: =IF(L104<0,L104,0)*-1 -> 0 | O104: 31B86187PX404010A | P104: 604.42
A105: 45781 | B105: 2025 | C105: 4 | D105: 0.69822917 | E105: PDT | F105: 唐瑞 楊 | G105: 网站付款 | H105: 已完成 | I105: USD | J105: 2.79 | K105: -0.63 | L105: 2.16 | M105: =IF(L105>0,L105,0) -> 2.16 | N105: =IF(L105<0,L105,0)*-1 -> 0 | O105: 08T615297C7990336 | P105: 606.58
A106: 45781 | B106: 2025 | C106: 4 | D106: 0.73487269 | E106: PDT | F106: yuhang zhao | G106: 定期付款 | H106: 已完成 | I106: USD | J106: 4.19 | K106: -0.64 | L106: 3.55 | M106: =IF(L106>0,L106,0) -> 3.55 | N106: =IF(L106<0,L106,0)*-1 -> 0 | O106: 5MD41184Y8131223V | P106: 610.13
A107: 45781 | B107: 2025 | C107: 4 | D107: 0.75798611 | E107: PDT | F107: yuhang zhao | G107: 定期付款 | H107: 已完成 | I107: USD | J107: 4.89 | K107: -0.66 | L107: 4.23 | M107: =IF(L107>0,L107,0) -> 4.23 | N107: =IF(L107<0,L107,0)*-1 -> 0 | O107: 7D898945XX733322E | P107: 614.36
A108: 45812 | B108: 2025 | C108: 4 | D108: 0.15707176 | E108: PDT | F108: chong yang | G108: 定期付款 | H108: 已完成 | I108: USD | J108: 1.09 | K108: -0.53 | L108: 0.56 | M108: =IF(L108>0,L108,0) -> 0.56 | N108: =IF(L108<0,L108,0)*-1 -> 0 | O108: 7SK87616YD3045606 | P108: 614.92
A109: 45842 | B109: 2025 | C109: 4 | D109: 0.098136574 | E109: PDT | F109: 广生 林 | G109: 定期付款 | H109: 已完成 | I109: USD | J109: 3.99 | K109: -0.69 | L109: 3.3 | M109: =IF(L109>0,L109,0) -> 3.3 | N109: =IF(L109<0,L109,0)*-1 -> 0 | O109: 5T101329XN019445M | P109: 618.22
A110: 45842 | B110: 2025 | C110: 4 | D110: 0.099421296 | E110: PDT | F110: 广生 林 | G110: 定期付款 | H110: 已完成 | I110: USD | J110: 3.99 | K110: -0.69 | L110: 3.3 | M110: =IF(L110>0,L110,0) -> 3.3 | N110: =IF(L110<0,L110,0)*-1 -> 0 | O110: 4VE00729PW978901P | P110: 621.52
A111: 45934 | B111: 2025 | C111: 4 | D111: 0.17135417 | E111: PDT | F111: 梦鑫 李 | G111: 定期付款 | H111: 已完成 | I111: USD | J111: 4.79 | K111: -0.73 | L111: 4.06 | M111: =IF(L111>0,L111,0) -> 4.06 | N111: =IF(L111<0,L111,0)*-1 -> 0 | O111: 8T5366628W7922821 | P111: 625.58
A112: 45995 | B112: 2025 | C112: 4 | D112: 0.24685185 | E112: PDT | F112: 京浔 蒋 | G112: 定期付款 | H112: 已完成 | I112: USD | J112: 1.98 | K112: -0.59 | L112: 1.39 | M112: =IF(L112>0,L112,0) -> 1.39 | N112: =IF(L112<0,L112,0)*-1 -> 0 | O112: 26268011T41640503 | P112: 626.97
A113: 4/13/2025 | B113: 2025 | C113: 4 | D113: 0.29361111 | E113: PDT | F113: 展 梅 | G113: 定期付款 | H113: 已完成 | I113: USD | J113: 20.25 | K113: -1.5 | L113: 18.75 | M113: =IF(L113>0,L113,0) -> 18.75 | N113: =IF(L113<0,L113,0)*-1 -> 0 | O113: 3UN66064A3976431Y | P113: 645.72
A114: 4/13/2025 | B114: 2025 | C114: 4 | D114: 0.29561343 | E114: PDT | F114: 展 梅 | G114: 定期付款 | H114: 已完成 | I114: USD | J114: 20.25 | K114: -1.5 | L114: 18.75 | M114: =IF(L114>0,L114,0) -> 18.75 | N114: =IF(L114<0,L114,0)*-1 -> 0 | O114: 3TY71808KE963014Y | P114: 664.47
A115: 4/16/2025 | B115: 2025 | C115: 4 | D115: 0.15402778 | E115: PDT | F115: Junjie Xiao | G115: 定期付款 | H115: 已完成 | I115: USD | J115: 1.09 | K115: -0.54 | L115: 0.55 | M115: =IF(L115>0,L115,0) -> 0.55 | N115: =IF(L115<0,L115,0)*-1 -> 0 | O115: 7U217655UT783890C | P115: 665.02
A116: 4/16/2025 | B116: 2025 | C116: 4 | D116: 0.15511574 | E116: PDT | F116: TENG WEI JIE | G116: 定期付款 | H116: 已完成 | I116: USD | J116: 4.79 | K116: -0.66 | L116: 4.13 | M116: =IF(L116>0,L116,0) -> 4.13 | N116: =IF(L116<0,L116,0)*-1 -> 0 | O116: 55599408EN535680R | P116: 669.15
A117: 4/16/2025 | B117: 2025 | C117: 4 | D117: 0.37971065 | E117: PDT | F117: TENG WEI JIE | G117: 付款退款 | H117: 已完成 | I117: USD | J117: -4.79 | K117: 0.17 | L117: -4.62 | M117: =IF(L117>0,L117,0) -> 0 | N117: =IF(L117<0,L117,0)*-1 -> 4.62 | O117: 6TF53153WH278004M | P117: 664.53
A118: 4/16/2025 | B118: 2025 | C118: 4 | D118: 0.48674769 | E118: PDT | F118: ZOHO DISTRIBUTION CORP | G118: 预先批准付款账单用户付款 | H118: 已完成 | I118: USD | J118: -2.5 | K118: 0 | L118: -2.5 | M118: =IF(L118>0,L118,0) -> 0 | N118: =IF(L118<0,L118,0)*-1 -> 2.5 | O118: 9BX96288L48108504 | P118: 662.03
A119: 4/20/2025 | B119: 2025 | C119: 4 | D119: 0.31640046 | E119: PDT | F119: xin zhu | G119: 网站付款 | H119: 已完成 | I119: USD | J119: 3.99 | K119: -0.69 | L119: 3.3 | M119: =IF(L119>0,L119,0) -> 3.3 | N119: =IF(L119<0,L119,0)*-1 -> 0 | O119: 9UG74009MJ814782V | P119: 665.33
A120: 4/20/2025 | B120: 2025 | C120: 4 | D120: 0.83980324 | E120: PDT | F120: xin zhu | G120: 付款退款 | H120: 已完成 | I120: USD | J120: -3.99 | K120: 0.2 | L120: -3.79 | M120: =IF(L120>0,L120,0) -> 0 | N120: =IF(L120<0,L120,0)*-1 -> 3.79 | O120: 0BC96594B8246535C | P120: 661.54
A121: 4/21/2025 | B121: 2025 | C121: 4 | D121: 0.15789352 | E121: PDT | F121: SHENG CHUANLONG | G121: 定期付款 | H121: 已完成 | I121: USD | J121: 4.99 | K121: -0.74 | L121: 4.25 | M121: =IF(L121>0,L121,0) -> 4.25 | N121: =IF(L121<0,L121,0)*-1 -> 0 | O121: 75D90675E5979404C | P121: 665.79
A122: 4/21/2025 | B122: 2025 | C122: 4 | D122: 0.96042824 | E122: PDT | F122: twitch頻道 | G122: 网站付款 | H122: 已完成 | I122: USD | J122: 2.99 | K122: -0.64 | L122: 2.35 | M122: =IF(L122>0,L122,0) -> 2.35 | N122: =IF(L122<0,L122,0)*-1 -> 0 | O122: 9NV81617NJ824012F | P122: 668.14
A123: 4/22/2025 | B123: 2025 | C123: 4 | D123: 0.62471065 | E123: PDT | F123: 镇玮 田 | G123: 定期付款 | H123: 已完成 | I123: USD | J123: 3.99 | K123: -0.69 | L123: 3.3 | M123: =IF(L123>0,L123,0) -> 3.3 | N123: =IF(L123<0,L123,0)*-1 -> 0 | O123: 2RU50559EU536013J | P123: 671.44
A124: 4/26/2025 | B124: 2025 | C124: 4 | D124: 0.89140046 | E124: PDT | F124: xin zhu | G124: 网站付款 | H124: 已完成 | I124: USD | J124: 6.99 | K124: -0.84 | L124: 6.15 | M124: =IF(L124>0,L124,0) -> 6.15 | N124: =IF(L124<0,L124,0)*-1 -> 0 | O124: 88313786SF848363K | P124: 677.59
A125: 4/27/2025 | B125: 2025 | C125: 4 | D125: 0.37259259 | E125: PDT | F125: Hoa Le | G125: 定期付款 | H125: 已完成 | I125: USD | J125: 3.99 | K125: -0.69 | L125: 3.3 | M125: =IF(L125>0,L125,0) -> 3.3 | N125: =IF(L125<0,L125,0)*-1 -> 0 | O125: 1PK23623X3515174D | P125: 680.89
A126: 45662 | B126: 2025 | C126: 5 | D126: 0.38413194 | E126: PDT | F126: 海波 梅 | G126: 网站付款 | H126: 已完成 | I126: USD | J126: 1.19 | K126: -0.55 | L126: 0.64 | M126: =IF(L126>0,L126,0) -> 0.64 | N126: =IF(L126<0,L126,0)*-1 -> 0 | O126: 9N6124498P795914B | P126: 681.53
A127: 45721 | B127: 2025 | C127: 5 | D127: 0.13884259 | E127: PDT | F127: Jack Ma | G127: 网站付款 | H127: 已完成 | I127: USD | J127: 5.99 | K127: -0.7 | L127: 5.29 | M127: =IF(L127>0,L127,0) -> 5.29 | N127: =IF(L127<0,L127,0)*-1 -> 0 | O127: 74F550128L492145D | P127: 686.82
A128: 45721 | B128: 2025 | C128: 5 | D128: 0.18898148 | E128: PDT | F128: 杨长江 | G128: 定期付款 | H128: 已完成 | I128: USD | J128: 2.79 | K128: -0.63 | L128: 2.16 | M128: =IF(L128>0,L128,0) -> 2.16 | N128: =IF(L128<0,L128,0)*-1 -> 0 | O128: 9CU96548MG812833C | P128: 688.98
A129: 45782 | B129: 2025 | C129: 5 | D129: 0.16841435 | E129: PDT | F129: Wang Hin Wong | G129: 定期付款 | H129: 已完成 | I129: USD | J129: 1.09 | K129: -0.54 | L129: 0.55 | M129: =IF(L129>0,L129,0) -> 0.55 | N129: =IF(L129<0,L129,0)*-1 -> 0 | O129: 4FT62371FB288104J | P129: 689.53
A130: 45813 | B130: 2025 | C130: 5 | D130: 0.47611111 | E130: PDT | F130: BunnyWay d.o.o. | G130: 预先批准付款账单用户付款 | H130: 已完成 | I130: USD | J130: -10 | K130: 0 | L130: -10 | M130: =IF(L130>0,L130,0) -> 0 | N130: =IF(L130<0,L130,0)*-1 -> 10 | O130: 31848732L5773105P | P130: 679.53
A131: 45813 | B131: 2025 | C131: 5 | D131: 0.75696759 | E131: PDT | F131: xin zhu | G131: 定期付款 | H131: 已完成 | I131: USD | J131: 18.26 | K131: -1.4 | L131: 16.86 | M131: =IF(L131>0,L131,0) -> 16.86 | N131: =IF(L131<0,L131,0)*-1 -> 0 | O131: 59H628962S2003321 | P131: 696.39
A132: 5/14/2025 | B132: 2025 | C132: 5 | D132: 0.086631944 | E132: PDT | F132: 震楷 凌 | G132: 网站付款 | H132: 已完成 | I132: USD | J132: 5.49 | K132: -0.76 | L132: 4.73 | M132: =IF(L132>0,L132,0) -> 4.73 | N132: =IF(L132<0,L132,0)*-1 -> 0 | O132: 6NN49629C7072505A | P132: 701.12
A133: 5/14/2025 | B133: 2025 | C133: 5 | D133: 0.21527778 | E133: PDT | F133: xin zhu | G133: 定期付款 | H133: 已完成 | I133: USD | J133: 5.99 | K133: -0.79 | L133: 5.2 | M133: =IF(L133>0,L133,0) -> 5.2 | N133: =IF(L133<0,L133,0)*-1 -> 0 | O133: 97E838489U198582J | P133: 706.32
A134: 5/14/2025 | B134: 2025 | C134: 5 | D134: 0.34408565 | E134: PDT | F134: chong yang | G134: 网站付款 | H134: 已完成 | I134: USD | J134: 1.09 | K134: -0.53 | L134: 0.56 | M134: =IF(L134>0,L134,0) -> 0.56 | N134: =IF(L134<0,L134,0)*-1 -> 0 | O134: 5G8760584U913813B | P134: 706.88
A135: 5/15/2025 | B135: 2025 | C135: 5 | D135: 0.18493056 | E135: PDT | F135: 梦鑫 李 | G135: 定期付款 | H135: 已完成 | I135: USD | J135: 4.79 | K135: -0.73 | L135: 4.06 | M135: =IF(L135>0,L135,0) -> 4.06 | N135: =IF(L135<0,L135,0)*-1 -> 0 | O135: 2SV813843Y3153545 | P135: 710.94
A136: 5/16/2025 | B136: 2025 | C136: 5 | D136: 0.16001157 | E136: PDT | F136: Junjie Xiao | G136: 定期付款 | H136: 已完成 | I136: USD | J136: 1.09 | K136: -0.54 | L136: 0.55 | M136: =IF(L136>0,L136,0) -> 0.55 | N136: =IF(L136<0,L136,0)*-1 -> 0 | O136: 9U315080EW928583X | P136: 711.49
A137: 5/16/2025 | B137: 2025 | C137: 5 | D137: 0.37478009 | E137: PDT | F137: xin zhu | G137: 网站付款 | H137: 已完成 | I137: USD | J137: 19.26 | K137: -1.45 | L137: 17.81 | M137: =IF(L137>0,L137,0) -> 17.81 | N137: =IF(L137<0,L137,0)*-1 -> 0 | O137: 7V389522KU183762K | P137: 729.3
A138: 5/16/2025 | B138: 2025 | C138: 5 | D138: 0.56358796 | E138: PDT | F138: ZOHO DISTRIBUTION CORP | G138: 预先批准付款账单用户付款 | H138: 已完成 | I138: USD | J138: -2.5 | K138: 0 | L138: -2.5 | M138: =IF(L138>0,L138,0) -> 0 | N138: =IF(L138<0,L138,0)*-1 -> 2.5 | O138: 3B506460N2125721T | P138: 726.8
A139: 5/19/2025 | B139: 2025 | C139: 5 | D139: 0.15969907 | E139: PDT | F139: Universal Reach Marketing Agency L.L.C-FZ | G139: 网站付款 | H139: 已完成 | I139: USD | J139: 24.99 | K139: -1.74 | L139: 23.25 | M139: =IF(L139>0,L139,0) -> 23.25 | N139: =IF(L139<0,L139,0)*-1 -> 0 | O139: 2KX3959800285744Y | P139: 750.05
A140: 5/19/2025 | B140: 2025 | C140: 5 | D140: 0.38630787 | E140: PDT | F140: 伟 黄 | G140: 网站付款 | H140: 已完成 | I140: USD | J140: 8.39 | K140: -0.91 | L140: 7.48 | M140: =IF(L140>0,L140,0) -> 7.48 | N140: =IF(L140<0,L140,0)*-1 -> 0 | O140: 6KV90616AV084750U | P140: 757.53
A141: 5/20/2025 | B141: 2025 | C141: 5 | D141: 0.19811343 | E141: PDT | F141: 雪强 史 | G141: 网站付款 | H141: 已完成 | I141: USD | J141: 8.39 | K141: -0.91 | L141: 7.48 | M141: =IF(L141>0,L141,0) -> 7.48 | N141: =IF(L141<0,L141,0)*-1 -> 0 | O141: 0Y473846SP5503802 | P141: 765.01
A142: 5/21/2025 | B142: 2025 | C142: 5 | D142: 0.14152778 | E142: PDT | F142: SHENG CHUANLONG | G142: 定期付款 | H142: 已完成 | I142: USD | J142: 4.99 | K142: -0.74 | L142: 4.25 | M142: =IF(L142>0,L142,0) -> 4.25 | N142: =IF(L142<0,L142,0)*-1 -> 0 | O142: 2BT55195E6229683Y | P142: 769.26
A143: 5/21/2025 | B143: 2025 | C143: 5 | D143: 0.78423611 | E143: PDT | F143: 梓豪 李 | G143: 定期付款 | H143: 已完成 | I143: USD | J143: 1.09 | K143: -0.54 | L143: 0.55 | M143: =IF(L143>0,L143,0) -> 0.55 | N143: =IF(L143<0,L143,0)*-1 -> 0 | O143: 9S204790VH8195941 | P143: 769.81
... A155: 5/31/2025 | B155: 2025 | C155: 5 | D155: 0.32189815 | E155: PDT | F155: 捷 汤 | G155: 定期付款 | H155: 已完成 | I155: USD | J155: 25.25 | K155: -1.75 | L155: 23.5 | M155: =IF(L155>0,L155,0) -> 23.5 | N155: =IF(L155<0,L155,0)*-1 -> 0 | O155: 1H123807DY018051Y | P155: 953.37
A156: 45722 | B156: 2025 | C156: 6 | D156: 0.15512731 | E156: America/Los_Angeles | F156: Hanwen Guo | G156: 网站付款 | I156: USD | J156: 5.99 | K156: -0.7 | L156: 5.29 | M156: =IF(L156>0,L156,0) -> 5.29 | N156: =IF(L156<0,L156,0)*-1 -> 0 | O156: 7VY142008W557842S | P156: 958.66
A157: 45722 | B157: 2025 | C157: 6 | D157: 0.18175926 | E157: America/Los_Angeles | F157: 杨长江 | G157: 定期付款 | I157: USD | J157: 2.79 | K157: -0.63 | L157: 2.16 | M157: =IF(L157>0,L157,0) -> 2.16 | N157: =IF(L157<0,L157,0)*-1 -> 0 | O157: 0CY16279MN618405E | P157: 960.82
A158: 45753 | B158: 2025 | C158: 6 | D158: 0.34475694 | E158: America/Los_Angeles | F158: GPLPackage | G158: 快速结账付款 | I158: USD | J158: -62 | K158: 0 | L158: -62 | M158: =IF(L158>0,L158,0) -> 0 | N158: =IF(L158<0,L158,0)*-1 -> 62 | O158: 3VU60510HN4340517 | P158: 898.82
...

Sheet USDT2025
A1: # | B1: 日期 | C1: 年 | D1: 月份 | E1: 对象 | F1: 类型 | G1: 描述 | H1: 收入 | I1: 支出 | J1: 结算否 | K1: 是否对帐 | L1: 结算总额 | M1: 结算日期 | N1: 结算银行 | O1: 备注
A2: 1 | B2: 45607 | C2: =YEAR(B2) -> 2024 | D2: =MONTH(B2) -> 11 | E2: NiiHost | F2: USDT | G2: 销售收入 | H2: 499.2897 | J2: 已结算 | K2: TRUE | L2: =SUM(H2:H15) -> 1452.3151 | M2: 45693 | N2: 水星银行SF | O2: 5笔USDT转换手续费 1.5x5
A3: 2 | B3: 45607 | C3: =YEAR(B3) -> 2024 | D3: =MONTH(B3) -> 11 | E3: NiiHost | F3: USDT | G3: 销售收入 | H3: 100 | J3: 已结算 | K3: TRUE | L3: 1452.3151 | M3: 45693 | N3: 水星银行SF | O3: 5笔USDT转换手续费 1.5x5
A4: 3 | B4: 45618 | C4: =YEAR(B4) -> 2024 | D4: =MONTH(B4) -> 11 | E4: NiiHost | F4: USDT | G4: 销售收入 | H4: 16.203 | J4: 已结算 | K4: TRUE | L4: 1452.3151 | M4: 45693 | N4: 水星银行SF | O4: 5笔USDT转换手续费 1.5x5
A5: 4 | B5: 45623 | C5: =YEAR(B5) -> 2024 | D5: =MONTH(B5) -> 11 | E5: NiiHost | F5: USDT | G5: 销售收入 | H5: 7.9986 | J5: 已结算 | K5: TRUE | L5: 1452.3151 | M5: 45693 | N5: 水星银行SF | O5: 5笔USDT转换手续费 1.5x5
A6: 5 | B6: 45624 | C6: =YEAR(B6) -> 2024 | D6: =MONTH(B6) -> 11 | E6: NiiHost | F6: USDT | G6: 销售收入 | H6: 12.589 | J6: 已结算 | K6: TRUE | L6: 1452.3151 | M6: 45693 | N6: 水星银行SF | O6: 5笔USDT转换手续费 1.5x5
A7: 6 | B7: 45625 | C7: =YEAR(B7) -> 2024 | D7: =MONTH(B7) -> 11 | E7: NiiHost | F7: USDT | G7: 销售收入 | H7: 7.2089 | J7: 已结算 | K7: TRUE | L7: 1452.3151 | M7: 45693 | N7: 水星银行SF | O7: 5笔USDT转换手续费 1.5x5
A8: 7 | B8: 45629 | C8: 2024 | D8: 12 | E8: NiiHost | F8: USDT | G8: 销售收入 | H8: 16.7572 | J8: 已结算 | K8: TRUE | L8: 1452.3151 | M8: 45693 | N8: 水星银行SF | O8: 5笔USDT转换手续费 1.5x5
A9: 8 | B9: 45632 | C9: 2024 | D9: 12 | E9: NiiHost | F9: USDT | G9: 销售收入 | H9: 3.9876 | J9: 已结算 | K9: TRUE | L9: 1452.3151 | M9: 45693 | N9: 水星银行SF | O9: 5笔USDT转换手续费 1.5x5
A10: 9 | B10: 45636 | C10: 2024 | D10: 12 | E10: NiiHost | F10: USDT | G10: 销售收入 | H10: 16.8003 | J10: 已结算 | K10: TRUE | L10: 1452.3151 | M10: 45693 | N10: 水星银行SF | O10: 5笔USDT转换手续费 1.5x5
A11: 10 | B11: 45636 | C11: 2024 | D11: 12 | E11: NiiHost | F11: USDT | G11: 销售收入 | H11: 600 | J11: 已结算 | K11: TRUE | L11: 1452.3151 | M11: 45693 | N11: 水星银行SF | O11: 5笔USDT转换手续费 1.5x5
A12: 11 | B12: 45643 | C12: 2024 | D12: 12 | E12: NiiHost | F12: USDT | G12: 销售收入 | H12: 10.9808 | J12: 已结算 | K12: TRUE | L12: 1452.3151 | M12: 45693 | N12: 水星银行SF | O12: 5笔USDT转换手续费 1.5x5
A13: 12 | B13: 45652 | C13: 2024 | D13: 12 | E13: NiiHost | F13: USDT | G13: 销售收入 | H13: 120 | J13: 已结算 | K13: TRUE | L13: 1452.3151 | M13: 45693 | N13: 水星银行SF | O13: 5笔USDT转换手续费 1.5x5
A14: 13 | B14: 45653 | C14: 2024 | D14: 12 | E14: NiiHost | F14: USDT | G14: 销售收入 | H14: 20.25 | J14: 已结算 | K14: TRUE | L14: 1452.3151 | M14: 45693 | N14: 水星银行SF | O14: 5笔USDT转换手续费 1.5x5
A15: 14 | B15: 45654 | C15: 2024 | D15: 12 | E15: NiiHost | F15: USDT | G15: 销售收入 | H15: 20.25 | J15: 已结算 | K15: TRUE | L15: 1452.3151 | M15: 45693 | N15: 水星银行SF | O15: 5笔USDT转换手续费 1.5x5
A16: 15 | B16: 45598 | C16: 2024 | D16: 11 | E16: AFF | F16: USDT | G16: 业务支出 | I16: 41.06 | K16: TRUE | O16: AF支付给张雨萱
A17: 16 | B17: 45628 | C17: 2024 | D17: 12 | E17: AFF | F17: USDT | G17: 业务支出 | I17: 62.8 | K17: TRUE | O17: AF支付给张雨萱
A18: 17 | B18: 45642 | C18: 2024 | D18: 12 | E18: AFF | F18: USDT | G18: 业务支出 | I18: 36.35 | K18: TRUE | O18: AF支付给优哥
A19: 18 | B19: 45659 | C19: 2025 | D19: 1 | E19: NiiHost | F19: USDT | G19: 销售收入 | H19: 8 | J19: 已结算 | K19: TRUE
A20: 19 | B20: 45663 | C20: 2025 | D20: 1 | E20: NiiHost | F20: USDT | G20: 销售收入 | H20: 2.49 | J20: 已结算 | K20: TRUE
A21: 20 | B21: 45664 | C21: 2025 | D21: 1 | E21: NiiHost | F21: USDT | G21: 销售收入 | H21: 17.7271 | J21: 已结算 | K21: TRUE
A22: 21 | B22: 45667 | C22: 2025 | D22: 1 | E22: Niihost | F22: USDT | G22: 销售收入 | H22: 600 | J22: 已结算 | K22: TRUE
A23: 22 | B23: 45667 | C23: 2025 | D23: 1 | E23: NiiHost | F23: USDT | G23: 销售收入 | H23: 72.0109 | J23: 已结算 | K23: TRUE
A24: 23 | B24: 45668 | C24: 2025 | D24: 1 | E24: NiiHost | F24: USDT | G24: 销售收入 | H24: 2 | J24: 已结算 | K24: TRUE
A25: 24 | B25: 45668 | C25: 2025 | D25: 1 | E25: NiiHost | F25: USDT | G25: 销售收入 | H25: 2 | J25: 已结算 | K25: TRUE
A26: 25 | B26: 45673 | C26: 2025 | D26: 1 | E26: Niihost | F26: USDT | G26: 销售收入 | H26: 6.7847 | J26: 已结算 | K26: TRUE
A27: 26 | B27: 45673 | C27: 2025 | D27: 1 | E27: NiiHost | F27: USDT | G27: 销售收入 | H27: 17.9932 | J27: 已结算 | K27: TRUE
A28: 27 | B28: 45673 | C28: 2025 | D28: 1 | E28: NiiHost | F28: USDT | G28: 销售收入 | H28: 70.0055 | J28: 已结算 | K28: TRUE
A29: 28 | B29: 45681 | C29: 2025 | D29: 1 | E29: NiiHost | F29: USDT | G29: 销售收入 | H29: 5.9712 | J29: 已结算 | K29: TRUE
A30: 29 | B30: 45685 | C30: 2025 | D30: 1 | E30: Niihost | F30: USDT | G30: 销售收入 | H30: 3.9986 | J30: 已结算 | K30: TRUE
A31: 30 | B31: 45688 | C31: 2025 | D31: 1 | E31: NiiHost | F31: USDT | G31: 销售收入 | H31: 18.1939 | J31: 已结算 | K31: TRUE
A32: 31 | B32: 45698 | C32: 2025 | D32: 2 | E32: NiiHost | F32: 银行转帐 | G32: 业务支出 | I32: 1452.3151 | J32: 已结算 | K32: TRUE | L32: 1452.3151 | M32: 45693 | N32: 水星银行SF | O32: 转到水星支付账单，5笔USDT转换手续费 1.5x5
A33: 32 | B33: 45698 | C33: 2025 | D33: 2 | E33: AFF | F33: USDT | G33: 业务支出 | I33: 41.41 | J33: 已结算 | K33: TRUE | O33: AF支付给张雨萱
A34: 33 | B34: 45698 | C34: 2025 | D34: 2 | E34: NiiHost | F34: USDT | G34: 销售收入 | H34: 600 | J34: 已结算 | K34: TRUE | O34: 可达鸭
A35: 34 | B35: 45699 | C35: 2025 | D35: 2 | E35: NiiHost | F35: USDT | G35: 销售收入 | H35: 48.9617 | J35: 已结算 | K35: TRUE
A36: 35 | B36: 45705 | C36: 2025 | D36: 2 | E36: Niihost | F36: USDT | G36: 销售收入 | H36: 70.1517 | K36: TRUE
A37: 36 | B37: 45707 | C37: 2025 | D37: 2 | E37: NiiHost | F37: USDT | G37: 销售收入 | H37: 100 | K37: TRUE
A38: 37 | B38: 45714 | C38: 2025 | D38: 2 | E38: NiiHost | F38: USDT | G38: 销售收入 | H38: 2.9986 | K38: TRUE
A39: 38 | B39: 45718 | C39: 2025 | D39: 3 | E39: NiiHost | F39: USDT | G39: 销售收入 | H39: 59.9821 | K39: TRUE
A40: 39 | B40: 45718 | C40: 2025 | D40: 3 | E40: NiiHost | F40: USDT | G40: 销售收入 | H40: 59.9822 | K40: TRUE
A41: 40 | B41: 45719 | C41: 2025 | D41: 3 | E41: NiiHost | F41: USDT | G41: 销售收入 | H41: 1.192 | K41: TRUE
A42: 41 | B42: 45720 | C42: 2025 | D42: 3 | E42: NiiHost | F42: USDT | G42: 业务支出 | I42: 2818.57 | J42: 已结算 | K42: TRUE | O42: KCD 支出费用（IEPL）
A43: 42 | B43: 45720 | C43: 2025 | D43: 3 | E43: NiiHost | F43: USDT | G43: 销售收入 | H43: 23.9863 | K43: TRUE
A44: 43 | B44: 45720 | C44: 2025 | D44: 3 | E44: NiiHost | F44: USDT | G44: 销售收入 | H44: 6.9986 | K44: TRUE
A45: 44 | B45: 45720 | C45: 2025 | D45: 3 | E45: NiiHost | F45: USDT | G45: 销售收入 | H45: 60.1596 | K45: TRUE
A46: 45 | B46: 45721 | C46: 2025 | D46: 3 | E46: NiiHost | F46: USDT | G46: 销售收入 | H46: 49.9807 | K46: TRUE
A47: 46 | B47: 45721 | C47: 2025 | D47: 3 | E47: NiiHost | F47: USDT | G47: 销售收入 | H47: 17.9835 | K47: TRUE
A48: 47 | B48: 45721 | C48: 2025 | D48: 3 | E48: Niihost | F48: TRX | G48: 销售收入 | H48: 5.39 | K48: TRUE | O48: TRX 22.23R\
A49: 48 | B49: 45727 | C49: 2025 | D49: 3 | E49: NiiHost | F49: USDT | G49: 销售收入 | H49: 600 | K49: TRUE
A50: 49 | B50: 45730 | C50: 2025 | D50: 3 | E50: NiiHost | F50: USDT | G50: 销售收入 | H50: 50.0539 | K50: TRUE
A51: 50 | B51: 45732 | C51: 2025 | D51: 3 | E51: NiiHost | F51: USDT | G51: 销售收入 | H51: 69.9779 | K51: TRUE
A52: 51 | B52: 45734 | C52: 2025 | D52: 3 | E52: NiiHost | F52: USDT | G52: 销售收入 | H52: 110 | K52: TRUE
A53: 52 | B53: 45737 | C53: 2025 | D53: 3 | E53: NiiHost | F53: USDT | G53: 销售收入 | H53: 9.5834 | K53: TRUE
A54: 53 | B54: 45738 | C54: 2025 | D54: 3 | E54: NiiHost | F54: USDT | G54: 销售收入 | H54: 49.9876 | K54: TRUE
A55: 54 | B55: 45741 | C55: 2025 | D55: 3 | E55: Niihost | F55: TRX | G55: 销售收入 | H55: 3.99 | K55: TRUE | O55: TRX 17.55
A56: 55 | B56: 45743 | C56: 2025 | D56: 3 | E56: Niihost | F56: TRX | G56: 销售收入 | H56: 1.79 | K56: TRUE | O56: TRX 7.65
A57: 56 | B57: 45744 | C57: 2025 | D57: 3 | E57: NiiHost | F57: USDT | G57: 销售收入 | H57: 60 | K57: TRUE
A58: 57 | B58: 45744 | C58: 2025 | D58: 3 | E58: NiiHost | F58: USDT | G58: 销售收入 | H58: 212.8748 | K58: TRUE
A59: 58 | B59: 45746 | C59: 2025 | D59: 3 | E59: NiiHost | F59: USDT | G59: 销售收入 | H59: 120.0702 | K59: TRUE
A60: 59 | B60: 45748 | C60: 2025 | D60: 4 | E60: NiiHost | F60: USDT | G60: 销售收入 | H60: 11.99 | K60: TRUE
A61: 60 | B61: 45748 | C61: 2025 | D61: 4 | E61: NiiHost | F61: USDT | G61: 销售收入 | H61: 11.99 | K61: TRUE
A62: 61 | B62: 45749 | C62: 2025 | D62: 4 | E62: NiiHost | F62: TRX | G62: 销售收入 | H62: 2.99 | K62: TRUE | O62: TRX 12.68
A63: 62 | B63: 45751 | C63: 2025 | D63: 4 | E63: NiiHost | F63: USDT | G63: 销售收入 | H63: 15.9726 | K63: TRUE
A64: 63 | B64: 45753 | C64: 2025 | D64: 4 | E64: NiiHost | F64: USDT | G64: 销售收入 | H64: 110 | K64: TRUE
A65: 64 | B65: 45754 | C65: 2025 | D65: 4 | E65: NiiHost | F65: USDT | G65: 销售收入 | H65: 17.99 | K65: TRUE
A66: 65 | B66: 45754 | C66: 2025 | D66: 4 | E66: NiiHost | F66: TRX | G66: 销售收入 | H66: 0.99 | K66: TRUE | O66: TRX 4.37
A67: 66 | B67: 45755 | C67: 2025 | D67: 4 | E67: NiiHost | F67: TRX | G67: 销售收入 | H67: 2.99 | K67: TRUE | O67: TRX 12.7
A68: 67 | B68: 45757 | C68: 2025 | D68: 4 | E68: NiiHost | F68: USDT | G68: 销售收入 | H68: 600 | K68: TRUE
A69: 68 | B69: 45759 | C69: 2025 | D69: 4 | E69: NiiHost | F69: USDT | G69: 销售收入 | H69: 7.9904 | K69: TRUE
A70: 69 | B70: 45761 | C70: 2025 | D70: 4 | E70: NiiHost | F70: USDT | G70: 销售收入 | H70: 15.99 | K70: TRUE | O70: 27.98 合并为一笔
A71: 70 | B71: 45761 | C71: 2025 | D71: 4 | E71: NiiHost | F71: USDT | G71: 销售收入 | H71: 11.99 | K71: TRUE
A72: 71 | B72: 45762 | C72: 2025 | D72: 4 | E72: NiiHost | F72: USDT | G72: 销售收入 | H72: 283.08 | K72: TRUE
A73: 72 | B73: 45763 | C73: 2025 | D73: 4 | E73: NiiHost | F73: USDT | G73: 销售收入 | H73: 69.99 | K73: TRUE
A74: 73 | B74: 45764 | C74: 2025 | D74: 4 | E74: NiiHost | F74: USDT | G74: 销售收入 | H74: 421.56439 | K74: TRUE
A75: 74 | B75: 45764 | C75: 2025 | D75: 4 | E75: NiiHost | F75: USDT | G75: 销售收入 | H75: 14.99 | K75: TRUE
A76: 75 | B76: 45765 | C76: 2025 | D76: 4 | E76: NiiHost | F76: USDT | G76: 销售收入 | H76: 14.99 | K76: TRUE
A77: 76 | B77: 45765 | C77: 2025 | D77: 4 | E77: NiiHost | F77: USDT | G77: 销售收入 | H77: 110 | K77: TRUE
A78: 77 | B78: 45765 | C78: 2025 | D78: 4 | E78: NiiHost | F78: USDT | G78: 销售收入 | H78: 14.99 | K78: TRUE
A79: 78 | B79: 45768 | C79: 2025 | D79: 4 | E79: NiiHost | F79: USDT | G79: 销售收入 | H79: 3.99 | K79: TRUE
A80: 79 | B80: 45773 | C80: 2025 | D80: 4 | E80: NiiHost | F80: USDT | G80: 销售收入 | H80: 179 | K80: TRUE
A81: 80 | B81: 45773 | C81: 2025 | D81: 4 | E81: NiiHost | F81: USDT | G81: 销售收入 | H81: 119.98 | K81: TRUE
A82: 81 | B82: 45775 | C82: 2025 | D82: 4 | E82: NiiHost | F82: USDT | G82: 销售收入 | H82: 2.99 | K82: TRUE
... A90: 89 | B90: 45782 | C90: 2025 | D90: 5 | E90: NiiHost | F90: USDT | G90: 销售收入 | H90: 110 | K90: TRUE
A91: 90 | B91: 45783 | C91: 2025 | D91: 5 | E91: NiiHost | F91: TRX | G91: 销售收入 | H91: 0.99 | K91: TRUE | O91: TRX 3.98
A92: 91 | B92: 45785 | C92: 2025 | D92: 5 | E92: NiiHost | F92: USDT | G92: 销售收入 | H92: 29.99 | K92: TRUE
A93: 92 | B93: 45785 | C93: 2025 | D93: 5 | E93: NiiHost | F93: USDT | G93: 销售收入 | H93: 536 | K93: TRUE | O93: Sun的
A94: 93 | B94: 45786 | C94: 2025 | D94: 5 | E94: NiiHost | F94: USDT | G94: 销售收入 | H94: 12.99 | K94: TRUE
A95: 94 | B95: 45786 | C95: 2025 | D95: 5 | E95: NiiHost | F95: USDT | G95: 销售收入 | H95: 600 | K95: TRUE
A96: 95 | B96: 45788 | C96: 2025 | D96: 5 | E96: NiiHost | F96: USDT | G96: 销售收入 | H96: 2.99 | K96: TRUE
A97: 96 | B97: 45789 | C97: 2025 | D97: 5 | E97: NiiHost | F97: USDT | G97: 销售收入 | H97: 287.4 | K97: TRUE
A98: 97 | B98: 45790 | C98: 2025 | D98: 5 | E98: NiiHost | F98: USDT | G98: 销售收入 | H98: 16.09 | K98: TRUE
A99: 98 | B99: 45794 | C99: 2025 | D99: 5 | E99: NiiHost | F99: TRX | G99: 销售收入 | H99: 3.99 | K99: TRUE | O99: TRX 14.68
A100: 99 | B100: 45794 | C100: 2025 | D100: 5 | E100: NiiHost | F100: USDT | G100: 销售收入 | H100: 99.99 | K100: TRUE
A101: 100 | B101: 45794 | C101: 2025 | D101: 5 | E101: NiiHost | F101: USDT | G101: 销售收入 | H101: 160 | K101: TRUE
A102: 101 | B102: 45795 | C102: 2025 | D102: 5 | E102: NiiHost | F102: USDT | G102: 销售收入 | H102: 110 | K102: TRUE
A103: 102 | B103: 45797 | C103: 2025 | D103: 5 | E103: NiiHost | F103: USDT | G103: 销售收入 | H103: 8.99 | K103: TRUE
A104: 103 | B104: 45799 | C104: 2025 | D104: 5 | E104: NiiHost | F104: USDT | G104: 销售收入 | H104: 20.69 | K104: TRUE
A105: 104 | B105: 45799 | C105: 2025 | D105: 5 | E105: NiiHost | F105: USDT | G105: 销售收入 | H105: 11.69 | K105: TRUE
A106: 105 | B106: 45803 | C106: 2025 | D106: 5 | E106: NiiHost | F106: USDT | G106: 销售收入 | H106: 8.99 | K106: TRUE
A107: 106 | B107: 45806 | C107: 2025 | D107: 5 | E107: NiiHost | F107: USDT | G107: 销售收入 | H107: 215 | K107: TRUE | O107: USDT 249 一起
...

Sheet 支付宝
A1: # | B1: 日期 | C1: 年 | D1: 月份 | E1: 对象 | F1: 类型 | G1: 描述 | H1: 收入 | I1: 支出 | J1: 结算否 | K1: 是否对帐 | L1: 结算总额 | M1: 结算日期 | N1: 结算银行 | O1: 备注
A2: 1 | B2: 45753 | C2: =YEAR(B2) -> 2025 | D2: =MONTH(B2) -> 4 | E2: NiiHost | F2: 银行转帐 | G2: 销售收入 | H2: 836 | J2: 已结算 | K2: TRUE | N2: 支付宝 | O2: 老孙
A3: 2 | B3: 45785 | C3: =YEAR(B3) -> 2025 | D3: =MONTH(B3) -> 5 | E3: NiiHost | F3: 银行转帐 | G3: 销售收入 | H3: 300 | J3: 已结算 | K3: TRUE | N3: 支付宝 | O3: 老孙
A4: 3 | B4: 45995 | C4: =YEAR(B4) -> 2025 | D4: 12 | E4: NiiHost | F4: 银行转帐 | G4: 销售收入 | H4: 460 | J4: 已结算 | K4: TRUE | N4: 支付宝 | O4: 老孙,3250

Sheet Wise2025
A1: Y | B1: M | C1: ID | D1: Status | E1: Direction | F1: Created on | G1: Finished on | H1: Source fee amount | I1: Source fee currency | J1: Target fee amount | K1: Target fee currency | L1: Source name | M1: Source amount (after fees) | N1: IN | O1: OUT | P1: Source currency | Q1: Target name | R1: Target amount (after fees) | S1: Target currency | T1: Exchange rate | U1: Reference | V1: Batch | W1: Created by
A2: 2025 | B2: 1 | C2: TRANSFER-1396540848 | D2: COMPLETED | E2: IN | F2: 45688.209 | G2: 45688.209 | H2: 0 | I2: USD | L2: STRIPE | M2: 26.5 | N2: =IF(E2="IN",M2,0) -> 26.5 | O2: =IF(E2="OUT",M2+H2,0) -> 0 | P2: USD | Q2: Stars Flying Inc | R2: 26.5 | S2: USD | T2: 1 | U2: TRANSFER | W2: XIANG JIAO
A3: 2025 | B3: 1 | C3: TRANSFER-1395031004 | D3: COMPLETED | E3: IN | F3: 45687.208 | G3: 45687.208 | H3: 0 | I3: USD | L3: STRIPE | M3: 24.57 | N3: =IF(E3="IN",M3,0) -> 24.57 | O3: =IF(E3="OUT",M3+H3,0) -> 0 | P3: USD | Q3: Stars Flying Inc | R3: 24.57 | S3: USD | T3: 1 | U3: TRANSFER | W3: XIANG JIAO
A4: 2025 | B4: 1 | C4: TRANSFER-1393613702 | D4: COMPLETED | E4: IN | F4: 45686.209 | G4: 45686.209 | H4: 0 | I4: USD | L4: STRIPE | M4: 141.59 | N4: =IF(E4="IN",M4,0) -> 141.59 | O4: =IF(E4="OUT",M4+H4,0) -> 0 | P4: USD | Q4: Stars Flying Inc | R4: 141.59 | S4: USD | T4: 1 | U4: TRANSFER | W4: XIANG JIAO
A5: 2025 | B5: 1 | C5: TRANSFER-1392185108 | D5: COMPLETED | E5: IN | F5: 45685.209 | G5: 45685.21 | H5: 0 | I5: USD | L5: STRIPE | M5: 9.1 | N5: =IF(E5="IN",M5,0) -> 9.1 | O5: =IF(E5="OUT",M5+H5,0) -> 0 | P5: USD | Q5: Stars Flying Inc | R5: 9.1 | S5: USD | T5: 1 | U5: TRANSFER | W5: XIANG JIAO
A6: 2025 | B6: 1 | C6: TRANSFER-1391386775 | D6: COMPLETED | E6: IN | F6: 45684.598 | G6: 45684.599 | H6: 0 | I6: USD | L6: STRIPE | M6: 67.53 | N6: =IF(E6="IN",M6,0) -> 67.53 | O6: =IF(E6="OUT",M6+H6,0) -> 0 | P6: USD | Q6: Stars Flying Inc | R6: 67.53 | S6: USD | T6: 1 | U6: TRANSFER | W6: XIANG JIAO
A7: 2025 | B7: 1 | C7: TRANSFER-1387449294 | D7: COMPLETED | E7: IN | F7: 45681.21 | G7: 45681.21 | H7: 0 | I7: USD | L7: STRIPE | M7: 52.59 | N7: =IF(E7="IN",M7,0) -> 52.59 | O7: =IF(E7="OUT",M7+H7,0) -> 0 | P7: USD | Q7: Stars Flying Inc | R7: 52.59 | S7: USD | T7: 1 | U7: TRANSFER | W7: XIANG JIAO
A8: 2025 | B8: 1 | C8: TRANSFER-1386084889 | D8: COMPLETED | E8: IN | F8: 45680.209 | G8: 45680.209 | H8: 0 | I8: USD | L8: STRIPE | M8: 249.19 | N8: =IF(E8="IN",M8,0) -> 249.19 | O8: =IF(E8="OUT",M8+H8,0) -> 0 | P8: USD | Q8: Stars Flying Inc | R8: 249.19 | S8: USD | T8: 1 | U8: TRANSFER | W8: XIANG JIAO
A9: 2025 | B9: 1 | C9: TRANSFER-1384738483 | D9: COMPLETED | E9: IN | F9: 45679.209 | G9: 45679.209 | H9: 0 | I9: USD | L9: STRIPE | M9: 106.01 | N9: =IF(E9="IN",M9,0) -> 106.01 | O9: =IF(E9="OUT",M9+H9,0) -> 0 | P9: USD | Q9: Stars Flying Inc | R9: 106.01 | S9: USD | T9: 1 | U9: TRANSFER | W9: XIANG JIAO
A10: 2025 | B10: 1 | C10: TRANSFER-1384006635 | D10: COMPLETED | E10: IN | F10: 45678.599 | G10: 45678.599 | H10: 0 | I10: USD | L10: STRIPE | M10: 114.36 | N10: =IF(E10="IN",M10,0) -> 114.36 | O10: =IF(E10="OUT",M10+H10,0) -> 0 | P10: USD | Q10: Stars Flying Inc | R10: 114.36 | S10: USD | T10: 1 | U10: TRANSFER | W10: XIANG JIAO
A11: 2025 | B11: 1 | C11: TRANSFER-1378923686 | D11: COMPLETED | E11: IN | F11: 45674.209 | G11: 45674.209 | H11: 0 | I11: USD | L11: STRIPE | M11: 57.6 | N11: =IF(E11="IN",M11,0) -> 57.6 | O11: =IF(E11="OUT",M11+H11,0) -> 0 | P11: USD | Q11: Stars Flying Inc | R11: 57.6 | S11: USD | T11: 1 | U11: TRANSFER | W11: XIANG JIAO
A12: 2025 | B12: 1 | C12: TRANSFER-1377542037 | D12: COMPLETED | E12: IN | F12: 45673.209 | G12: 45673.21 | H12: 0 | I12: USD | L12: STRIPE | M12: 1.64 | N12: =IF(E12="IN",M12,0) -> 1.64 | O12: =IF(E12="OUT",M12+H12,0) -> 0 | P12: USD | Q12: Stars Flying Inc | R12: 1.64 | S12: USD | T12: 1 | U12: TRANSFER | W12: XIANG JIAO
A13: 2025 | B13: 1 | C13: TRANSFER-1376080546 | D13: COMPLETED | E13: IN | F13: 45672.21 | G13: 45672.21 | H13: 0 | I13: USD | L13: STRIPE | M13: 152.08 | N13: =IF(E13="IN",M13,0) -> 152.08 | O13: =IF(E13="OUT",M13+H13,0) -> 0 | P13: USD | Q13: Stars Flying Inc | R13: 152.08 | S13: USD | T13: 1 | U13: TRANSFER | W13: XIANG JIAO
... A22: 2025 | B22: 1 | C22: TRANSFER-1364922592 | D22: COMPLETED | E22: IN | F22: 45663.601 | G22: 45663.601 | H22: 0 | I22: USD | L22: STRIPE | M22: 119.04 | N22: =IF(E22="IN",M22,0) -> 119.04 | O22: =IF(E22="OUT",M22+H22,0) -> 0 | P22: USD | Q22: Stars Flying Inc | R22: 119.04 | S22: USD | T22: 1 | U22: TRANSFER | W22: XIANG JIAO
A23: 2025 | B23: 1 | C23: TRANSFER-1364198099 | D23: COMPLETED | E23: OUT | F23: 45663.256 | G23: 45663.256 | H23: 0 | I23: USD | L23: Stars Flying Inc | M23: 400 | N23: =IF(E23="IN",M23,0) -> 0 | O23: =IF(E23="OUT",M23+H23,0) -> 400 | P23: USD | Q23: MIN CHEN | R23: 400 | S23: USD | T23: 1 | U23: 579221 | W23: XIANG JIAO
A24: 2025 | B24: 1 | C24: TRANSFER-1360784844 | D24: COMPLETED | E24: IN | F24: 45660.208 | G24: 45660.209 | H24: 0 | I24: USD | L24: STRIPE | M24: 150.43 | N24: =IF(E24="IN",M24,0) -> 150.43 | O24: =IF(E24="OUT",M24+H24,0) -> 0 | P24: USD | Q24: Stars Flying Inc | R24: 150.43 | S24: USD | T24: 1 | U24: TRANSFER | W24: XIANG JIAO
A25: 2025 | B25: 1 | C25: TRANSFER-1359139264 | D25: COMPLETED | E25: OUT | F25: 45659.142 | G25: 45659.608 | H25: 1.13 | I25: USD | L25: Stars Flying Inc | M25: 1395.08 | N25: =IF(E25="IN",M25,0) -> 0 | O25: =IF(E25="OUT",M25+H25,0) -> 1396.21 | P25: USD | Q25: O2 Network Limited | R25: 1395.08 | S25: USD | T25: 1 | U25: 202501 fee | W25: XIANG JIAO
A26: 2025 | B26: 1 | C26: TRANSFER-1359899450 | D26: COMPLETED | E26: IN | F26: 45659.597 | G26: 45659.598 | H26: 0 | I26: USD | L26: STRIPE | M26: 608.31 | N26: =IF(E26="IN",M26,0) -> 608.31 | O26: =IF(E26="OUT",M26+H26,0) -> 0 | P26: USD | Q26: Stars Flying Inc | R26: 608.31 | S26: USD | T26: 1 | U26: TRANSFER | W26: XIANG JIAO
A27: 2025 | B27: 2 | C27: TRANSFER-1431133946 | D27: COMPLETED | E27: OUT | F27: 45714.324 | G27: 45714.608 | H27: 1.13 | I27: USD | L27: Stars Flying Inc | M27: 1782.62 | N27: =IF(E27="IN",M27,0) -> 0 | O27: =IF(E27="OUT",M27+H27,0) -> 1783.75 | P27: USD | Q27: Stars Flying Inc | R27: 1782.62 | S27: USD | T27: 1 | W27: XIANG JIAO
A28: 2025 | B28: 2 | C28: TRANSFER-1430972366 | D28: COMPLETED | E28: IN | F28: 45714.208 | G28: 45714.208 | H28: 0 | I28: USD | L28: STRIPE | M28: 128.57 | N28: =IF(E28="IN",M28,0) -> 128.57 | O28: =IF(E28="OUT",M28+H28,0) -> 0 | P28: USD | Q28: Stars Flying Inc | R28: 128.57 | S28: USD | T28: 1 | U28: TRANSFER | W28: XIANG JIAO
A29: 2025 | B29: 2 | C29: TRANSFER-1429462782 | D29: COMPLETED | E29: IN | F29: 45713.208 | G29: 45713.208 | H29: 0 | I29: USD | L29: STRIPE | M29: 114.18 | N29: =IF(E29="IN",M29,0) -> 114.18 | O29: =IF(E29="OUT",M29+H29,0) -> 0 | P29: USD | Q29: Stars Flying Inc | R29: 114.18 | S29: USD | T29: 1 | U29: TRANSFER | W29: XIANG JIAO
A30: 2025 | B30: 2 | C30: TRANSFER-1428681578 | D30: COMPLETED | E30: IN | F30: 45712.599 | G30: 45712.599 | H30: 0 | I30: USD | L30: STRIPE | M30: 81.91 | N30: =IF(E30="IN",M30,0) -> 81.91 | O30: =IF(E30="OUT",M30+H30,0) -> 0 | P30: USD | Q30: Stars Flying Inc | R30: 81.91 | S30: USD | T30: 1 | U30: TRANSFER | W30: XIANG JIAO
A31: 2025 | B31: 2 | C31: TRANSFER-1424873508 | D31: COMPLETED | E31: IN | F31: 45709.208 | G31: 45709.209 | H31: 0 | I31: USD | L31: STRIPE | M31: 18.36 | N31: =IF(E31="IN",M31,0) -> 18.36 | O31: =IF(E31="OUT",M31+H31,0) -> 0 | P31: USD | Q31: Stars Flying Inc | R31: 18.36 | S31: USD | T31: 1 | U31: TRANSFER | W31: XIANG JIAO
A32: 2025 | B32: 2 | C32: TRANSFER-1423502861 | D32: COMPLETED | E32: IN | F32: 45708.208 | G32: 45708.209 | H32: 0 | I32: USD | L32: STRIPE | M32: 96.13 | N32: =IF(E32="IN",M32,0) -> 96.13 | O32: =IF(E32="OUT",M32+H32,0) -> 0 | P32: USD | Q32: Stars Flying Inc | R32: 96.13 | S32: USD | T32: 1 | U32: TRANSFER | W32: XIANG JIAO
A33: 2025 | B33: 2 | C33: TRANSFER-1422169092 | D33: COMPLETED | E33: IN | F33: 45707.209 | G33: 45707.209 | H33: 0 | I33: USD | L33: STRIPE | M33: 21.08 | N33: =IF(E33="IN",M33,0) -> 21.08 | O33: =IF(E33="OUT",M33+H33,0) -> 0 | P33: USD | Q33: Stars Flying Inc | R33: 21.08 | S33: USD | T33: 1 | U33: TRANSFER | W33: XIANG JIAO
A34: 2025 | B34: 2 | C34: TRANSFER-1421419459 | D34: COMPLETED | E34: IN | F34: 45706.599 | G34: 45706.599 | H34: 0 | I34: USD | L34: STRIPE | M34: 34.34 | N34: =IF(E34="IN",M34,0) -> 34.34 | O34: =IF(E34="OUT",M34+H34,0) -> 0 | P34: USD | Q34: Stars Flying Inc | R34: 34.34 | S34: USD | T34: 1 | U34: TRANSFER | W34: XIANG JIAO
A35: 2025 | B35: 2 | C35: TRANSFER-1416052183 | D35: COMPLETED | E35: IN | F35: 45702.209 | G35: 45702.209 | H35: 0 | I35: USD | L35: STRIPE | M35: 50.5 | N35: =IF(E35="IN",M35,0) -> 50.5 | O35: =IF(E35="OUT",M35+H35,0) -> 0 | P35: USD | Q35: Stars Flying Inc | R35: 50.5 | S35: USD | T35: 1 | U35: TRANSFER | W35: XIANG JIAO
A36: 2025 | B36: 2 | C36: TRANSFER-1414648589 | D36: COMPLETED | E36: IN | F36: 45701.208 | G36: 45701.567 | H36: 0 | I36: USD | L36: STRIPE | M36: 7.15 | N36: =IF(E36="IN",M36,0) -> 7.15 | O36: =IF(E36="OUT",M36+H36,0) -> 0 | P36: USD | Q36: Stars Flying Inc | R36: 7.15 | S36: USD | T36: 1 | U36: TRANSFER | W36: XIANG JIAO
A37: 2025 | B37: 2 | C37: TRANSFER-1413933449 | D37: COMPLETED | E37: IN | F37: 45700.599 | G37: 45700.6 | H37: 0 | I37: USD | L37: PAYPAL | M37: 500 | N37: =IF(E37="IN",M37,0) -> 500 | O37: =IF(E37="OUT",M37+H37,0) -> 0 | P37: USD | Q37: Stars Flying Inc | R37: 500 | S37: USD | T37: 1 | U37: TRANSFER | W37: XIANG JIAO
A38: 2025 | B38: 2 | C38: TRANSFER-1413302209 | D38: COMPLETED | E38: IN | F38: 45700.209 | G38: 45700.21 | H38: 0 | I38: USD | L38: STRIPE | M38: 29.04 | N38: =IF(E38="IN",M38,0) -> 29.04 | O38: =IF(E38="OUT",M38+H38,0) -> 0 | P38: USD | Q38: Stars Flying Inc | R38: 29.04 | S38: USD | T38: 1 | U38: TRANSFER | W38: XIANG JIAO
A39: 2025 | B39: 2 | C39: DIRECT_DEBIT_TRANSACTION-19834950 | D39: COMPLETED | E39: OUT | F39: 45699.594 | G39: 45699.594 | M39: 19.86 | N39: =IF(E39="IN",M39,0) -> 0 | O39: =IF(E39="OUT",M39+H39,0) -> 19.86 | P39: USD | Q39: STRIPE | R39: 19.86 | S39: USD | T39: 1 | U39: 2025-02-10-224954.644_225458_91000016365878 | W39: XIANG JIAO
A40: 2025 | B40: 2 | C40: TRANSFER-1411153430 | D40: COMPLETED | E40: IN | F40: 45698.64 | G40: 45698.64 | H40: 0 | I40: USD | L40: STRIPE | M40: 53.48 | N40: =IF(E40="IN",M40,0) -> 53.48 | O40: =IF(E40="OUT",M40+H40,0) -> 0 | P40: USD | Q40: Stars Flying Inc | R40: 53.48 | S40: USD | T40: 1 | U40: TRANSFER | W40: XIANG JIAO
A41: 2025 | B41: 2 | C41: TRANSFER-1406954157 | D41: COMPLETED | E41: IN | F41: 45695.208 | G41: 45695.208 | H41: 0 | I41: USD | L41: STRIPE | M41: 1.62 | N41: =IF(E41="IN",M41,0) -> 1.62 | O41: =IF(E41="OUT",M41+H41,0) -> 0 | P41: USD | Q41: Stars Flying Inc | R41: 1.62 | S41: USD | T41: 1 | U41: TRANSFER | W41: XIANG JIAO
A42: 2025 | B42: 2 | C42: TRANSFER-1405461084 | D42: COMPLETED | E42: IN | F42: 45694.208 | G42: 45694.209 | H42: 0 | I42: USD | L42: STRIPE | M42: 76.31 | N42: =IF(E42="IN",M42,0) -> 76.31 | O42: =IF(E42="OUT",M42+H42,0) -> 0 | P42: USD | Q42: Stars Flying Inc | R42: 76.31 | S42: USD | T42: 1 | U42: TRANSFER | W42: XIANG JIAO
A43: 2025 | B43: 2 | C43: TRANSFER-1403837711 | D43: COMPLETED | E43: OUT | F43: 45693.106 | G43: 45693.608 | H43: 1.13 | I43: USD | L43: Stars Flying Inc | M43: 2175.03 | N43: =IF(E43="IN",M43,0) -> 0 | O43: =IF(E43="OUT",M43+H43,0) -> 2176.16 | P43: USD | Q43: O2 Network Limited | R43: 2175.03 | S43: USD | T43: 1 | U43: IDC FEE | W43: XIANG JIAO
A44: 2025 | B44: 2 | C44: TRANSFER-1403917632 | D44: COMPLETED | E44: IN | F44: 45693.208 | G44: 45693.208 | H44: 0 | I44: USD | L44: STRIPE | M44: 50.87 | N44: =IF(E44="IN",M44,0) -> 50.87 | O44: =IF(E44="OUT",M44+H44,0) -> 0 | P44: USD | Q44: Stars Flying Inc | R44: 50.87 | S44: USD | T44: 1 | U44: TRANSFER | W44: XIANG JIAO
A45: 2025 | B45: 2 | C45: TRANSFER-1402313872 | D45: COMPLETED | E45: IN | F45: 45692.209 | G45: 45692.209 | H45: 0 | I45: USD | L45: STRIPE | M45: 57.66 | N45: =IF(E45="IN",M45,0) -> 57.66 | O45: =IF(E45="OUT",M45+H45,0) -> 0 | P45: USD | Q45: Stars Flying Inc | R45: 57.66 | S45: USD | T45: 1 | U45: TRANSFER | W45: XIANG JIAO
A46: 2025 | B46: 2 | C46: TRANSFER-1401379633 | D46: COMPLETED | E46: IN | F46: 45691.601 | G46: 45691.601 | H46: 0 | I46: USD | L46: STRIPE | M46: 11.38 | N46: =IF(E46="IN",M46,0) -> 11.38 | O46: =IF(E46="OUT",M46+H46,0) -> 0 | P46: USD | Q46: Stars Flying Inc | R46: 11.38 | S46: USD | T46: 1 | U46: TRANSFER | W46: XIANG JIAO
A47: 2025 | B47: 4 | C47: TRANSFER-1515648131 | D47: COMPLETED | E47: IN | F47: 4/28/2025 13:21 | G47: 4/28/2025 13:21 | H47: 0 | I47: USD | L47: STRIPE | M47: 675.55 | N47: =IF(E47="IN",M47,0) -> 675.55 | O47: =IF(E47="OUT",M47+H47,0) -> 0 | P47: USD | Q47: Stars Flying Inc | R47: 675.55 | S47: USD | T47: 1 | U47: TRANSFER | W47: XIANG JIAO
A48: 2025 | B48: 4 | C48: TRANSFER-1506203092 | D48: COMPLETED | E48: IN | F48: 4/21/2025 13:21 | G48: 4/21/2025 13:21 | H48: 0 | I48: USD | L48: STRIPE | M48: 586.95 | N48: =IF(E48="IN",M48,0) -> 586.95 | O48: =IF(E48="OUT",M48+H48,0) -> 0 | P48: USD | Q48: Stars Flying Inc | R48: 586.95 | S48: USD | T48: 1 | U48: TRANSFER | W48: XIANG JIAO
A49: 2025 | B49: 5 | C49: TRANSFER-1556637619 | D49: COMPLETED | E49: IN | F49: 5/27/2025 13:22 | G49: 5/27/2025 13:22 | H49: 0 | I49: USD | L49: STRIPE | M49: 1074.58 | N49: =IF(E49="IN",M49,0) -> 1074.58 | O49: =IF(E49="OUT",M49+H49,0) -> 0 | P49: USD | Q49: Stars Flying Inc | R49: 1074.58 | S49: USD | T49: 1 | U49: TRANSFER | W49: XIANG JIAO
A50: 2025 | B50: 5 | C50: TRANSFER-1545796581 | D50: COMPLETED | E50: IN | F50: 5/19/2025 13:26 | G50: 5/19/2025 13:26 | H50: 0 | I50: USD | L50: STRIPE | M50: 266.33 | N50: =IF(E50="IN",M50,0) -> 266.33 | O50: =IF(E50="OUT",M50+H50,0) -> 0 | P50: USD | Q50: Stars Flying Inc | R50: 266.33 | S50: USD | T50: 1 | U50: TRANSFER | W50: XIANG JIAO
A51: 2025 | B51: 5 | C51: TRANSFER-1536251788 | D51: COMPLETED | E51: IN | F51: 45996.558 | G51: 45996.558 | H51: 0 | I51: USD | L51: STRIPE | M51: 456.84 | N51: =IF(E51="IN",M51,0) -> 456.84 | O51: =IF(E51="OUT",M51+H51,0) -> 0 | P51: USD | Q51: Stars Flying Inc | R51: 456.84 | S51: USD | T51: 1 | U51: TRANSFER | W51: XIANG JIAO
A52: 2025 | B52: 5 | C52: TRANSFER-1526264279 | D52: COMPLETED | E52: IN | F52: 45782.56 | G52: 45782.56 | H52: 0 | I52: USD | L52: STRIPE | M52: 292.8 | N52: =IF(E52="IN",M52,0) -> 292.8 | O52: =IF(E52="OUT",M52+H52,0) -> 0 | P52: USD | Q52: Stars Flying Inc | R52: 292.8 | S52: USD | T52: 1 | U52: TRANSFER | W52: XIANG JIAO
A53: 2025 | B53: 6 | C53: TRANSFER-1605831287 | D53: COMPLETED | E53: IN | F53: 6/30/2025 13:42 | G53: 6/30/2025 13:42 | H53: 0 | I53: USD | L53: STRIPE | M53: 178.04 | N53: =IF(E53="IN",M53,0) -> 178.04 | O53: =IF(E53="OUT",M53+H53,0) -> 0 | P53: USD | Q53: Stars Flying Inc | R53: 178.04 | S53: USD | T53: 1 | U53: TRANSFER | W53: XIANG JIAO
A54: 2025 | B54: 6 | C54: TRANSFER-1595303114 | D54: COMPLETED | E54: IN | F54: 6/23/2025 13:37 | G54: 6/23/2025 13:37 | H54: 0 | I54: USD | L54: STRIPE | M54: 202.14 | N54: =IF(E54="IN",M54,0) -> 202.14 | O54: =IF(E54="OUT",M54+H54,0) -> 0 | P54: USD | Q54: Stars Flying Inc | R54: 202.14 | S54: USD | T54: 1 | U54: TRANSFER | W54: XIANG JIAO
A55: 2025 | B55: 6 | C55: TRANSFER-1585950041 | D55: COMPLETED | E55: IN | F55: 6/16/2025 13:26 | G55: 6/16/2025 13:27 | H55: 0 | I55: USD | L55: STRIPE | M55: 728.71 | N55: =IF(E55="IN",M55,0) -> 728.71 | O55: =IF(E55="OUT",M55+H55,0) -> 0 | P55: USD | Q55: Stars Flying Inc | R55: 728.71 | S55: USD | T55: 1 | U55: TRANSFER | W55: XIANG JIAO
A56: 2025 | B56: 6 | C56: TRANSFER-1576122666 | D56: COMPLETED | E56: IN | F56: 45906.569 | G56: 45906.569 | H56: 0 | I56: USD | L56: STRIPE | M56: 999.89 | N56: =IF(E56="IN",M56,0) -> 999.89 | O56: =IF(E56="OUT",M56+H56,0) -> 0 | P56: USD | Q56: Stars Flying Inc | R56: 999.89 | S56: USD | T56: 1 | U56: TRANSFER | W56: XIANG JIAO
A57: 2025 | B57: 6 | C57: TRANSFER-1568713381 | D57: COMPLETED | E57: OUT | F57: 45753.321 | G57: 45753.567 | H57: 1.13 | I57: USD | L57: Stars Flying Inc | M57: 367.26 | N57: =IF(E57="IN",M57,0) -> 0 | O57: =IF(E57="OUT",M57+H57,0) -> 368.39 | P57: USD | Q57: O2 Network Limited | R57: 367.26 | S57: USD | T57: 1 | U57: IDC FEE | W57: XIANG JIAO
A58: 2025 | B58: 6 | C58: TRANSFER-1568702701 | D58: COMPLETED | E58: OUT | F58: 45753.315 | G58: 45753.565 | H58: 1.13 | I58: USD | L58: Stars Flying Inc | M58: 1894.56 | N58: =IF(E58="IN",M58,0) -> 0 | O58: =IF(E58="OUT",M58+H58,0) -> 1895.69 | P58: USD | Q58: O2 Network Limited | R58: 1894.56 | S58: USD | T58: 1 | U58: IDC FEE | W58: XIANG JIAO
A59: 2025 | B59: 6 | C59: TRANSFER-1565742845 | D59: COMPLETED | E59: IN | F59: 45694.56 | G59: 45694.56 | H59: 0 | I59: USD | L59: STRIPE | M59: 2032.87 | N59: =IF(E59="IN",M59,0) -> 2032.87 | O59: =IF(E59="OUT",M59+H59,0) -> 0 | P59: USD | Q59: Stars Flying Inc | R59: 2032.87 | S59: USD | T59: 1 | U59: TRANSFER | W59: XIANG JIAO
A60: 2025 | B60: 7 | C60: TRANSFER-1647318004 | D60: COMPLETED | E60: IN | F60: 7/28/2025 13:39 | G60: 7/28/2025 13:40 | H60: 0 | I60: USD | L60: STRIPE | M60: 769.74 | N60: =IF(E60="IN",M60,0) -> 769.74 | O60: =IF(E60="OUT",M60+H60,0) -> 0 | P60: USD | Q60: Stars Flying Inc | R60: 769.74 | S60: USD | T60: 1 | U60: TRANSFER | W60: XIANG JIAO
A61: 2025 | B61: 7 | C61: TRANSFER-1637362143 | D61: COMPLETED | E61: IN | F61: 7/21/2025 13:22 | G61: 7/21/2025 13:23 | H61: 0 | I61: USD | L61: STRIPE | M61: 553.45 | N61: =IF(E61="IN",M61,0) -> 553.45 | O61: =IF(E61="OUT",M61+H61,0) -> 0 | P61: USD | Q61: Stars Flying Inc | R61: 553.45 | S61: USD | T61: 1 | U61: TRANSFER | W61: XIANG JIAO
A62: 2025 | B62: 7 | C62: TRANSFER-1627462610 | D62: COMPLETED | E62: IN | F62: 7/14/2025 13:41 | G62: 7/14/2025 13:41 | H62: 0 | I62: USD | L62: STRIPE | M62: 1158.13 | N62: =IF(E62="IN",M62,0) -> 1158.13 | O62: =IF(E62="OUT",M62+H62,0) -> 0 | P62: USD | Q62: Stars Flying Inc | R62: 1158.13 | S62: USD | T62: 1 | U62: TRANSFER | W62: XIANG JIAO
A63: 2025 | B63: 7 | C63: TRANSFER-1620323838 | D63: COMPLETED | E63: OUT | F63: 45907.476 | G63: 45907.564 | H63: 1.13 | I63: USD | L63: Stars Flying Inc | M63: 728.95 | N63: =IF(E63="IN",M63,0) -> 0 | O63: =IF(E63="OUT",M63+H63,0) -> 730.08 | P63: USD | Q63: O2 Network Limited | R63: 728.95 | S63: USD | T63: 1 | U63: IDC FEE | W63: XIANG JIAO
A64: 2025 | B64: 7 | C64: TRANSFER-1617167336 | D64: COMPLETED | E64: IN | F64: 45845.57 | G64: 45845.571 | H64: 0 | I64: USD | L64: STRIPE | M64: 168.45 | N64: =IF(E64="IN",M64,0) -> 168.45 | O64: =IF(E64="OUT",M64+H64,0) -> 0 | P64: USD | Q64: Stars Flying Inc | R64: 168.45 | S64: USD | T64: 1 | U64: TRANSFER | W64: XIANG JIAO
A65: 2025 | B65: 7 | C65: TRANSFER-1614637813 | D65: COMPLETED | E65: OUT | F65: 45784.51 | G65: 45845.567 | H65: 1.13 | I65: USD | L65: Stars Flying Inc | M65: 2056.44 | N65: =IF(E65="IN",M65,0) -> 0 | O65: =IF(E65="OUT",M65+H65,0) -> 2057.57 | P65: USD | Q65: O2 Network Limited | R65: 2056.44 | S65: USD | T65: 1 | U65: IDC FEE | W65: XIANG JIAO
A66: 2025 | B66: 8 | C66: TRANSFER-1699312318 | D66: COMPLETED | E66: OUT | F66: 8/31/2025 17:17 | G66: 8/31/2025 17:17 | H66: 0 | I66: USD | L66: Stars Flying Inc | M66: 10 | N66: =IF(E66="IN",M66,0) -> 0 | O66: =IF(E66="OUT",M66+H66,0) -> 10 | P66: USD | Q66: XIANG JIAO | R66: 10 | S66: USD | T66: 1 | W66: XIANG JIAO | X66: General
A67: 2025 | B67: 8 | C67: TRANSFER-1689481415 | D67: COMPLETED | E67: IN | F67: 8/25/2025 13:24 | G67: 8/25/2025 13:24 | H67: 0 | I67: USD | L67: STRIPE | M67: 399.43 | N67: =IF(E67="IN",M67,0) -> 399.43 | O67: =IF(E67="OUT",M67+H67,0) -> 0 | P67: USD | Q67: Stars Flying Inc | R67: 399.43 | S67: USD | T67: 1 | U67: TRANSFER | W67: XIANG JIAO | X67: Money added
A68: 2025 | B68: 8 | C68: TRANSFER-1679625086 | D68: COMPLETED | E68: IN | F68: 8/18/2025 13:25 | G68: 8/18/2025 13:25 | H68: 0 | I68: USD | L68: STRIPE | M68: 663.12 | N68: =IF(E68="IN",M68,0) -> 663.12 | O68: =IF(E68="OUT",M68+H68,0) -> 0 | P68: USD | Q68: Stars Flying Inc | R68: 663.12 | S68: USD | T68: 1 | U68: TRANSFER | W68: XIANG JIAO | X68: Money added
A69: 2025 | B69: 8 | C69: TRANSFER-1669523566 | D69: COMPLETED | E69: IN | F69: 45969.56 | G69: 45969.56 | H69: 0 | I69: USD | L69: STRIPE | M69: 291.6 | N69: =IF(E69="IN",M69,0) -> 291.6 | O69: =IF(E69="OUT",M69+H69,0) -> 0 | P69: USD | Q69: Stars Flying Inc | R69: 291.6 | S69: USD | T69: 1 | U69: TRANSFER | W69: XIANG JIAO | X69: Money added
A70: 2025 | B70: 8 | C70: TRANSFER-1659693424 | D70: COMPLETED | E70: OUT | F70: 45785.092 | G70: 45785.658 | H70: 1.13 | I70: USD | L70: Stars Flying Inc | M70: 3966.87 | N70: =IF(E70="IN",M70,0) -> 0 | O70: =IF(E70="OUT",M70+H70,0) -> 3968 | P70: USD | Q70: O2 Network Limited | R70: 3966.87 | S70: USD | T70: 1 | U70: IDC FEE | W70: XIANG JIAO | X70: General
A71: 2025 | B71: 8 | C71: TRANSFER-1659079981 | D71: COMPLETED | E71: IN | F71: 45755.681 | G71: 45755.681 | H71: 0 | I71: USD | L71: STRIPE | M71: 689.89 | N71: =IF(E71="IN",M71,0) -> 689.89 | O71: =IF(E71="OUT",M71+H71,0) -> 0 | P71: USD | Q71: Stars Flying Inc | R71: 689.89 | S71: USD | T71: 1 | U71: TRANSFER | W71: XIANG JIAO | X71: Money added
A72: 2025 | B72: 9 | C72: TRANSFER-1744567135 | D72: COMPLETED | E72: IN | F72: 9/29/2025 13:37 | G72: 9/29/2025 13:38 | H72: 0 | I72: USD | L72: STRIPE | M72: 171.03 | N72: =IF(E72="IN",M72,0) -> 171.03 | O72: =IF(E72="OUT",M72+H72,0) -> 0 | P72: USD | Q72: Stars Flying Inc | R72: 171.03 | S72: USD | T72: 1 | U72: TRANSFER | W72: XIANG JIAO | X72: Money added
A73: 2025 | B73: 9 | C73: TRANSFER-1733773384 | D73: COMPLETED | E73: IN | F73: 9/22/2025 13:41 | G73: 9/22/2025 13:42 | H73: 0 | I73: USD | L73: STRIPE | M73: 294.19 | N73: =IF(E73="IN",M73,0) -> 294.19 | O73: =IF(E73="OUT",M73+H73,0) -> 0 | P73: USD | Q73: Stars Flying Inc | R73: 294.19 | S73: USD | T73: 1 | U73: TRANSFER | W73: XIANG JIAO | X73: Money added
A74: 2025 | B74: 9 | C74: TRANSFER-1723230624 | D74: COMPLETED | E74: IN | F74: 9/15/2025 13:25 | G74: 9/15/2025 13:26 | H74: 0 | I74: USD | L74: STRIPE | M74: 144.77 | N74: =IF(E74="IN",M74,0) -> 144.77 | O74: =IF(E74="OUT",M74+H74,0) -> 0 | P74: USD | Q74: Stars Flying Inc | R74: 144.77 | S74: USD | T74: 1 | U74: TRANSFER | W74: XIANG JIAO | X74: Money added
A75: 2025 | B75: 9 | C75: TRANSFER-1712695203 | D75: COMPLETED | E75: IN | F75: 45878.691 | G75: 45878.692 | H75: 0 | I75: USD | L75: STRIPE | M75: 117.43 | N75: =IF(E75="IN",M75,0) -> 117.43 | O75: =IF(E75="OUT",M75+H75,0) -> 0 | P75: USD | Q75: Stars Flying Inc | R75: 117.43 | S75: USD | T75: 1 | U75: TRANSFER | W75: XIANG JIAO | X75: Money added
A76: 2025 | B76: 9 | C76: TRANSFER-1711480481 | D76: COMPLETED | E76: OUT | F76: 45878.148 | G76: 45878.565 | H76: 1.13 | I76: USD | L76: Stars Flying Inc | M76: 3200 | N76: =IF(E76="IN",M76,0) -> 0 | O76: =IF(E76="OUT",M76+H76,0) -> 3201.13 | P76: USD | Q76: O2 Network Limited | R76: 3200 | S76: USD | T76: 1 | U76: IDC FEE | W76: XIANG JIAO | X76: General
A77: 2025 | B77: 9 | C77: TRANSFER-1702835049 | D77: COMPLETED | E77: IN | F77: 45697.562 | G77: 45697.562 | H77: 0 | I77: USD | L77: STRIPE | M77: 725.6 | N77: =IF(E77="IN",M77,0) -> 725.6 | O77: =IF(E77="OUT",M77+H77,0) -> 0 | P77: USD | Q77: Stars Flying Inc | R77: 725.6 | S77: USD | T77: 1 | U77: TRANSFER | W77: XIANG JIAO | X77: Money added
A78: 2025 | B78: 9 | C78: TRANSFER-1701195504 | D78: COMPLETED | E78: OUT | F78: 45666.663 | G78: 45666.663 | H78: 0 | I78: USD | L78: Stars Flying Inc | M78: 660 | N78: =IF(E78="IN",M78,0) -> 0 | O78: =IF(E78="OUT",M78+H78,0) -> 660 | P78: USD | Q78: XIANG JIAO | R78: 660 | S78: USD | T78: 1 | W78: XIANG JIAO | X78: General
A79: 2025 | B79: 10 | C79: TRANSFER-1789241504 | D79: COMPLETED | E79: IN | F79: 10/27/2025 13:22 | G79: 10/27/2025 13:22 | H79: 0 | I79: USD | L79: STRIPE | M79: 174.6 | N79: =IF(E79="IN",M79,0) -> 174.6 | O79: =IF(E79="OUT",M79+H79,0) -> 0 | P79: USD | Q79: Stars Flying Inc | R79: 174.6 | S79: USD | T79: 1 | U79: TRANSFER | W79: XIANG JIAO | X79: Money added
A80: 2025 | B80: 10 | C80: TRANSFER-1778916806 | D80: COMPLETED | E80: IN | F80: 10/20/2025 13:37 | G80: 10/20/2025 13:37 | H80: 0 | I80: USD | L80: STRIPE | M80: 390.49 | N80: =IF(E80="IN",M80,0) -> 390.49 | O80: =IF(E80="OUT",M80+H80,0) -> 0 | P80: USD | Q80: Stars Flying Inc | R80: 390.49 | S80: USD | T80: 1 | U80: TRANSFER | W80: XIANG JIAO | X80: Money added
A81: 2025 | B81: 10 | C81: TRANSFER-1770202295 | D81: COMPLETED | E81: IN | F81: 10/14/2025 17:38 | G81: 10/14/2025 17:38 | H81: 0 | I81: USD | L81: STRIPE | M81: 134.68 | N81: =IF(E81="IN",M81,0) -> 134.68 | O81: =IF(E81="OUT",M81+H81,0) -> 0 | P81: USD | Q81: Stars Flying Inc | R81: 134.68 | S81: USD | T81: 1 | U81: TRANSFER | W81: XIANG JIAO | X81: Money added
A82: 2025 | B82: 10 | C82: DIRECT_DEBIT_TRANSACTION-26669541 | D82: COMPLETED | E82: OUT | F82: 45879.563 | G82: 45879.563 | M82: 262.5 | N82: =IF(E82="IN",M82,0) -> 0 | O82: =IF(E82="OUT",M82+H82,0) -> 262.5 | P82: USD | Q82: ARIN | R82: 262.5 | S82: USD | T82: 1 | U82: 2025-10-07-225332.168_88969_91000010022520 | W82: XIANG JIAO | X82: General
A83: 2025 | B83: 10 | C83: TRANSFER-1758962903 | D83: COMPLETED | E83: IN | F83: 45848.569 | G83: 45848.57 | H83: 0 | I83: USD | L83: PAYPAL | M83: 700 | N83: =IF(E83="IN",M83,0) -> 700 | O83: =IF(E83="OUT",M83+H83,0) -> 0 | P83: USD | Q83: Stars Flying Inc | R83: 700 | S83: USD | T83: 1 | U83: TRANSFER | W83: XIANG JIAO | X83: Money added
A84: 2025 | B84: 10 | C84: TRANSFER-1757058924 | D84: COMPLETED | E84: IN | F84: 45818.567 | G84: 45818.567 | H84: 0 | I84: USD | L84: STRIPE | M84: 137.78 | N84: =IF(E84="IN",M84,0) -> 137.78 | O84: =IF(E84="OUT",M84+H84,0) -> 0 | P84: USD | Q84: Stars Flying Inc | R84: 137.78 | S84: USD | T84: 1 | U84: TRANSFER | W84: XIANG JIAO | X84: Money added
A85: 2025 | B85: 10 | C85: TRANSFER-1753533601 | D85: COMPLETED | E85: OUT | F85: 45726.89 | G85: 45726.89 | H85: 0 | I85: USD | L85: Stars Flying Inc | M85: 704 | N85: =IF(E85="IN",M85,0) -> 0 | O85: =IF(E85="OUT",M85+H85,0) -> 704 | P85: USD | Q85: XIANG JIAO | R85: 704 | S85: USD | T85: 1 | W85: XIANG JIAO | X85: General
A86: 2025 | B86: 11 | C86: TRANSFER-1839425159 | D86: COMPLETED | E86: OUT | F86: 11/27/2025 3:47 | G86: 11/27/2025 3:47 | H86: 0 | I86: USD | L86: Stars Flying Inc | M86: 670 | N86: =IF(E86="IN",M86,0) -> 0 | O86: =IF(E86="OUT",M86+H86,0) -> 670 | P86: USD | Q86: XIANG JIAO | R86: 670 | S86: USD | T86: 1 | W86: XIANG JIAO | X86: General
A87: 2025 | B87: 11 | C87: TRANSFER-1834972822 | D87: COMPLETED | E87: IN | F87: 11/24/2025 14:36 | G87: 11/24/2025 14:36 | H87: 0 | I87: USD | L87: STRIPE | M87: 256.15 | N87: =IF(E87="IN",M87,0) -> 256.15 | O87: =IF(E87="OUT",M87+H87,0) -> 0 | P87: USD | Q87: Stars Flying Inc | R87: 256.15 | S87: USD | T87: 1 | U87: TRANSFER | W87: XIANG JIAO | X87: Money added
A88: 2025 | B88: 11 | C88: TRANSFER-1824476075 | D88: COMPLETED | E88: IN | F88: 11/17/2025 14:52 | G88: 11/17/2025 14:52 | H88: 0 | I88: USD | L88: STRIPE | M88: 972.85 | N88: =IF(E88="IN",M88,0) -> 972.85 | O88: =IF(E88="OUT",M88+H88,0) -> 0 | P88: USD | Q88: Stars Flying Inc | R88: 972.85 | S88: USD | T88: 1 | U88: TRANSFER | W88: XIANG JIAO | X88: Money added
A89: 2025 | B89: 11 | C89: TRANSFER-1813267788 | D89: COMPLETED | E89: IN | F89: 45941.598 | G89: 45941.599 | H89: 0 | I89: USD | L89: STRIPE | M89: 290.9 | N89: =IF(E89="IN",M89,0) -> 290.9 | O89: =IF(E89="OUT",M89+H89,0) -> 0 | P89: USD | Q89: Stars Flying Inc | R89: 290.9 | S89: USD | T89: 1 | U89: TRANSFER | W89: XIANG JIAO | X89: Money added
A90: 2025 | B90: 11 | C90: TRANSFER-1801499776 | D90: COMPLETED | E90: IN | F90: 45727.609 | G90: 45727.609 | H90: 0 | I90: USD | L90: STRIPE | M90: 953.11 | N90: =IF(E90="IN",M90,0) -> 953.11 | O90: =IF(E90="OUT",M90+H90,0) -> 0 | P90: USD | Q90: Stars Flying Inc | R90: 953.11 | S90: USD | T90: 1 | U90: TRANSFER | W90: XIANG JIAO | X90: Money added
A91: 2025 | B91: 11 | C91: TRANSFER-1799074105 | D91: COMPLETED | E91: OUT | F91: 45699.115 | G91: 45699.115 | H91: 0 | I91: USD | L91: Stars Flying Inc | M91: 750 | N91: =IF(E91="IN",M91,0) -> 0 | O91: =IF(E91="OUT",M91+H91,0) -> 750 | P91: USD | Q91: XIANG JIAO | R91: 750 | S91: USD | T91: 1 | W91: XIANG JIAO | X91: General
A92: 2025 | B92: 12 | C92: TRANSFER-1893608646 | D92: COMPLETED | E92: IN | F92: 12/29/2025 14:37 | G92: 12/29/2025 14:37 | H92: 0 | I92: USD | L92: STRIPE | M92: 316.04 | N92: =IF(E92="IN",M92,0) -> 316.04 | O92: =IF(E92="OUT",M92+H92,0) -> 0 | P92: USD | Q92: Stars Flying Inc | R92: 316.04 | S92: USD | T92: 1 | U92: TRANSFER | W92: XIANG JIAO | X92: Money added
A93: 2025 | B93: 12 | C93: TRANSFER-1892552565 | D93: COMPLETED | E93: OUT | F93: 12/29/2025 4:15 | G93: 12/29/2025 4:15 | H93: 0 | I93: USD | L93: Stars Flying Inc | M93: 400 | N93: =IF(E93="IN",M93,0) -> 0 | O93: =IF(E93="OUT",M93+H93,0) -> 400 | P93: USD | Q93: ZHEN TAN | R93: 400 | S93: USD | T93: 1 | U93: 505685 | W93: XIANG JIAO | X93: General
A94: 2025 | B94: 12 | C94: TRANSFER-1883039616 | D94: COMPLETED | E94: IN | F94: 12/22/2025 14:22 | G94: 12/22/2025 14:22 | H94: 0 | I94: USD | L94: STRIPE | M94: 336.82 | N94: =IF(E94="IN",M94,0) -> 336.82 | O94: =IF(E94="OUT",M94+H94,0) -> 0 | P94: USD | Q94: Stars Flying Inc | R94: 336.82 | S94: USD | T94: 1 | U94: TRANSFER | W94: XIANG JIAO | X94: Money added
A95: 2025 | B95: 12 | C95: TRANSFER-1871341557 | D95: COMPLETED | E95: IN | F95: 12/15/2025 14:36 | G95: 12/15/2025 14:36 | H95: 0 | I95: USD | L95: STRIPE | M95: 69.12 | N95: =IF(E95="IN",M95,0) -> 69.12 | O95: =IF(E95="OUT",M95+H95,0) -> 0 | P95: USD | Q95: Stars Flying Inc | R95: 69.12 | S95: USD | T95: 1 | U95: TRANSFER | W95: XIANG JIAO | X95: Money added
A96: 2025 | B96: 12 | C96: TRANSFER-1869133685 | D96: COMPLETED | E96: OUT | F96: 12/14/2025 2:57 | G96: 12/14/2025 2:57 | H96: 1.13 | I96: USD | L96: Stars Flying Inc | M96: 1100 | N96: =IF(E96="IN",M96,0) -> 0 | O96: =IF(E96="OUT",M96+H96,0) -> 1101.13 | P96: USD | Q96: KURUN CLOUD INC | R96: 1100 | S96: USD | T96: 1 | U96: IDC FEE | W96: XIANG JIAO | X96: General
A97: 2025 | B97: 12 | C97: TRANSFER-1859870182 | D97: COMPLETED | E97: IN | F97: 45881.598 | G97: 45881.599 | H97: 0 | I97: USD | L97: STRIPE | M97: 87.82 | N97: =IF(E97="IN",M97,0) -> 87.82 | O97: =IF(E97="OUT",M97+H97,0) -> 0 | P97: USD | Q97: Stars Flying Inc | R97: 87.82 | S97: USD | T97: 1 | U97: TRANSFER | W97: XIANG JIAO | X97: Money added
A98: 2025 | B98: 12 | C98: TRANSFER-1847469085 | D98: COMPLETED | E98: IN | F98: 45669.599 | G98: 45669.599 | H98: 0 | I98: USD | L98: STRIPE | M98: 168.51 | N98: =IF(E98="IN",M98,0) -> 168.51 | O98: =IF(E98="OUT",M98+H98,0) -> 0 | P98: USD | Q98: Stars Flying Inc | R98: 168.51 | S98: USD | T98: 1 | U98: TRANSFER | W98: XIANG JIAO | X98: Money added

Sheet Payssion
A1: Date Created | B1: M | C1: App Name | D1: Transaction ID | E1: State | F1: pm_id | G1: Total Amount | H1: Paid Amount | I1: Fee Amount | J1: Net Amount | K1: Refund Amount | L1: Currency | M1: Amount Local | N1: Currency Local | O1: Description | P1: Order Id | Q1: Order Extra | R1: Country
A2: 6/15/2025 17:05 | B2: 6 | C2: niihost | D2: Z615071207130212 | E2: completed | F2: alipay_cn | G2: 13.99 | H2: 13.99 | I2: 0.41 | J2: 13.58 | K2: 0 | L2: USD | O2: NiiHost - 账单编号 #69644 | P2: 69644 | R2: SG
A3: 6/15/2025 16:53 | B3: 6 | C3: niihost | D3: Z615064211711944 | E3: completed | F3: alipay_cn | G3: 14.39 | H3: 14.39 | I3: 0.42 | J3: 13.97 | K3: 0 | L3: USD | O3: NiiHost - 账单编号 #69620 | P3: 69620 | R3: US
A4: 6/15/2025 14:04 | B4: 6 | C4: niihost | D4: Z615962801728599 | E4: completed | F4: alipay_cn | G4: 18.39 | H4: 18.39 | I4: 0.54 | J4: 17.85 | K4: 0 | L4: USD | O4: NiiHost - 账单编号 #69608 | P4: 69608 | R4: CN
A5: 6/16/2025 15:54 | B5: 6 | C5: niihost | D5: Z616892591154823 | E5: completed | F5: alipay_cn | G5: 28.79 | H5: 28.79 | I5: 0.84 | J5: 27.95 | K5: 0 | L5: USD | O5: NiiHost - 账单编号 #69860 | P5: 69860 | R5: JP
A6: 6/16/2025 14:30 | B6: 6 | C6: niihost | D6: Z616842030424225 | E6: completed | F6: alipay_cn | G6: 7.99 | H6: 7.99 | I6: 0.24 | J6: 7.75 | K6: 0 | L6: USD | O6: NiiHost - 账单编号 #69848 | P6: 69848 | R6: US
A7: 6/16/2025 14:09 | B7: 6 | C7: niihost | D7: Z616829595702571 | E7: completed | F7: alipay_cn | G7: 56.79 | H7: 56.79 | I7: 1.65 | J7: 55.14 | K7: 0 | L7: USD | O7: NiiHost - Invoice #69836 | P7: 69836 | R7: CN
A8: 6/17/2025 22:57 | B8: 6 | C8: niihost | D8: Z617010750478726 | E8: completed | F8: alipay_cn | G8: 165.59 | H8: 165.59 | I8: 4.81 | J8: 160.78 | K8: 0 | L8: USD | O8: NiiHost - 账单编号 #70196 | P8: 70196 | R8: HK
A9: 6/17/2025 15:45 | B9: 6 | C9: niihost | D9: Z617751219154849 | E9: completed | F9: alipay_cn | G9: 20.25 | H9: 20.25 | I9: 0.59 | J9: 19.66 | K9: 0 | L9: USD | O9: NiiHost - 账单编号 #70172 | P9: 70172 | R9: KR
A10: 6/17/2025 13:45 | B10: 6 | C10: niihost | D10: Z617679177182219 | E10: completed | F10: alipay_cn | G10: 3.19 | H10: 3.19 | I10: 0.1 | J10: 3.09 | K10: 0 | L10: USD | O10: NiiHost - 账单编号 #70148 | P10: 70148 | R10: US
A11: 6/17/2025 4:36 | B11: 6 | C11: niihost | D11: Z617350142280760 | E11: completed | F11: alipay_cn | G11: 5.99 | H11: 5.99 | I11: 0.18 | J11: 5.81 | K11: 0 | L11: USD | O11: NiiHost - 账单编号 #70124 | P11: 70124 | R11: GB
A12: 6/18/2025 19:54 | B12: 6 | C12: niihost | D12: Z618764975709699 | E12: completed | F12: alipay_cn | G12: 4.79 | H12: 4.79 | I12: 0.14 | J12: 4.65 | K12: 0 | L12: USD | O12: NiiHost - 账单编号 #70641 | P12: 70641 | R12: US
A13: 6/18/2025 15:59 | B13: 6 | C13: niihost | D13: Z618623858631229 | E13: completed | F13: alipay_cn | G13: 17.99 | H13: 17.99 | I13: 0.53 | J13: 17.46 | K13: 0 | L13: USD | O13: NiiHost - 账单编号 #70617 | P13: 70617 | R13: GB
... A21: 6/18/2025 6:05 | B21: 6 | C21: niihost | D21: Z618267348844270 | E21: completed | F21: alipay_cn | G21: 14.39 | H21: 14.39 | I21: 0.42 | J21: 13.97 | K21: 0 | L21: USD | O21: NiiHost - 账单编号 #70364 | P21: 70364 | R21: US
A22: 6/18/2025 5:14 | B22: 6 | C22: niihost | D22: R618236418975823 | E22: refunded | F22: alipay_cn | G22: -4.49 | H22: -4.49 | I22: 0.5 | J22: -4.49 | K22: 3.99 | L22: USD | O22: refund Z618217457125554 | P22: 70340 | Q22: Z618217457125554 | R22: HK
A23: 6/18/2025 5:03 | B23: 6 | C23: niihost | D23: Z618230153955985 | E23: completed | F23: alipay_cn | G23: 20.69 | H23: 20.69 | I23: 0.6 | J23: 20.09 | K23: 0 | L23: USD | O23: NiiHost - Invoice #70208 | P23: 70208 | R23: US
A24: 6/18/2025 4:42 | B24: 6 | C24: niihost | D24: Z618217457125554 | E24: completed | F24: alipay_cn | G24: 3.99 | H24: 3.99 | I24: 0.12 | J24: 3.87 | K24: 3.99 | L24: USD | O24: NiiHost - 账单编号 #70340 | P24: 70340 | R24: HK
A25: 6/18/2025 1:03 | B25: 6 | C25: niihost | D25: Z618086342039709 | E25: completed | F25: alipay_cn | G25: 3.99 | H25: 3.99 | I25: 0.12 | J25: 3.87 | K25: 0 | L25: USD | O25: NiiHost - 账单编号 #70328 | P25: 70328 | R25: HK
A26: 6/19/2025 10:21 | B26: 6 | C26: niihost | D26: Z619284810872039 | E26: completed | F26: alipay_cn | G26: 12.99 | H26: 12.99 | I26: 0.38 | J26: 12.61 | K26: 0 | L26: USD | O26: NiiHost - 账单编号 #70965 | P26: 70965 | R26: US
A27: 6/19/2025 4:10 | B27: 6 | C27: niihost | D27: Z619062519137115 | E27: completed | F27: alipay_cn | G27: 20.69 | H27: 20.69 | I27: 0.6 | J27: 20.09 | K27: 0 | L27: USD | O27: NiiHost - 账单编号 #70929 | P27: 70929 | R27: HK
A28: 6/19/2025 3:48 | B28: 6 | C28: niihost | D28: Z619048875093040 | E28: completed | F28: alipay_cn | G28: 3.99 | H28: 3.99 | I28: 0.12 | J28: 3.87 | K28: 0 | L28: USD | O28: NiiHost - 账单编号 #70917 | P28: 70917 | R28: HK
A29: 6/20/2025 10:23 | B29: 6 | C29: niihost | D29: Z620150069759688 | E29: completed | F29: alipay_cn | G29: 1 | H29: 1 | I29: 0.03 | J29: 0.97 | K29: 0 | L29: USD | O29: NiiHost - 账单编号 #71193 | P29: 71193
A30: 6/20/2025 8:39 | B30: 6 | C30: niihost | D30: Z620087707607169 | E30: completed | F30: alipay_cn | G30: 1.98 | H30: 1.98 | I30: 0.06 | J30: 1.92 | K30: 0 | L30: USD | O30: NiiHost - 账单编号 #71181 | P30: 71181 | R30: CN
A31: 6/20/2025 8:37 | B31: 6 | C31: niihost | D31: Z620086401034816 | E31: completed | F31: alipay_cn | G31: 1.98 | H31: 1.98 | I31: 0.06 | J31: 1.92 | K31: 0 | L31: USD | O31: NiiHost - 账单编号 #71169 | P31: 71169 | R31: CN
A32: 6/20/2025 7:51 | B32: 6 | C32: niihost | D32: Z620059179705188 | E32: completed | F32: alipay_cn | G32: 20.69 | H32: 20.69 | I32: 0.6 | J32: 20.09 | K32: 0 | L32: USD | O32: NiiHost - 账单编号 #71145 | P32: 71145 | R32: JP
A33: 6/20/2025 3:08 | B33: 6 | C33: niihost | D33: Z620889083855269 | E33: completed | F33: alipay_cn | G33: 1 | H33: 1 | I33: 0.03 | J33: 0.97 | K33: 0 | L33: USD | O33: NiiHost - 账单编号 #71109 | P33: 71109 | R33: HK
A34: 6/20/2025 2:05 | B34: 6 | C34: niihost | D34: Z620851369204214 | E34: completed | F34: alipay_cn | G34: 2.99 | H34: 2.99 | I34: 0.09 | J34: 2.9 | K34: 0 | L34: USD | O34: NiiHost - Invoice #71097 | P34: 71097 | R34: US
A35: 6/20/2025 1:36 | B35: 6 | C35: niihost | D35: Z620833681875566 | E35: completed | F35: alipay_cn | G35: 24.25 | H35: 24.25 | I35: 0.71 | J35: 23.54 | K35: 0 | L35: USD | O35: NiiHost - 账单编号 #71013 | P35: 71013 | R35: CN
A36: 6/21/2025 20:43 | B36: 6 | C36: niihost | D36: Z621386107729204 | E36: completed | F36: alipay_cn | G36: 2.99 | H36: 2.99 | I36: 0.09 | J36: 2.9 | K36: 0 | L36: USD | O36: NiiHost - Invoice #71337 | P36: 71337 | R36: CN
A37: 6/21/2025 11:24 | B37: 6 | C37: niihost | D37: Z621050937245256 | E37: completed | F37: alipay_cn | G37: 19.99 | H37: 19.99 | I37: 0.58 | J37: 19.41 | K37: 0 | L37: USD | O37: NiiHost - 账单编号 #71325 | P37: 71325 | R37: US
A38: 6/21/2025 9:47 | B38: 6 | C38: niihost | D38: Z621992402937426 | E38: completed | F38: alipay_cn | G38: 6.99 | H38: 6.99 | I38: 0.21 | J38: 6.78 | K38: 0 | L38: USD | O38: NiiHost - 账单编号 #71313 | P38: 71313 | R38: US
A39: 6/21/2025 1:35 | B39: 6 | C39: niihost | D39: Z621697220531691 | E39: completed | F39: alipay_cn | G39: 2.99 | H39: 2.99 | I39: 0.09 | J39: 2.9 | K39: 0 | L39: USD | O39: NiiHost - 账单编号 #68828 | P39: 68828 | R39: CN
A40: 6/22/2025 16:11 | B40: 6 | C40: niihost | D40: Z622087056007122 | E40: completed | F40: alipay_cn | G40: 5.49 | H40: 5.49 | I40: 0.16 | J40: 5.33 | K40: 0 | L40: USD | O40: NiiHost - 账单编号 #71541 | P40: 71541 | R40: HK
A41: 6/23/2025 15:42 | B41: 6 | C41: niihost | D41: Z623933620275707 | E41: completed | F41: alipay_cn | G41: 20.25 | H41: 20.25 | I41: 0.59 | J41: 19.66 | K41: 0 | L41: USD | O41: NiiHost - 账单编号 #71853 | P41: 71853 | R41: JP
... A49: 6/25/2025 12:19 | B49: 6 | C49: niihost | D49: Z625539412297551 | E49: completed | F49: alipay_cn | G49: 2.99 | H49: 2.99 | I49: 0.09 | J49: 2.9 | K49: 0 | L49: USD | O49: NiiHost - 账单编号 #72429 | P49: 72429 | R49: VN
A50: 6/25/2025 3:23 | B50: 6 | C50: niihost | D50: R625218196687513 | E50: refunded | F50: alipay_cn | G50: -20.75 | H50: -20.75 | I50: 0.5 | J50: -20.75 | K50: 20.25 | L50: USD | O50: refund Z624424338785248 | P50: 72273 | Q50: Z624424338785248 | R50: HK
A51: 6/26/2025 12:22 | B51: 6 | C51: niihost | D51: Z626405420217821 | E51: completed | F51: alipay_cn | G51: 20.75 | H51: 20.75 | I51: 0.61 | J51: 20.14 | K51: 0 | L51: USD | O51: NiiHost - 账单编号 #69128 | P51: 69128 | R51: VN
A52: 6/26/2025 11:14 | B52: 6 | C52: niihost | D52: Z626364432193490 | E52: completed | F52: alipay_cn | G52: 587.99 | H52: 587.99 | I52: 17.06 | J52: 570.93 | K52: 0 | L52: USD | O52: NiiHost - 账单编号 #72789 | P52: 72789 | R52: CN
A53: 6/26/2025 4:07 | B53: 6 | C53: niihost | D53: Z626108683096431 | E53: completed | F53: alipay_cn | G53: 2.01 | H53: 2.01 | I53: 0.06 | J53: 1.95 | K53: 0 | L53: USD | O53: NiiHost - 账单编号 #72753 | P53: 72753 | R53: GB
A54: 6/26/2025 1:17 | B54: 6 | C54: niihost | D54: Z626006406496460 | E54: completed | F54: alipay_cn | G54: 2.99 | H54: 2.99 | I54: 0.09 | J54: 2.9 | K54: 0 | L54: USD | O54: NiiHost - 账单编号 #72741 | P54: 72741 | R54: US
A55: 6/28/2025 11:38 | B55: 6 | C55: niihost | D55: Z628107358451063 | E55: completed | F55: alipay_cn | G55: 1 | H55: 1 | I55: 0.03 | J55: 0.97 | K55: 0 | L55: USD | O55: NiiHost - 账单编号 #73113 | P55: 73113 | R55: US
A56: 6/28/2025 8:09 | B56: 6 | C56: niihost | D56: Z628981677544091 | E56: completed | F56: alipay_cn | G56: 119.98 | H56: 119.98 | I56: 3.48 | J56: 116.5 | K56: 0 | L56: USD | O56: NiiHost - 账单编号 #73089 | P56: 73089 | R56: HK
A57: 6/29/2025 13:00 | B57: 6 | C57: niihost | D57: Z629020539588561 | E57: completed | F57: alipay_cn | G57: 85.51 | H57: 85.51 | I57: 2.48 | J57: 83.03 | K57: 0 | L57: USD | O57: NiiHost - 账单编号 #73209 | P57: 73209 | R57: SG
A58: 6/29/2025 12:25 | B58: 6 | C58: niihost | D58: Z629999255055753 | E58: completed | F58: alipay_cn | G58: 13.02 | H58: 13.02 | I58: 0.38 | J58: 12.64 | K58: 0 | L58: USD | O58: NiiHost - 账单编号 #73185 | P58: 73185 | R58: US
A59: 6/30/2025 11:14 | B59: 6 | C59: niihost | D59: Z630820789994976 | E59: completed | F59: alipay_cn | G59: 9.99 | H59: 9.99 | I59: 0.29 | J59: 9.7 | K59: 0 | L59: USD | O59: NiiHost - 账单编号 #73389 | P59: 73389 | R59: PH
A60: 6/30/2025 10:51 | B60: 6 | C60: niihost | D60: Z630807041070870 | E60: completed | F60: alipay_cn | G60: 32.95 | H60: 32.95 | I60: 0.96 | J60: 31.99 | K60: 0 | L60: USD | O60: NiiHost - Invoice #73377 | P60: 73377 | R60: SG
A61: 6/30/2025 4:13 | B61: 6 | C61: niihost | D61: Z630568009343629 | E61: completed | F61: alipay_cn | G61: 29.98 | H61: 29.98 | I61: 0.87 | J61: 29.11 | K61: 0 | L61: USD | O61: NiiHost - 账单编号 #73365 | P61: 73365 | R61: HK
A62: 6/30/2025 4:08 | B62: 6 | C62: niihost | D62: Z630565188059839 | E62: completed | F62: alipay_cn | G62: 28.79 | H62: 28.79 | I62: 0.84 | J62: 27.95 | K62: 0 | L62: USD | O62: NiiHost - 账单编号 #73341 | P62: 73341 | R62: HK
... A64: 6/30/2025 2:07 | B64: 6 | C64: niihost | D64: Z630492224491942 | E64: completed | F64: alipay_cn | G64: 18.99 | H64: 18.99 | I64: 0.55 | J64: 18.44 | K64: 0 | L64: USD | O64: NiiHost - 账单编号 #69776 | P64: 69776 | R64: GB
A65: 6/26/2025 14:24 | B65: 6 | D65: W626478964872095 | G65: 1500 | I65: 20 | J65: -1480 | L65: USD | O65: 提款到水星
A66: 45664.909 | B66: 7 | C66: niihost | D66: Z701065639263464 | E66: completed | F66: alipay_cn | G66: 1.88 | H66: 1.88 | I66: 0.06 | J66: 1.82 | K66: 0 | L66: USD | O66: NiiHost - 账单编号 #70677 | P66: 70677 | R66: DE
A67: 45664.79 | B67: 7 | C67: niihost | D67: Z701962243974927 | E67: completed | F67: alipay_cn | G67: 17.99 | H67: 17.99 | I67: 0.53 | J67: 17.46 | K67: 0 | L67: USD | O67: NiiHost - Invoice #73545 | P67: 73545 | R67: JP
A68: 45664.74 | B68: 7 | C68: niihost | D68: Z701919425421093 | E68: completed | F68: alipay_cn | G68: 2.99 | H68: 2.99 | I68: 0.09 | J68: 2.9 | K68: 0 | L68: USD | O68: NiiHost - 账单编号 #73533 | P68: 73533 | R68: CN
A69: 45664.502 | B69: 7 | C69: niihost | D69: Z701714059864003 | E69: completed | F69: alipay_cn | G69: 2.99 | H69: 2.99 | I69: 0.09 | J69: 2.9 | K69: 2.99 | L69: USD | O69: NiiHost - 账单编号 #73521 | P69: 73521 | R69: JP
A70: 45664.405 | B70: 7 | C70: niihost | D70: Z701630254961494 | E70: completed | F70: alipay_cn | G70: 19.99 | H70: 19.99 | I70: 0.58 | J70: 19.41 | K70: 0 | L70: USD | O70: NiiHost - 账单编号 #73497 | P70: 73497 | R70: HK
A71: 45664.382 | B71: 7 | C71: niihost | D71: Z701610275374321 | E71: completed | F71: alipay_cn | G71: 1.88 | H71: 1.88 | I71: 0.06 | J71: 1.82 | K71: 0 | L71: USD | O71: NiiHost - 账单编号 #70869 | P71: 70869 | R71: FR
A72: 45664.345 | B72: 7 | C72: niihost | D72: Z701578661990572 | E72: completed | F72: alipay_cn | G72: 25.25 | H72: 25.25 | I72: 0.74 | J72: 24.51 | K72: 0 | L72: USD | O72: NiiHost - 账单编号 #73485 | P72: 73485 | R72: HK
A73: 45664.313 | B73: 7 | C73: niihost | D73: Z701550709359034 | E73: completed | F73: alipay_cn | G73: 1.99 | H73: 1.99 | I73: 0.06 | J73: 1.93 | K73: 1.99 | L73: USD | O73: NiiHost - 账单编号 #73461 | P73: 73461 | R73: JP
A74: 45695.97 | B74: 7 | C74: niihost | D74: Z702982380585107 | E74: completed | F74: alipay_cn | G74: 9.99 | H74: 9.99 | I74: 0.29 | J74: 9.7 | K74: 0 | L74: USD | O74: NiiHost - 账单编号 #73809 | P74: 73809 | R74: US
A75: 45695.652 | B75: 7 | C75: niihost | D75: Z702707949637319 | E75: completed | F75: alipay_cn | G75: 20.69 | H75: 20.69 | I75: 0.6 | J75: 20.09 | K75: 0 | L75: USD | O75: NiiHost - 账单编号 #73797 | P75: 73797 | R75: CN
A76: 45695.644 | B76: 7 | C76: niihost | D76: Z702700469729964 | E76: completed | F76: alipay_cn | G76: 2.49 | H76: 2.49 | I76: 0.08 | J76: 2.41 | K76: 0 | L76: USD | O76: NiiHost - 账单编号 #73785 | P76: 73785 | R76: HK
A77: 45695.556 | B77: 7 | C77: niihost | D77: Z702624992036235 | E77: completed | F77: alipay_cn | G77: 59.49 | H77: 59.49 | I77: 1.73 | J77: 57.76 | K77: 13.58 | L77: USD | O77: NiiHost - 账单编号 #73773 | P77: 73773 | R77: CN
... A91: 45784.33 | B91: 7 | C91: niihost | D91: Z705021102785439 | E91: completed | F91: alipay_cn | G91: 7.99 | H91: 7.99 | I91: 0.24 | J91: 7.75 | K91: 0 | L91: USD | O91: NiiHost - 账单编号 #74338 | P91: 74338 | R91: US
A92: 45784.217 | B92: 7 | C92: niihost | D92: R705924257034783 | E92: refunded | F92: alipay_cn | G92: -2.49 | H92: -2.49 | I92: 0.5 | J92: -2.49 | K92: 1.99 | L92: USD | O92: refund Z701550709359034 | P92: 73461 | Q92: Z701550709359034 | R92: JP
A93: 45784.217 | B93: 7 | C93: niihost | D93: R705923696392307 | E93: refunded | F93: alipay_cn | G93: -3.49 | H93: -3.49 | I93: 0.5 | J93: -3.49 | K93: 2.99 | L93: USD | O93: refund Z701714059864003 | P93: 73521 | Q93: Z701714059864003 | R93: JP
A94: 45815.31 | B94: 7 | C94: niihost | D94: Z706867824918247 | E94: completed | F94: alipay_cn | G94: 2.99 | H94: 2.99 | I94: 0.09 | J94: 2.9 | K94: 0 | L94: USD | O94: NiiHost - 账单编号 #74470 | P94: 74470 | R94: CN
A95: 45815.251 | B95: 7 | C95: niihost | D95: R706817423432023 | E95: refunded | F95: alipay_cn | G95: -4.99 | H95: -4.99 | I95: 0.5 | J95: -4.99 | K95: 4.49 | L95: USD | O95: refund Z704332300843799 | P95: 74122 | Q95: Z704332300843799 | R95: JP
A96: 45876.626 | B96: 7 | C96: niihost | D96: Z708868865858392 | E96: completed | F96: alipay_cn | G96: 2.99 | H96: 2.99 | I96: 0.09 | J96: 2.9 | K96: 2.99 | L96: USD | O96: NiiHost - 账单编号 #74734 | P96: 74734 | R96: JP
A97: 45937.285 | B97: 7 | C97: niihost | D97: Z710302332448701 | E97: completed | F97: alipay_cn | G97: 2.99 | H97: 2.99 | I97: 0.09 | J97: 2.9 | K97: 0 | L97: USD | O97: NiiHost - 账单编号 #75034 | P97: 75034 | R97: CN
A98: 45937.126 | B98: 7 | C98: niihost | D98: R710165424020210 | E98: refunded | F98: alipay_cn | G98: -3.49 | H98: -3.49 | I98: 0.5 | J98: -3.49 | K98: 2.99 | L98: USD | O98: refund Z708868865858392 | P98: 74734 | Q98: Z708868865858392 | R98: JP
A99: 45998.759 | B99: 7 | C99: niihost | D99: Z712439933472443 | E99: completed | F99: alipay_cn | G99: 26.99 | H99: 26.99 | I99: 0.79 | J99: 26.2 | K99: 26.2 | L99: USD | O99: NiiHost - 账单编号 #75418 | P99: 75418 | R99: HK
A100: 45998.274 | B100: 7 | C100: niihost | D100: Z712021194947958 | E100: completed | F100: alipay_cn | G100: 20.75 | H100: 20.75 | I100: 0.61 | J100: 20.14 | K100: 0 | L100: USD | O100: NiiHost - Invoice #74422 | P100: 74422 | R100: CN
A101: 7/13/2025 17:08 | B101: 7 | C101: niihost | D101: Z713265029309014 | E101: completed | F101: alipay_cn | G101: 4.54 | H101: 4.54 | I101: 0.14 | J101: 4.4 | K101: 0 | L101: USD | O101: NiiHost - 账单编号 #75490 | P101: 75490 | R101: HK
A102: 7/13/2025 13:06 | B102: 7 | C102: niihost | D102: Z713119725852549 | E102: completed | F102: alipay_cn | G102: 90.34 | H102: 90.34 | I102: 2.62 | J102: 87.72 | K102: 0 | L102: USD | O102: NiiHost - 账单编号 #75478 | P102: 75478 | R102: JP
A103: 7/14/2025 17:26 | B103: 7 | C103: niihost | D103: R714139864845116 | E103: refunded | F103: alipay_cn | G103: -3.49 | H103: -3.49 | I103: 0.5 | J103: -3.49 | K103: 2.99 | L103: USD | O103: refund Z714099657760580 | P103: 75634 | Q103: Z714099657760580 | R103: SG
A104: 7/14/2025 16:19 | B104: 7 | C104: niihost | D104: Z714099657760580 | E104: completed | F104: alipay_cn | G104: 2.99 | H104: 2.99 | I104: 0.09 | J104: 2.9 | K104: 2.99 | L104: USD | O104: NiiHost - 账单编号 #75634 | P104: 75634 | R104: SG
A105: 7/14/2025 12:00 | B105: 7 | C105: niihost | D105: Z714944246647355 | E105: completed | F105: alipay_cn | G105: 3.99 | H105: 3.99 | I105: 0.12 | J105: 3.87 | K105: 0 | L105: USD | O105: NiiHost - 账单编号 #75598 | P105: 75598 | R105: CA
A106: 7/15/2025 17:20 | B106: 7 | C106: niihost | D106: Z715000481464956 | E106: completed | F106: alipay_cn | G106: 118.9 | H106: 118.9 | I106: 3.45 | J106: 115.45 | K106: 112.96 | L106: USD | O106: NiiHost - 账单编号 #75826 | P106: 75826 | R106: CN
A107: 7/16/2025 16:37 | B107: 7 | C107: niihost | D107: Z716838664290708 | E107: completed | F107: alipay_cn | G107: 7.99 | H107: 7.99 | I107: 0.24 | J107: 7.75 | K107: 0 | L107: USD | O107: NiiHost - 账单编号 #76066 | P107: 76066 | R107: JP
A108: 7/16/2025 16:19 | B108: 7 | C108: niihost | D108: Z716827671507064 | E108: completed | F108: alipay_cn | G108: 7.99 | H108: 7.99 | I108: 0.24 | J108: 7.75 | K108: 0 | L108: USD | O108: NiiHost - 账单编号 #76054 | P108: 76054 | R108: US
A109: 7/16/2025 7:31 | B109: 7 | C109: niihost | D109: Z716511084635875 | E109: completed | F109: alipay_cn | G109: 20.69 | H109: 20.69 | I109: 0.6 | J109: 20.09 | K109: 0 | L109: USD | O109: NiiHost - 账单编号 #69596 | P109: 69596 | R109: HK
A110: 7/17/2025 8:18 | B110: 7 | C110: niihost | D110: Z717403056427663 | E110: completed | F110: alipay_cn | G110: 20.69 | H110: 20.69 | I110: 0.6 | J110: 20.09 | K110: 0 | L110: USD | O110: NiiHost - 账单编号 #76174 | P110: 76174 | R110: HK
A111: 7/17/2025 4:44 | B111: 7 | C111: niihost | D111: Z717274602747649 | E111: completed | F111: alipay_cn | G111: 22.99 | H111: 22.99 | I111: 0.67 | J111: 22.32 | K111: 0 | L111: USD | O111: NiiHost - 账单编号 #76162 | P111: 76162 | R111: BR
A112: 7/18/2025 12:44 | B112: 7 | C112: niihost | D112: Z718426673667828 | E112: completed | F112: alipay_cn | G112: 20.71 | H112: 20.71 | I112: 0.6 | J112: 20.11 | K112: 0 | L112: USD | O112: NiiHost - 账单编号 #74314 | P112: 74314 | R112: HK
A113: 7/18/2025 9:55 | B113: 7 | C113: niihost | D113: Z718325239212137 | E113: completed | F113: alipay_cn | G113: 6.49 | H113: 6.49 | I113: 0.19 | J113: 6.3 | K113: 0 | L113: USD | O113: NiiHost - 账单编号 #76426 | P113: 76426 | R113: CN
A114: 7/18/2025 6:15 | B114: 7 | C114: niihost | D114: R718193155338194 | E114: refunded | F114: alipay_cn | G114: -26.7 | H114: -26.7 | I114: 0.5 | J114: -26.7 | K114: 26.2 | L114: USD | O114: refund Z712439933472443 | P114: 75418 | Q114: Z712439933472443 | R114: HK
A115: 7/19/2025 8:34 | B115: 7 | C115: niihost | D115: Z719140748696575 | E115: completed | F115: alipay_cn | G115: 5.99 | H115: 5.99 | I115: 0.18 | J115: 5.81 | K115: 0 | L115: USD | O115: NiiHost - 账单编号 #73893 | P115: 73893 | R115: HK
A116: 7/20/2025 16:26 | B116: 7 | C116: niihost | D116: Z720287978975449 | E116: completed | F116: alipay_cn | G116: 2.79 | H116: 2.79 | I116: 0.08 | J116: 2.71 | K116: 0 | L116: USD | O116: NiiHost - 账单编号 #71397 | P116: 71397 | R116: CN
A117: 7/20/2025 12:55 | B117: 7 | C117: niihost | D117: Z720161218366049 | E117: completed | F117: alipay_cn | G117: 8.99 | H117: 8.99 | I117: 0.26 | J117: 8.73 | K117: 0 | L117: USD | O117: NiiHost - Invoice #74530 | P117: 74530 | R117: JP
A118: 7/21/2025 10:32 | B118: 7 | C118: niihost | D118: Z721939521541896 | E118: completed | F118: alipay_cn | G118: 9.99 | H118: 9.99 | I118: 0.29 | J118: 9.7 | K118: 0 | L118: USD | O118: NiiHost - 账单编号 #76834 | P118: 76834 | R118: US
A119: 7/25/2025 16:51 | B119: 7 | C119: niihost | D119: Z725622867274456 | E119: completed | F119: alipay_cn | G119: 9.99 | H119: 9.99 | I119: 0.29 | J119: 9.7 | K119: 0 | L119: USD | O119: NiiHost - 账单编号 #75886 | P119: 75886 | R119: PH
A120: 7/26/2025 17:08 | B120: 7 | C120: niihost | D120: Z726497284941825 | E120: completed | F120: alipay_cn | G120: 3.99 | H120: 3.99 | I120: 0.12 | J120: 3.87 | K120: 0 | L120: USD | O120: NiiHost - 账单编号 #77734 | P120: 77734 | R120: HK
A121: 7/27/2025 17:51 | B121: 7 | C121: niihost | D121: Z727386618711139 | E121: completed | F121: alipay_cn | G121: 20.69 | H121: 20.69 | I121: 0.6 | J121: 20.09 | K121: 0 | L121: USD | O121: NiiHost - 账单编号 #77938 | P121: 77938 | R121: SG
A122: 7/28/2025 15:18 | B122: 7 | C122: niihost | D122: R728159102779636 | E122: refunded | F122: alipay_cn | G122: -14.08 | H122: -14.08 | I122: 0.5 | J122: -14.08 | K122: 13.58 | L122: USD | O122: refund Z702624992036235 | P122: 73773 | Q122: Z702624992036235 | R122: CN
A123: 7/28/2025 15:14 | B123: 7 | C123: niihost | D123: R728156786183859 | E123: refunded | F123: alipay_cn | G123: -113.46 | H123: -113.46 | I123: 0.5 | J123: -113.46 | K123: 112.96 | L123: USD | O123: refund Z715000481464956 | P123: 75826 | Q123: Z715000481464956 | R123: CN
A124: 7/30/2025 9:06 | B124: 7 | C124: niihost | D124: Z730663904730290 | E124: completed | F124: alipay_cn | G124: 17.27 | H124: 17.27 | I124: 0.5 | J124: 16.77 | K124: 0 | L124: USD | O124: NiiHost - 账单编号 #78370 | P124: 78370 | R124: JP
A125: 45665.458 | B125: 8 | C125: niihost | D125: Z801460501733066 | E125: completed | F125: alipay_cn | G125: 54.74 | H125: 54.74 | I125: 1.59 | J125: 53.15 | K125: 0 | L125: USD | O125: NiiHost - 账单编号 #76546 | P125: 76546 | R125: HK
A126: 45724.608 | B126: 8 | C126: niihost | D126: Z803317469652038 | E126: completed | F126: alipay_cn | G126: 1 | H126: 1 | I126: 0.03 | J126: 0.97 | K126: 0 | L126: USD | O126: NiiHost - 账单编号 #69356 | P126: 69356 | R126: HK
A127: 45724.377 | B127: 8 | C127: niihost | D127: Z803117931992261 | E127: completed | F127: alipay_cn | G127: 2.01 | H127: 2.01 | I127: 0.06 | J127: 1.95 | K127: 0 | L127: USD | O127: NiiHost - 账单编号 #78538 | P127: 78538 | R127: JP
A128: 45724.176 | B128: 8 | C128: niihost | D128: Z803944365059993 | E128: completed | F128: alipay_cn | G128: 15 | H128: 15 | I128: 0.44 | J128: 14.56 | K128: 0 | L128: USD | O128: NiiHost - 账单编号 #79258 | P128: 79258 | R128: GB
...

Sheet TUTU账目
A1: 序号 | B1: 对象 | C1: 详情 | D1: 账户 | E1: 收入 | F1: 收入日期 | G1: 支出 | H1: 支出日期 | I1: 核实 | J1: 经手人 | K1: 备注
A2: 1 | B2: TUTU | C2: 快车道服务费INV-001874 | D2: Peter | E2: 364.68 | F2: 45468 | G2: 364.68 | H2: 45468 | I2: 已核查 | J2: Thuny
A3: 2 | B3: TUTU | C3: 快车道服务费INV-001891 | D3: Peter | E3: 414.58 | F3: 45474 | G3: 414.58 | H3: 45474 | I3: 已核查 | J3: Thuny
A4: 3 | B4: TUTU | C4: 快车道服务费INV-002005 | D4: Peter | E4: 346.28 | F4: 45504 | G4: 346.28 | H4: 45504 | I4: 已核查 | J4: Thuny
A5: 4 | B5: TUTU | C5: 快车道服务费INV-002135 | D5: Peter | E5: 441.28 | F5: 45535 | G5: 441.28 | H5: 45535 | I5: 已核查 | J5: Thuny
A6: 5 | B6: TUTU | C6: 快车道服务费INV-002275 | D6: Peter | E6: 364.68 | F6: 45536 | G6: 364.68 | H6: 45536 | I6: 已核查 | J6: Thuny
A7: 6 | B7: TUTU | C7: 快车道服务费INV-002435 | D7: Peter | E7: 404.58 | F7: 45596 | G7: 404.58 | H7: 45596 | I7: 已核查 | J7: Thuny
A8: 7 | B8: TUTU | C8: 快车道服务费INV-002603 | D8: Peter | G8: 402.68 | H8: 45626
A9: 8 | B9: TUTU | C9: 快车道服务费INV-002759 | D9: Peter | G9: 409.14 | H9: 45657
A10: 9 | B10: TUTU | C10: 快车道服务费INV-002927 | D10: Peter | G10: 411.8 | H10: 45682
A11: 10 | B11: TUTU | C11: 快车道服务费INV-003095 | D11: Peter | G11: 409.9 | H11: 45716
A12: 11 | B12: TUTU | C12: 快车道服务费INV-003276 | D12: Peter | G12: 401.4 | H12: 45747
A13: 12 | B13: TUTU | C13: 快车道服务费INV-003479 | D13: Peter | G13: 400.12 | H13: 45777
A14: 13 | B14: TUTU | C14: 快车道服务费INV-003674 | D14: Peter | G14: $395.10 | H14: 45811
A15: 14 | B15: TUTU | C15: 快车道服务费INV-003861 | D15: Peter | G15: 374.696 | H15: 45843
A16: 15 | B16: TUTU | C16: 快车道服务费INV-004066 | D16: Peter | G16: 374.76 | H16: 45873
A17: 16 | B17: TUTU | C17: 快车道服务费INV-004278 | D17: Peter | G17: 374.758 | H17: 45907
A18: 17 | B18: TUTU | C18: 快车道服务费INV-004512 | D18: Peter | G18: 374.758 | H18: 45939
A19: 18 | B19: TUTU | C19: 快车道服务费INV-004765 | D19: Peter | G19: 374.787 | H19: 45964
A20: 19 | B20: TUTU | C20: 快车道服务费INV-004988 | D20: Peter | G20: 374.988 | H20: 45992
A21: 20 | B21: TUTU | C21: KURUN 18684，18685 | D21: Peter | G21: 280 | H21: 46003
A22: 21 | B22: TUTU | C22: 快车道服务费INV-005233 | D22: Peter | G22: 373.117 | H22: 46022
A26: 合计 | E26: =SUM(E2:E17) -> 2336.08 | G26: =SUM(G2:G25) -> 7672.984

Sheet 供应商账单
A1: 序号 | B1: 商户 | C1: 账单号 | D1: Year | E1: M | F1: Due Date | G1: Balance Due | H1: power-T | I1: power-N | J1: IPV4-T | K1: IPV4-N | L1: BW | M1: BW-T | N1: BWH-N | O1: 罚金及其它 | P1: SUM | Q1: TuTu | R1: NiiHost | S1: 支付方式 | T1: 支付日期 | U1: 支付情况
A2: 1 | B2: KCD-HK | C2: INV-001874 | D2: 2024 | E2: 6 | F2: 45468 | G2: 631.98 | H2: 314.28 | I2: 164.9 | J2: 50.4 | K2: 102.4 | L2: 0 | M2: 0 | N2: 0 | O2: 0 | P2: =SUM(H2:L2,O2) -> 631.98 | Q2: =SUM(H2,J2,M2) -> 364.68 | R2: =SUM(I2,K2,N2,O2) -> 267.3 | S2: 水星 | U2: 已支付
A3: 2 | B3: KCD-HK | C3: INV-001891 | D3: 2024 | E3: 7 | F3: 45474 | G3: 948.86 | H3: 314.28 | I3: 329.8 | J3: 50.4 | K3: 192 | L3: 62.38 | M3: 49.9 | N3: 12.48 | O3: 0 | P3: =SUM(H3:L3,O3) -> 948.86 | Q3: =SUM(H3,J3,M3) -> 414.58 | R3: =SUM(I3,K3,N3,O3) -> 534.28 | S3: 水星 | U3: 已支付
A4: 3 | B4: KCD-HK | C4: INV-002005 | D4: 2024 | E4: 7 | F4: 45504 | G4: 868.08 | H4: 314.28 | I4: 329.8 | J4: 32 | K4: 192 | L4: 0 | M4: 0 | O4: 0 | P4: =SUM(H4:L4,O4) -> 868.08 | Q4: =SUM(H4,J4,M4) -> 346.28 | R4: =SUM(I4,K4,N4,O4) -> 521.8 | S4: 水星 | U4: 已支付
A5: 4 | B5: KCD-HK | C5: INV-002135 | D5: 2024 | E5: 8 | F5: 45535 | G5: 1269.46 | H5: 314.28 | I5: 329.8 | J5: 50.4 | K5: 192 | L5: 382.98 | M5: 76.6 | N5: 306.38 | O5: 2 | P5: =SUM(H5:L5,O5) -> 1271.46 | Q5: =SUM(H5,J5,M5) -> 441.28 | R5: =SUM(I5,K5,N5,O5) -> 830.18 | S5: 水星 | U5: 已支付
A6: 5 | B6: KCD-HK | C6: INV-002275 | D6: 2024 | E6: 9 | F6: 45536 | G6: 886.48 | H6: 314.28 | I6: 329.8 | J6: 50.4 | K6: 192 | L6: 0 | M6: 0 | N6: 0 | O6: 0 | P6: =SUM(H6:L6,O6) -> 886.48 | Q6: =SUM(H6,J6,M6) -> 364.68 | R6: =SUM(I6,K6,N6,O6) -> 521.8 | S6: 水星 | U6: 已支付
A7: 6 | B7: PQ | C7: 73341 | D7: 2024 | E7: 9 | F7: 45547 | G7: 210 | H7: 0 | I7: 210 | J7: 0 | K7: 0 | L7: 0 | M7: 0 | N7: 0 | O7: 0 | P7: =SUM(H7:L7,O7) -> 210 | Q7: =SUM(H7,J7,M7) -> 0 | R7: =SUM(I7,K7,N7,O7) -> 210 | S7: 水星 | U7: 已支付
A8: 7 | B8: KCD-HK | C8: INV-002435 | D8: 2024 | E8: 10 | F8: 45596 | G8: 1285.48 | H8: 314.28 | I8: 329.8 | J8: 50.4 | K8: 192 | L8: 399 | M8: =IF(B8="KCD-HK",L8*0.1,0) -> 39.9 | N8: =IF(B8="KCD-HK",L8*0.9,L8) -> 359.1 | O8: 0 | P8: =SUM(H8:L8,O8) -> 1285.48 | Q8: =SUM(H8,J8,M8) -> 404.58 | R8: =SUM(I8,K8,N8,O8) -> 880.9 | S8: 水星 | U8: 已支付
A9: 8 | B9: PQ | C9: 75927 | D9: 2024 | E9: 10 | F9: 45596 | G9: 210 | H9: 0 | I9: 210 | J9: 0 | K9: 0 | L9: 0 | M9: =IF(B9="KCD-HK",L9*0.1,0) -> 0 | N9: =IF(B9="KCD-HK",L9*0.9,L9) -> 0 | O9: 0 | P9: =SUM(H9:L9,O9) -> 210 | Q9: =SUM(H9,J9,M9) -> 0 | R9: =SUM(I9,K9,N9,O9) -> 210 | S9: 水星 | U9: 已支付
A10: 9 | B10: PQ | C10: 75928 | D10: 2024 | E10: 11 | F10: 45621 | G10: 250 | H10: 0 | I10: 250 | J10: 0 | K10: 0 | L10: 0 | M10: =IF(B10="KCD-HK",L10*0.1,0) -> 0 | N10: =IF(B10="KCD-HK",L10*0.9,L10) -> 0 | O10: 0 | P10: =SUM(H10:L10,O10) -> 250 | Q10: =SUM(H10,J10,M10) -> 0 | R10: =SUM(I10,K10,N10,O10) -> 250 | S10: 水星 | U10: 已支付
A11: 10 | B11: KCD-HK | C11: INV-002603 | D11: 2024 | E11: 11 | F11: 45626 | G11: 1266.48 | H11: 314.28 | I11: 329.8 | J11: 50.4 | K11: 192 | L11: 380 | M11: =IF(B11="KCD-HK",L11*0.1,0) -> 38 | N11: =IF(B11="KCD-HK",L11*0.9,L11) -> 342 | O11: 20 | P11: =SUM(H11:L11,O11) -> 1286.48 | Q11: =SUM(H11,J11,M11) -> 402.68 | R11: =SUM(I11,K11,N11,O11) -> 883.8 | S11: 水星 | U11: 已支付
A12: 11 | B12: PQ | C12: 77921 | D12: 2024 | E12: 11 | F12: 45624 | G12: 206.49 | H12: 0 | I12: 206.49 | J12: 0 | K12: 0 | L12: 0 | M12: =IF(B12="KCD-HK",L12*0.1,0) -> 0 | N12: =IF(B12="KCD-HK",L12*0.9,L12) -> 0 | O12: 0 | P12: =SUM(H12:L12,O12) -> 206.49 | Q12: =SUM(H12,J12,M12) -> 0 | R12: =SUM(I12,K12,N12,O12) -> 206.49 | S12: WISE | U12: 通过WISE已支付
A13: 12 | B13: KCD-HK | C13: INV-002759 | D13: 2024 | E13: 12 | F13: 45657 | G13: 1395.08 | H13: 314.28 | I13: 329.8 | J13: 50.4 | K13: 256 | L13: 444.6 | M13: =IF(B13="KCD-HK",L13*0.1,0) -> 44.46 | N13: =IF(B13="KCD-HK",L13*0.9,L13) -> 400.14 | O13: 0 | P13: =SUM(H13:L13,O13) -> 1395.08 | Q13: =SUM(H13,J13,M13) -> 409.14 | R13: =SUM(I13,K13,N13,O13) -> 985.94 | S13: WISE | U13: 通过WISE已支付
A14: 13 | B14: PQ | C14: 77921 | D14: 2024 | E14: 12 | F14: 45635 | G14: 206.49 | H14: 0 | I14: 206.49 | J14: 0 | K14: 0 | L14: 0 | M14: =IF(B14="KCD-HK",L14*0.1,0) -> 0 | N14: =IF(B14="KCD-HK",L14*0.9,L14) -> 0 | O14: 0 | P14: =SUM(H14:L14,O14) -> 206.49 | Q14: =SUM(H14,J14,M14) -> 0 | R14: =SUM(I14,K14,N14,O14) -> 206.49 | S14: WISE | U14: 通过WISE已支付
A15: 14 | B15: PQ | C15: 78591 | D15: 2024 | E15: 12 | F15: 45650 | G15: 246.62 | H15: 0 | I15: 246.62 | J15: 0 | K15: 0 | L15: 0 | M15: =IF(B15="KCD-HK",L15*0.1,0) -> 0 | N15: =IF(B15="KCD-HK",L15*0.9,L15) -> 0 | O15: 0 | P15: =SUM(H15:L15,O15) -> 246.62 | Q15: =SUM(H15,J15,M15) -> 0 | R15: =SUM(I15,K15,N15,O15) -> 246.62 | S15: WISE | U15: 通过WISE已支付
A16: 15 | B16: PQ | C16: 79419 | D16: 2025 | E16: 1 | F16: 45669 | G16: 204.56 | H16: 0 | I16: 204.56 | J16: 0 | K16: 0 | L16: 0 | M16: =IF(B16="KCD-HK",L16*0.1,0) -> 0 | N16: =IF(B16="KCD-HK",L16*0.9,L16) -> 0 | O16: 0 | P16: =SUM(H16:L16,O16) -> 204.56 | Q16: =SUM(H16,J16,M16) -> 0 | R16: =SUM(I16,K16,N16,O16) -> 204.56 | S16: WISE | U16: 通过WISE已支付
A17: 16 | B17: KCD-HK | C17: INV-002927 | D17: 2025 | E17: 1 | F17: 45688 | G17: 1421.68 | H17: 314.28 | I17: 329.8 | J17: 50.4 | K17: 256 | L17: 471.2 | M17: =IF(B17="KCD-HK",L17*0.1,0) -> 47.12 | N17: =IF(B17="KCD-HK",L17*0.9,L17) -> 424.08 | O17: 0 | P17: =SUM(H17:L17,O17) -> 1421.68 | Q17: =SUM(H17,J17,M17) -> 411.8 | R17: =SUM(I17,K17,N17,O17) -> 1009.88 | S17: WISE | U17: 通过WISE已支付
A18: 17 | B18: KCD-HK | C18: INV-003010 | D18: 2025 | E18: 1 | F18: 45681 | G18: 2 | H18: 0 | I18: 0 | J18: 0 | K18: 0 | L18: 0 | M18: =IF(B18="KCD-HK",L18*0.1,0) -> 0 | N18: =IF(B18="KCD-HK",L18*0.9,L18) -> 0 | O18: 2 | P18: =SUM(H18:L18,O18) -> 2 | Q18: =SUM(H18,J18,M18) -> 0 | R18: =SUM(I18,K18,N18,O18) -> 2 | S18: WISE | U18: 通过WISE已支付
A19: 18 | B19: KCD-JP | C19: INV-003025 | D19: 2025 | E19: 1 | F19: 45679 | G19: 457.01 | H19: 0 | I19: 88.23 | J19: 0 | K19: 17.42 | L19: 36.76 | M19: =IF(B19="KCD-HK",L19*0.1,0) -> 0 | N19: =IF(B19="KCD-HK",L19*0.9,L19) -> 36.76 | O19: 314.6 | P19: =SUM(H19:L19,O19) -> 457.01 | Q19: =SUM(H19,J19,M19) -> 0 | R19: =SUM(I19,K19,N19,O19) -> 457.01 | S19: WISE | U19: 通过WISE已支付
A20: 19 | B20: KCD-IEPL | C20: INV-003029 | D20: 2025 | E20: 1 | F20: 45680 | G20: 1335.97 | H20: 0 | I20: 83.59 | J20: 0 | K20: 68.26 | L20: 1114.47 | M20: =IF(B20="KCD-HK",L20*0.1,0) -> 0 | N20: =IF(B20="KCD-HK",L20*0.9,L20) -> 1114.47 | O20: 69.65 | P20: =SUM(H20:L20,O20) -> 1335.97 | Q20: =SUM(H20,J20,M20) -> 0 | R20: =SUM(I20,K20,N20,O20) -> 1335.97 | S20: 水星 | U20: 通过水星已支付
A21: 20 | B21: KCD-IEPL | C21: INV-003029+ | D21: 2025 | E21: 1 | F21: 45680 | G21: 15.89 | H21: 0 | I21: 0 | J21: 0 | K21: 0 | L21: 15.89 | M21: =IF(B21="KCD-HK",L21*0.1,0) -> 0 | N21: =IF(B21="KCD-HK",L21*0.9,L21) -> 15.89 | O21: 0 | P21: =SUM(H21:L21,O21) -> 15.89 | Q21: =SUM(H21,J21,M21) -> 0 | R21: =SUM(I21,K21,N21,O21) -> 15.89 | S21: USTD | U21: 通过USTD支付
A22: 21 | B22: KCD-JP | C22: INV-003030 | D22: 2025 | E22: 1 | F22: 45688 | G22: 294.34 | H22: 0 | I22: 182.34 | J22: 0 | K22: 36 | L22: 76 | M22: =IF(B22="KCD-HK",L22*0.1,0) -> 0 | N22: =IF(B22="KCD-HK",L22*0.9,L22) -> 76 | O22: 0 | P22: =SUM(H22:L22,O22) -> 294.34 | Q22: =SUM(H22,J22,M22) -> 0 | R22: =SUM(I22,K22,N22,O22) -> 294.34 | S22: WISE | U22: 通过WISE已支付
A23: 22 | B23: PQ | C23: 80033 | D23: 2025 | E23: 1 | F23: 45682 | G23: 248.48 | H23: 0 | I23: 248.48 | J23: 0 | K23: 0 | L23: 0 | M23: =IF(B23="KCD-HK",L23*0.1,0) -> 0 | N23: =IF(B23="KCD-HK",L23*0.9,L23) -> 0 | O23: 0 | P23: =SUM(H23:L23,O23) -> 248.48 | Q23: =SUM(H23,J23,M23) -> 0 | R23: =SUM(I23,K23,N23,O23) -> 248.48 | S23: ALIPAY | U23: 通过支付宝已支付
A24: 23 | B24: PQ | C24: 80913 | D24: 2025 | E24: 2 | F24: 45699 | G24: 205.33 | H24: 0 | I24: 205.33 | J24: 0 | K24: 0 | L24: 0 | M24: =IF(B24="KCD-HK",L24*0.1,0) -> 0 | N24: =IF(B24="KCD-HK",L24*0.9,L24) -> 0 | O24: 0 | P24: =SUM(H24:L24,O24) -> 205.33 | Q24: =SUM(H24,J24,M24) -> 0 | R24: =SUM(I24,K24,N24,O24) -> 205.33 | S24: ALIPAY | U24: 通过支付宝已支付
A25: 24 | B25: PQ | C25: 81559 | D25: 2025 | E25: 2 | F25: 45712 | G25: 248.69 | H25: 0 | I25: 248.69 | J25: 0 | K25: 0 | L25: 0 | M25: =IF(B25="KCD-HK",L25*0.1,0) -> 0 | N25: =IF(B25="KCD-HK",L25*0.9,L25) -> 0 | O25: 0 | P25: =SUM(H25:L25,O25) -> 248.69 | Q25: =SUM(H25,J25,M25) -> 0 | R25: =SUM(I25,K25,N25,O25) -> 248.69 | S25: ALIPAY | U25: 通过支付宝已支付
A26: 25 | B26: KCD-IEPL | C26: INV-003170 | D26: 2025 | E26: 2 | F26: 45716 | G26: 2614.99 | H26: 0 | I26: 82.58 | J26: 0 | K26: 90.84 | L26: 2441.57 | M26: =IF(B26="KCD-HK",L26*0.1,0) -> 0 | N26: =IF(B26="KCD-HK",L26*0.9,L26) -> 2441.57 | O26: 0 | P26: =SUM(H26:L26,O26) -> 2614.99 | Q26: =SUM(H26,J26,M26) -> 0 | R26: =SUM(I26,K26,N26,O26) -> 2614.99 | S26: USTD | U26: 通过USTD支付1400美金，水星支付380美金，水星支付500
A27: 26 | B27: KCD-HK | C27: INV-003095 | D27: 2025 | E27: 2 | F27: 45716 | G27: 1402.68 | H27: 314.28 | I27: 329.8 | J27: 50.4 | K27: 256 | L27: 452.2 | M27: =IF(B27="KCD-HK",L27*0.1,0) -> 45.22 | N27: =IF(B27="KCD-HK",L27*0.9,L27) -> 406.98 | O27: 0 | P27: =SUM(H27:L27,O27) -> 1402.68 | Q27: =SUM(H27,J27,M27) -> 409.9 | R27: =SUM(I27,K27,N27,O27) -> 992.78 | S27: USTD | U27: 通过USTD支付
A28: 27 | B28: KCD-JP | C28: INV-003169 | D28: 2025 | E28: 2 | F28: 45716 | G28: 403.76 | H28: 0 | I28: 182.34 | J28: 0 | K28: 36 | L28: 76 | M28: =IF(B28="KCD-HK",L28*0.1,0) -> 0 | N28: =IF(B28="KCD-HK",L28*0.9,L28) -> 76 | O28: 109.42 | P28: =SUM(H28:L28,O28) -> 403.76 | Q28: =SUM(H28,J28,M28) -> 0 | R28: =SUM(I28,K28,N28,O28) -> 403.76 | S28: 水星 | U28: 通过水星支付
A29: 28 | B29: PQ | C29: 82617 | D29: 2025 | E29: 3 | F29: 45720 | G29: 119.19 | H29: 0 | I29: 119.19 | J29: 0 | K29: 0 | L29: 0 | M29: =IF(B29="KCD-HK",L29*0.1,0) -> 0 | N29: =IF(B29="KCD-HK",L29*0.9,L29) -> 0 | O29: 0 | P29: =SUM(H29:L29,O29) -> 119.19 | Q29: =SUM(H29,J29,M29) -> 0 | R29: =SUM(I29,K29,N29,O29) -> 119.19 | S29: ALIPAY | U29: 通过支付宝已支付866元
A30: 29 | B30: PQ | C30: 82947 | D30: 2025 | E30: 3 | F30: 45741 | G30: 426.81 | H30: 0 | I30: 426.81 | J30: 0 | K30: 0 | L30: 0 | M30: =IF(B30="KCD-HK",L30*0.1,0) -> 0 | N30: =IF(B30="KCD-HK",L30*0.9,L30) -> 0 | O30: 0 | P30: =SUM(H30:L30,O30) -> 426.81 | Q30: =SUM(H30,J30,M30) -> 0 | R30: =SUM(I30,K30,N30,O30) -> 426.81 | S30: ALIPAY | U30: 通过支付宝已支付3100元
A31: 30 | B31: KCD-HK | C31: INV-003276 | D31: 2025 | E31: 3 | F31: 45747 | G31: 1317.67 | H31: 314.28 | I31: 329.8 | J31: 50.4 | K31: 256 | L31: 367.19 | M31: =IF(B31="KCD-HK",L31*0.1,0) -> 36.719 | N31: =IF(B31="KCD-HK",L31*0.9,L31) -> 330.471 | O31: -230.86 | P31: =SUM(H31:L31,O31) -> 1086.81 | Q31: =SUM(H31,J31,M31) -> 401.399 | R31: =SUM(I31,K31,N31,O31) -> 685.411 | S31: 水星 | U31: 通过水星支付
A32: 31 | B32: KCD-JP | C32: INV-003345 | D32: 2025 | E32: 3 | F32: 45747 | G32: 324.42 | H32: 0 | I32: 182.34 | J32: 0 | K32: 36 | L32: 106.08 | M32: =IF(B32="KCD-HK",L32*0.1,0) -> 0 | N32: =IF(B32="KCD-HK",L32*0.9,L32) -> 106.08 | O32: 0 | P32: =SUM(H32:L32,O32) -> 324.42 | Q32: =SUM(H32,J32,M32) -> 0 | R32: =SUM(I32,K32,N32,O32) -> 324.42 | S32: 水星 | U32: 通过水星支付
A33: 32 | B33: KCD-IEPL | C33: INV-003407 | D33: 2025 | E33: 3 | F33: 45747 | G33: 631.65 | H33: 0 | I33: 101.49 | J33: 0 | K33: 137.76 | L33: 406.8 | M33: 0 | N33: 406.8 | O33: -14.41 | P33: =SUM(H33:L33,O33) -> 631.64 | Q33: =SUM(H33,J33,M33) -> 0 | R33: =SUM(I33,K33,N33,O33) -> 631.64 | S33: 水星 | U33: 通过水星支付
A34: 33 | B34: KCD-IEPL | C34: 押金 | D34: 2025 | E34: 4 | F34: 45749 | G34: 1012.54 | H34: 0 | I34: 0 | J34: 0 | K34: 0 | L34: 1012.54 | M34: 0 | N34: 1012.54 | P34: =SUM(H34:L34,O34) -> 1012.54 | Q34: =SUM(H34,J34,M34) -> 0 | R34: =SUM(I34,K34,N34,O34) -> 1012.54 | S34: 水星 | U34: 通过水星支付
A35: 34 | B35: PQ | C35: 83731 | D35: 2025 | E35: 4 | F35: 45758 | G35: 206.64 | H35: 0 | I35: 206.64 | J35: 0 | K35: 0 | L35: 0 | M35: =IF(B35="KCD-HK",L35*0.1,0) -> 0 | N35: =IF(B35="KCD-HK",L35*0.9,L35) -> 0 | O35: 0 | P35: =SUM(H35:L35,O35) -> 206.64 | Q35: =SUM(H35,J35,M35) -> 0 | R35: =SUM(I35,K35,N35,O35) -> 206.64 | S35: ALIPAY | U35: 通过支付宝已支付
A36: 35 | B36: PQ | C36: 84333 | D36: 2025 | E36: 4 | F36: 45772 | G36: 426.29 | H36: 0 | I36: 426.29 | J36: 0 | K36: 0 | L36: 0 | M36: 0 | N36: 0 | O36: 0 | P36: =SUM(H36:L36,O36) -> 426.29 | Q36: =SUM(H36,J36,M36) -> 0 | R36: =SUM(I36,K36,N36,O36) -> 426.29 | S36: ALIPAY | U36: 通过支付宝已支付
A37: 36 | B37: KCD-HK | C37: INV-003479 | D37: 2025 | E37: 4 | F37: 45777 | G37: 1387.43 | H37: 314.28 | I37: 344.34 | J37: 50.4 | K37: 256 | L37: 354.41 | M37: =IF(B37="KCD-HK",L37*0.1,0) -> 35.441 | N37: =IF(B37="KCD-HK",L37*0.9,L37) -> 318.969 | O37: 68 | P37: =SUM(H37:L37,O37) -> 1387.43 | Q37: =SUM(H37,J37,M37) -> 400.121 | R37: =SUM(I37,K37,N37,O37) -> 987.309 | S37: 水星 | T37: 45777 | U37: 本月账单扣除INV-003276当中的230.86，实为1156.57
A38: 37 | B38: KCD-IEPL | C38: INV-003610 | D38: 2025 | E38: 4 | F38: 45777 | G38: 1388.23 | H38: 0 | I38: 101.47 | J38: 0 | K38: 249.28 | L38: 1037.48 | M38: 0 | N38: 1037.48 | O38: -0.76 | P38: =SUM(H38:L38,O38) -> 1387.47 | Q38: =SUM(H38,J38,M38) -> 0 | R38: =SUM(I38,K38,N38,O38) -> 1387.47 | S38: 水星 | T38: 45782 | U38: 通过水星支付，-0.76为对方计算的汇率差，找平账单
A39: 38 | B39: KCD-IEPL | C39: INV-003407+ | D39: 2025 | E39: 4 | F39: 45777 | G39: 111.55 | H39: 0 | I39: 0 | J39: 0 | K39: 111.55 | L39: 0 | M39: 0 | N39: 0 | O39: 0 | P39: =SUM(H39:L39,O39) -> 111.55 | Q39: =SUM(H39,J39,M39) -> 0 | R39: =SUM(I39,K39,N39,O39) -> 111.55 | S39: 水星 | T39: 45782 | U39: 通过水星支付，4月份新增加的IP
A40: 39 | B40: KCD-JP | C40: INV-003345 | D40: 2025 | E40: 4 | F40: 45777 | G40: 324.42 | H40: 0 | I40: 182.34 | J40: 0 | K40: 36 | L40: 106.08 | M40: =IF(B40="KCD-HK",L40*0.1,0) -> 0 | N40: =IF(B40="KCD-HK",L40*0.9,L40) -> 106.08 | O40: 0 | P40: =SUM(H40:L40,O40) -> 324.42 | Q40: =SUM(H40,J40,M40) -> 0 | R40: =SUM(I40,K40,N40,O40) -> 324.42 | S40: 水星 | T40: 45782 | U40: 通过水星支付
A41: 40 | B41: PQ | C41: 83731 | D41: 2025 | E41: 5 | F41: 45790 | G41: 207.53 | H41: 0 | I41: 207.53 | J41: 0 | K41: 0 | L41: 0 | M41: =IF(B41="KCD-HK",L41*0.1,0) -> 0 | N41: =IF(B41="KCD-HK",L41*0.9,L41) -> 0 | O41: 0 | P41: =SUM(H41:L41,O41) -> 207.53 | Q41: =SUM(H41,J41,M41) -> 0 | R41: =SUM(I41,K41,N41,O41) -> 207.53 | S41: ALIPAY | T41: 45790 | U41: 通过支付宝已支付
A42: 41 | B42: KCD-JP | C42: INV-003736 | D42: 2025 | E42: 5 | F42: 45808 | G42: 537.26 | H42: 0 | I42: 182.34 | J42: 0 | K42: 36 | L42: 318.92 | M42: =IF(B42="KCD-HK",L42*0.1,0) -> 0 | N42: =IF(B42="KCD-HK",L42*0.9,L42) -> 318.92 | O42: 0 | P42: =SUM(H42:L42,O42) -> 537.26 | Q42: =SUM(H42,J42,M42) -> 0 | R42: =SUM(I42,K42,N42,O42) -> 537.26 | S42: WISE | T42: 45812 | U42: 通过wise支付367.26，2025年7月9日通过wise支付$170
A43: 42 | B43: PQ | C43: 85819 | D43: 2025 | E43: 5 | F43: 45772 | G43: 432.36 | H43: 0 | I43: 432.36 | J43: 0 | K43: 0 | L43: 0 | M43: 0 | N43: 0 | O43: 0 | P43: =SUM(H43:L43,O43) -> 432.36 | Q43: =SUM(H43,J43,M43) -> 0 | R43: =SUM(I43,K43,N43,O43) -> 432.36 | S43: ALIPAY | T43: 45802 | U43: 通过支付宝已支付
A44: 43 | B44: KCD-HK | C44: INV-003674 | D44: 2025 | E44: 6 | F44: 45811 | G44: 1123.5 | H44: 314.28 | I44: 198.66 | J44: 50.4 | K44: 256 | L44: 304.16 | M44: =IF(B44="KCD-HK",L44*0.1,0) -> 30.416 | N44: =IF(B44="KCD-HK",L44*0.9,L44) -> 273.744 | O44: 0 | P44: =SUM(H44:L44,O44) -> 1123.5 | Q44: =SUM(H44,J44,M44) -> 395.096 | R44: =SUM(I44,K44,N44,O44) -> 728.404 | S44: WISE | T44: 45812 | U44: 通过wise支付728.4，另外的395.1通过水星
A45: 44 | B45: KCD-IEPL | C45: INV-003737 | D45: 2025 | E45: 6 | F45: 45811 | G45: 1166.16 | H45: 0 | I45: 736.77 | J45: 0 | K45: 1000 | L45: 6664.59 | M45: 0 | N45: 6664.59 | O45: 0 | P45: =SUM(H45:K45,M45:O45) -> 8401.36 | Q45: =SUM(H45,J45,M45) -> 0 | R45: 1166.16 | S45: WISE | T45: 45812 | U45: 通过wise支付
A46: 45 | B46: PQ | C46: 86579 | D46: 2025 | E46: 6 | F46: 45819 | G46: 208.04 | H46: 0 | I46: 208.04 | J46: 0 | K46: 0 | L46: 0 | M46: =IF(B46="KCD-HK",L46*0.1,0) -> 0 | N46: =IF(B46="KCD-HK",L46*0.9,L46) -> 0 | O46: 0 | P46: =SUM(H46:L46,O46) -> 208.04 | Q46: =SUM(H46,J46,M46) -> 0 | R46: =SUM(I46,K46,N46,O46) -> 208.04 | S46: ALIPAY | T46: 45819 | U46: 通过支付宝已支付
A47: 46 | B47: PQ | C47: 87423 | D47: 2025 | E47: 6 | F47: 45832 | G47: 432.36 | H47: 0 | I47: 432.36 | J47: 0 | K47: 0 | L47: 0 | M47: 0 | N47: 0 | O47: 0 | P47: =SUM(H47:L47,O47) -> 432.36 | Q47: =SUM(H47,J47,M47) -> 0 | R47: =SUM(I47,K47,N47,O47) -> 432.36 | S47: ALIPAY | T47: 45832 | U47: 通过支付宝已支付
A48: 47 | B48: KCD-HK | C48: INV-003861 | D48: 2025 | E48: 7 | F48: 45840 | G48: 919.5 | H48: 314.28 | I48: 198.66 | J48: 50.4 | K48: 256 | L48: 100.16 | M48: =IF(B48="KCD-HK",L48*0.1,0) -> 10.016 | N48: =IF(B48="KCD-HK",L48*0.9,L48) -> 90.144 | O48: 0 | P48: =SUM(H48:L48,O48) -> 919.5 | Q48: =SUM(H48,J48,M48) -> 374.696 | R48: =SUM(I48,K48,N48,O48) -> 544.804 | S48: WISE | T48: 45843 | U48: 通过wise支付
A49: 48 | B49: KCD-JP | C49: INV-003920 | D49: 2025 | E49: 7 | F49: 45840 | G49: 558.95 | H49: 0 | I49: 182.34 | J49: 0 | K49: 36 | L49: 340.62 | M49: =IF(B49="KCD-HK",L49*0.1,0) -> 0 | N49: =IF(B49="KCD-HK",L49*0.9,L49) -> 340.62 | O49: 0 | P49: =SUM(H49:L49,O49) -> 558.96 | Q49: =SUM(H49,J49,M49) -> 0 | R49: =SUM(I49,K49,N49,O49) -> 558.96 | S49: WISE | T49: 45847 | U49: 通过wise支付
A50: 49 | B50: KCD-IEPL | C50: INV-003737 | D50: 2025 | E50: 7 | F50: 45840 | G50: 1137.14 | H50: 0 | I50: 736.77 | J50: 0 | K50: 1000 | L50: 3411.15 | M50: 0 | N50: 3411.15 | O50: 0 | P50: =SUM(H50:K50,M50:O50) -> 5147.92 | Q50: =SUM(H50,J50,M50) -> 0 | R50: 1137.14 | S50: WISE | T50: 45843 | U50: 通过wise支付
A51: 50 | B51: QZ-IEPL | C51: 7.10-7.31预付 | D51: 2025 | E51: 7 | F51: 2025-7010 | H51: 0 | I51: 1300 | J51: 0 | K51: 750 | L51: 6364 | M51: 0 | N51: 6363 | O51: 0 | P51: =SUM(H51:K51,M51:O51) -> 8413 | Q51: =SUM(H51,J51,M51) -> 0 | R51: 1185.14 | S51: USTD | T51: 45848 | U51: 通过USDT支付
A52: 51 | B52: PQ | C52: 89013 | D52: 2025 | E52: 7 | F52: 45863 | G52: 812.13 | H52: 0 | I52: 812.13 | J52: 0 | K52: 0 | L52: 0 | M52: 0 | N52: 0 | O52: 0 | P52: =SUM(H52:L52,O52) -> 812.13 | Q52: =SUM(H52,J52,M52) -> 0 | R52: =SUM(I52,K52,N52,O52) -> 812.13 | S52: ALIPAY | T52: 45863 | U52: 通过支付宝已支付
A53: 52 | B53: KCD-IEPL | C53: INV-004124 | D53: 2025 | E53: 8 | F53: 45873 | G53: 6635.93 | H53: 0 | I53: 775.48 | J53: 0 | K53: 8670 | L53: 16375.98 | M53: 0 | N53: 37375.98 | O53: 360 | P53: =SUM(H53:K53,M53:O53) -> 47181.46 | Q53: =SUM(H53,J53,M53) -> 0 | R53: 6635.93 | S53: WISE | T53: 45874 | U53: 2025年8月2日wise支付2600.29（18,752.75），2025年8月13日水星支付3,959.95（28,428.71）
A54: 53 | B54: KCD-HK | C54: INV-004066 | D54: 2025 | E54: 8 | F54: 45873 | G54: 919.5 | H54: 314.28 | I54: 198.66 | J54: 50.4 | K54: 256 | L54: 100.81 | M54: =IF(B54="KCD-HK",L54*0.1,0) -> 10.081 | N54: =IF(B54="KCD-HK",L54*0.9,L54) -> 90.729 | O54: 0 | P54: =SUM(H54:L54,O54) -> 920.15 | Q54: =SUM(H54,J54,M54) -> 374.761 | R54: =SUM(I54,K54,N54,O54) -> 545.389 | S54: WISE | T54: 45874
A55: 54 | B55: KCD-JP | C55: INV-004123 | D55: 2025 | E55: 8 | F55: 45873 | G55: 558.95 | H55: 0 | I55: 182.34 | J55: 0 | K55: 36 | L55: 228.09 | M55: =IF(B55="KCD-HK",L55*0.1,0) -> 0 | N55: =IF(B55="KCD-HK",L55*0.9,L55) -> 228.09 | O55: 0 | P55: =SUM(H55:L55,O55) -> 446.43 | Q55: =SUM(H55,J55,M55) -> 0 | R55: =SUM(I55,K55,N55,O55) -> 446.43 | S55: WISE | T55: 45874
A56: 55 | B56: QZ-IEPL | C56: 7.10-7.31实销 | D56: 2025 | E56: 8 | F56: 45873 | H56: 0 | I56: 1300 | J56: 0 | K56: 750 | L56: 4636 | M56: 0 | N56: 4636 | O56: -8413 | P56: =(I56+L56)/31*22+K56+O56 -> -3450.3548 | Q56: =SUM(H56,J56,M56) -> 0 | S56: 冲抵 | U56: 7.10-7.31预付还剩余486.18
A57: 56 | B57: QZ-IEPL | C57: 8月预付 | D57: 2025 | E57: 8 | F57: 45873 | G57: 1204.1754 | H57: 0 | I57: 1300 | J57: 0 | K57: 1200 | L57: 9500 | M57: 0 | N57: 9500 | O57: -3450.3548 | P57: =(I57+L57)+K57+O57 -> 8549.6452 | Q57: =SUM(H57,J57,M57) -> 0 | R57: =P57/7.1 -> 1204.1754 | S57: USTD | T57: 45873 | U57: 7.10-7.31预付还剩余486.18，仅需支付1204USDT
A58: 57 | B58: PQ | C58: 90469 | D58: 2025 | E58: 8 | F58: 45894 | G58: 671.19 | H58: 0 | I58: 900 | J58: 0 | K58: 0 | L58: 3900 | M58: 0 | N58: 3900 | O58: 0 | P58: =(I58+L58)+K58+O58 -> 4800 | Q58: =SUM(H58,J58,M58) -> 0 | R58: 671.19 | S58: ALIPAY | T58: 45894 | U58: 通过支付宝已支付
A59: 58 | B59: QZ-IEPL | C59: 8.01-1.31实销 | D59: 2025 | E59: 8 | F59: 45902 | H59: 0 | I59: 1300 | J59: 0 | K59: 1750 | L59: 8087.54 | M59: 0 | N59: 8087.54 | O59: 0 | P59: =I59+L59+K59+O59 -> 11137.54 | Q59: =SUM(H59,J59,M59) -> 0 | S59: 冲抵 | U59: 8月预付还剩余1412.46人民币
A60: 59 | B60: QZ-IEPL | C60: 9月预付 | D60: 2025 | E60: 9 | F60: 45902 | G60: 1491.2028 | H60: 0 | I60: 1300 | J60: 0 | K60: 1200 | L60: 9500 | M60: 0 | N60: 9500 | O60: -1412.46 | P60: =(I60+L60)+K60+O60 -> 10587.54 | Q60: =SUM(H60,J60,M60) -> 0 | R60: =P60/7.1 -> 1491.2028 | S60: USTD | T60: 45903 | U60: 9月预付仅需支付1204USDT
A61: 60 | B61: KCD-JP | C61: INV-004333 | D61: 2025 | E61: 9 | F61: 45902 | G61: 444.75 | H61: 0 | I61: 182.34 | J61: 0 | K61: 36 | L61: 226.41 | M61: =IF(B61="KCD-HK",L61*0.1,0) -> 0 | N61: =IF(B61="KCD-HK",L61*0.9,L61) -> 226.41 | O61: 0 | P61: =SUM(H61:L61,O61) -> 444.75 | Q61: =SUM(H61,J61,M61) -> 0 | R61: =SUM(I61,K61,N61,O61) -> 444.75 | S61: WISE | T61: 45907
A62: 61 | B62: KCD-HK | C62: INV-004278 | D62: 2025 | E62: 9 | F62: 45873 | G62: 920.12 | H62: 314.28 | I62: 198.66 | J62: 50.4 | K62: 256 | L62: 100.78 | M62: =IF(B62="KCD-HK",L62*0.1,0) -> 10.078 | N62: =IF(B62="KCD-HK",L62*0.9,L62) -> 90.702 | O62: 48 | P62: =SUM(H62:L62,O62) -> 968.12 | Q62: =SUM(H62,J62,M62) -> 374.758 | R62: =SUM(I62,K62,N62,O62) -> 593.362 | S62: WISE | T62: 45907 | U62: 有一个IP滥用，罚48 USD
A63: 62 | B63: KCD-IEPL | C63: INV-004562 | D63: 2025 | E63: 9 | F63: 45873 | G63: 5028.81 | H63: 0 | I63: 775.48 | J63: 0 | K63: 4930 | L63: 30178.4 | M63: 0 | N63: 30178.4 | O63: 0 | P63: =SUM(H63:K63,M63:O63) -> 35883.88 | Q63: =SUM(H63,J63,M63) -> 0 | R63: 5028.11 | S63: WISE | T63: 45907 | U63: WISE支付了3200，USDT支付了727,又在USDT支付了1101.11
A64: 63 | B64: PQ | C64: 91939 | D64: 2025 | E64: 9 | F64: 45924 | G64: 673.01 | H64: 0 | I64: 900 | J64: 0 | K64: 0 | L64: 3900 | M64: 0 | N64: 3900 | O64: 0 | P64: =(I64+L64)+K64+O64 -> 4800 | Q64: =SUM(H64,J64,M64) -> 0 | R64: 673.01 | S64: 水星 | T64: 45924 | U64: 通过水星SWIFT支付
A65: 64 | B65: KCD-JP | C65: INV-004561 | D65: 2025 | E65: 10 | F65: 45930 | G65: 453.91 | H65: 0 | I65: 182.34 | J65: 0 | K65: 36 | L65: 235.57 | M65: =IF(B65="KCD-HK",L65*0.1,0) -> 0 | N65: =IF(B65="KCD-HK",L65*0.9,L65) -> 235.57 | O65: 0 | P65: =SUM(H65:L65,O65) -> 453.91 | Q65: =SUM(H65,J65,M65) -> 0 | R65: =SUM(I65,K65,N65,O65) -> 453.91 | S65: 水星 | T65: 45930 | U65: 通过水星支付
A66: 65 | B66: KCD-HK | C66: INV-004512 | D66: 2025 | E66: 10 | F66: 45935 | G66: 922.25 | H66: 314.28 | I66: 198.66 | J66: 50.4 | K66: 256 | L66: 100.78 | M66: =IF(B66="KCD-HK",L66*0.1,0) -> 10.078 | N66: =IF(B66="KCD-HK",L66*0.9,L66) -> 90.702 | O66: 48 | P66: =SUM(H66:L66,O66) -> 968.12 | Q66: =SUM(H66,J66,M66) -> 374.758 | R66: =SUM(I66,K66,N66,O66) -> 593.362 | S66: 水星 | T66: 45939 | U66: 通过水星支付
A67: 66 | B67: KCD-IEPL | C67: INV-004562 | D67: 2025 | E67: 10 | F67: 45937 | G67: 5460.29 | H67: 0 | I67: 775.48 | J67: 0 | K67: 5530 | L67: 32569.45 | M67: 0 | N67: 32569.45 | O67: 0 | P67: =SUM(H67:K67,M67:O67) -> 38874.93 | Q67: =SUM(H67,J67,M67) -> 0 | R67: 5460.29 | S67: USTD | T67: 45937 | U67: 通过加密货币支付
A68: 67 | B68: QZ-IEPL | C68: 9.01-9.30实销 | D68: 2025 | E68: 9 | F68: 45940 | H68: 0 | I68: 1300 | J68: 0 | K68: 1020 | L68: 10285 | M68: 0 | N68: 10285 | O68: 0 | P68: =I68+L68+K68+O68 -> 12605 | Q68: =SUM(H68,J68,M68) -> 0 | S68: 冲抵
A69: 68 | B69: QZ-IEPL | C69: 10月预付 | D69: 2025 | E69: 10 | F69: 45940 | G69: 1609.1 | H69: 0 | I69: 1300 | J69: 0 | K69: 1020 | L69: 8500 | M69: 0 | N69: 8500 | O69: 605 | P69: =I69+L69+K69+O69 -> 11425 | Q69: =SUM(H69,J69,M69) -> 0 | R69: =P69/7.1 -> 1609.1549 | S69: USTD | T69: 45940 | U69: 通过加密货币支付
A70: 69 | B70: PQ | C70: 93386 | D70: 2025 | E70: 10 | F70: 45950 | G70: 674.18 | H70: 0 | I70: 900 | J70: 0 | K70: 0 | L70: 3900 | M70: 0 | N70: 3900 | O70: 0 | P70: =(I70+L70)+K70+O70 -> 4800 | Q70: =SUM(H70,J70,M70) -> 0 | R70: 674.18 | S70: 水星 | T70: 45950 | U70: 通过水星SWIFT支付
A71: 70 | B71: KCD-JP | C71: INV-004811 | D71: 2025 | E71: 11 | F71: 45960 | G71: 453.91 | H71: 0 | I71: 182.34 | J71: 0 | K71: 36 | L71: 216.25 | M71: =IF(B71="KCD-HK",L71*0.1,0) -> 0 | N71: =IF(B71="KCD-HK",L71*0.9,L71) -> 216.25 | O71: 0 | P71: =SUM(H71:L71,O71) -> 434.59 | Q71: =SUM(H71,J71,M71) -> 0 | R71: =SUM(I71,K71,N71,O71) -> 434.59 | S71: USTD | T71: 45965
A72: 71 | B72: KCD-HK | C72: INV-004765 | D72: 2025 | E72: 11 | F72: 45960 | G72: 922.25 | H72: 314.28 | I72: 198.66 | J72: 50.4 | K72: 256 | L72: 101.07 | M72: =IF(B72="KCD-HK",L72*0.1,0) -> 10.107 | N72: =IF(B72="KCD-HK",L72*0.9,L72) -> 90.963 | O72: 0 | P72: =SUM(H72:L72,O72) -> 920.41 | Q72: =SUM(H72,J72,M72) -> 374.787 | R72: =SUM(I72,K72,N72,O72) -> 545.623 | S72: USTD | T72: 45965
A73: 72 | B73: KCD-IEPL | C73: INV-004921 | D73: 2025 | E73: 11 | F73: 45962 | G73: 7366.17 | H73: 0 | I73: 775.48 | J73: 0 | K73: 15730 | L73: 35922.55 | M73: 0 | N73: 35922.55 | O73: 0 | P73: =SUM(I73,K73,N73) -> 52428.03 | Q73: =SUM(H73,J73,M73) -> 0 | R73: 7366.17 | S73: USTD | T73: 45965
A74: 73 | B74: QZ-IEPL | C74: 10.01-10.31实销 | D74: 2025 | E74: 10 | F74: 45940 | H74: 0 | I74: 1300 | J74: 0 | K74: 1350 | L74: 3859 | M74: 0 | N74: 3859 | O74: 0 | P74: =SUM(H74:K74,N74) -> 6509 | Q74: 0 | S74: 冲抵
A75: 74 | B75: QZ-IEPL | C75: 11月预付 | D75: 2025 | E75: 11 | F75: 45940 | G75: 1609.1 | H75: 0 | I75: 1300 | J75: 0 | K75: 1350 | L75: 8500 | M75: 0 | N75: 8500 | O75: -4311 | P75: =SUM(I75:K75,N75:O75) -> 6839 | Q75: 0 | R75: =P75/7.1 -> 963.23944 | S75: USTD | T75: 45965
A76: 75 | B76: PQ | C76: 94977 | D76: 2025 | E76: 11 | F76: 45985 | G76: 676.49 | H76: 0 | I76: 900 | J76: 0 | K76: 0 | L76: 3900 | M76: 0 | N76: 3900 | O76: 0 | P76: =(I76+L76)+K76+O76 -> 4800 | Q76: =SUM(H76,J76,M76) -> 0 | R76: 676.49 | S76: USTD | T76: 45985 | U76: 通过加密货币支付
A77: 76 | B77: PQ | C77: 95663 | D77: 2025 | E77: 11 | F77: 45987 | G77: 360.96 | H77: 0 | I77: 0 | J77: 0 | K77: 0 | L77: 2556.67 | M77: 0 | N77: 3900 | O77: 0 | P77: =(I77+L77)+K77+O77 -> 2556.67 | Q77: =SUM(H77,J77,M77) -> 0 | R77: 360.96 | S77: USTD | T77: 45987 | U77: 通过加密货币支付，新增加2条线路
A78: 77 | B78: QZ-IEPL | C78: 11.01-11.30实销 | D78: 2025 | E78: 11 | F78: 45993 | H78: 0 | I78: 1300 | J78: 0 | K78: 1350 | L78: 2475.37 | M78: 0 | N78: 2475.37 | O78: 0 | P78: 5125.37 | Q78: 0 | S78: 冲抵
A79: 78 | B79: QZ-IEPL | C79: 12月预付 | D79: 2025 | E79: 12 | F79: 45999 | G79: 1327.3 | H79: 0 | I79: 2600 | J79: 0 | K79: 1850 | L79: 12100 | M79: 0 | N79: 12100 | O79: -6024.63 | P79: =SUM(H79:M79,O79) -> 10525.37 | Q79: 0 | R79: 1327.3 | S79: USTD | T79: 46002 | U79: 通过加密货币支付
A80: 79 | B80: KCD-JP | C80: INV-005035 | D80: 2025 | E80: 12 | F80: 45991 | G80: 433.48 | H80: 0 | I80: 182.34 | J80: 0 | K80: 36 | L80: 215.14 | M80: =IF(B80="KCD-HK",L80*0.1,0) -> 0 | N80: =IF(B80="KCD-HK",L80*0.9,L80) -> 215.14 | O80: 0 | P80: =SUM(H80:L80,O80) -> 433.48 | Q80: =SUM(H80,J80,M80) -> 0 | R80: =SUM(I80,K80,N80,O80) -> 433.48 | S80: 水星 | T80: 45994 | U80: 通过水星支付
A81: 80 | B81: KCD-HK | C81: INV-004988 | D81: 2025 | E81: 12 | F81: 45991 | G81: 922.42 | H81: 314.28 | I81: 198.66 | J81: 50.4 | K81: 256 | L81: 103.08 | M81: =IF(B81="KCD-HK",L81*0.1,0) -> 10.308 | N81: =IF(B81="KCD-HK",L81*0.9,L81) -> 92.772 | O81: 0 | P81: =SUM(H81:L81,O81) -> 922.42 | Q81: =SUM(H81,J81,M81) -> 374.988 | R81: =SUM(I81,K81,N81,O81) -> 547.432 | S81: 水星 | T81: 45994 | U81: 通过水星支付
A82: 81 | B82: KCD-IEPL | C82: INV-005182 | D82: 2025 | E82: 12 | F82: 45992 | G82: 7494.29 | H82: 0 | I82: 775.48 | J82: 0 | K82: 35280 | L82: 16961.65 | M82: 0 | N82: 16961.65 | O82: 0 | P82: =SUM(I82,K82,N82) -> 53017.13 | Q82: =SUM(H82,J82,M82) -> 0 | R82: 7494.29 | S82: USTD | T82: 45995 | U82: 通过加密货币支付
A83: 82 | B83: KURUN | C83: 18684，18685 | D83: 2025 | E83: 12 | F83: 46003 | G83: 1100 | H83: 280 | I83: 720 | J83: 0 | K83: 0 | L83: 0 | M83: 0 | N83: 0 | O83: 100 | P83: =SUM(H83:L83,O83) -> 1100 | Q83: 280 | R83: =SUM(I83,K83,N83,O83) -> 820 | S83: 水星 | T83: 46003 | U83: 100美金是购买交换机
A84: 83 | B84: PQ | C84: 96547 | D84: 2025 | E84: 12 | F84: 46014 | G84: 360.96 | H84: 0 | I84: 0 | J84: 0 | K84: 0 | L84: 6094.66 | M84: 0 | N84: 3900 | O84: 0 | P84: 6094.66 | Q84: =SUM(H84,J84,M84) -> 0 | R84: 867.09 | S84: USTD | T84: 46014 | U84: 通过加密货币支付，奶姐的独线退回
A85: 84 | B85: KCD-JP | C85: INV-005274 | D85: 2025 | E85: 12 | F85: 46022 | G85: 401.82 | H85: 0 | I85: 182.34 | J85: 0 | K85: 36 | L85: 183.48 | M85: =IF(B85="KCD-HK",L85*0.1,0) -> 0 | N85: =IF(B85="KCD-HK",L85*0.9,L85) -> 183.48 | O85: 0 | P85: =SUM(H85:L85,O85) -> 401.82 | Q85: =SUM(H85,J85,M85) -> 0 | R85: =SUM(I85,K85,N85,O85) -> 401.82 | S85: 水星 | T85: 46026 | U85: 通过水星支付
A86: 85 | B86: KCD-HK | C86: INV-005233 | D86: 2025 | E86: 12 | F86: 46022 | G86: 903.71 | H86: 314.28 | I86: 198.66 | J86: 50.4 | K86: 256 | L86: 84.37 | M86: =IF(B86="KCD-HK",L86*0.1,0) -> 8.437 | N86: =IF(B86="KCD-HK",L86*0.9,L86) -> 75.933 | O86: 0 | P86: =SUM(H86:L86,O86) -> 903.71 | Q86: =SUM(H86,J86,M86) -> 373.117 | R86: =SUM(I86,K86,N86,O86) -> 530.593 | S86: 水星 | T86: 46026 | U86: 通过水星支付
A87: 86 | B87: QZ-IEPL | C87: 12.01-12.31实销 | D87: 2025 | E87: 12 | F87: 46022 | H87: 0 | I87: 1600 | J87: 0 | K87: 1800 | L87: 8233.35 | M87: 0 | N87: 8233.35 | O87: 0 | P87: 8233.35 | Q87: 0 | S87: 冲抵
A88: 87 | B88: QZ-IEPL | C88: 01月预付 | D88: 2026 | E88: 1 | F88: 46022 | G88: 1778.8 | H88: 0 | I88: 1600 | J88: 0 | K88: 1400 | L88: 13090 | M88: 0 | N88: 13090 | O88: -3994.177 | P88: =SUM(H88:M88,O88) -> 12095.823 | Q88: 0 | R88: 1778.8 | S88: USTD | T88: 46026 | U88: 通过加密货币支付
A89: 88 | B89: KCD-IEPL | C89: INV-005536 | D89: 2025 | E89: 12 | F89: 46022 | G89: 913.55 | H89: 0 | I89: 775.48 | J89: 0 | K89: 2020 | L89: 3593.61 | M89: 0 | N89: 3646.89 | O89: 0 | P89: 3593.61 | Q89: =SUM(H89,J89,M89) -> 0 | R89: 913.55 | S89: 水星 | T89: 46026 | U89: 通过水星支付
A94: Total() | G94: =SUM(G2:G93) -> 88641.228 | P94: =SUM(P2:P93) -> 421728.57 | Q94: =SUM(Q2:Q93) -> 8068.081 | R94: =SUM(R2:R93) -> 81369.132 | U94: Null
A95: Total(￥) | G95: =G94*7.21 -> 639103.26 | P95: =P94*7.21 -> 3040663 | Q95: =Q94*7.21 -> 58170.864 | R95: =R94*7.21 -> 586671.44

Sheet W系统销售统计2025
A1: ID | B1: User ID | C1: Client Name | D1: Currency | E1: Payment Method | F1: Date | G1: M | H1: Description | I1: Invoice ID | J1: Transaction ID | K1: Amount In | L1: Fees | M1: Amount Out | N1: Exchange Rate | O1: Income | P1: Income ($)
A2: 1 | B2: 6463 | C2: ec Al | D2: USD | E2: Alipay ????????? (QR+APP) | F2: 45658.033 | G2: 1 | H2: Invoice Payment | I2: 40939 | J2: pi_3Qc8bYRxxun8okeS0Pytn5Xo | K2: 3.45 | L2: 0 | M2: 0 | N2: 1 | O2: =K2-L2-M2 -> 3.45 | P2: =IF(D2="USD",O2,O2/N2) -> 3.45
A3: 2 | B3: 6495 | C3: Wataru Ko | D3: USD | E3: Alipay ????????? (QR+APP) | F3: 45658.104 | G3: 1 | H3: Invoice Payment | I3: 40975 | J3: pi_3QcAC6Rxxun8okeS0FlHXm8i | K3: 20.25 | L3: 0 | M3: 0 | N3: 1 | O3: =K3-L3-M3 -> 20.25 | P3: =IF(D3="USD",O3,O3/N3) -> 20.25
A4: 3 | B4: 6514 | C4: ye duo | D4: USD | E4: Alipay ????????? (QR+APP) | F4: 45658.542 | G4: 1 | H4: Invoice Payment | I4: 41059 | J4: pi_3QcJzcRxxun8okeS0CxcLmtX | K4: 2.49 | L4: 0 | M4: 0 | N4: 1 | O4: =K4-L4-M4 -> 2.49 | P4: =IF(D4="USD",O4,O4/N4) -> 2.49
A5: 4 | B5: 6522 | C5: Ge Yi Ge | D5: USD | E5: Alipay ????????? (QR+APP) | F5: 45658.796 | G5: 1 | H5: Invoice Payment | I5: 41107 | J5: pi_3QcPk3Rxxun8okeS1WssHLO1 | K5: 20.25 | L5: 0 | M5: 0 | N5: 1 | O5: =K5-L5-M5 -> 20.25 | P5: =IF(D5="USD",O5,O5/N5) -> 20.25
A6: 5 | B6: 6525 | C6: snarls defunct | D6: USD | E6: PayPal | F6: 45658.807 | G6: 1 | H6: Invoice Payment | I6: 41119 | J6: 5NN567791J961805J | K6: 20.25 | L6: 1.5 | M6: 0 | N6: 1 | O6: =K6-L6-M6 -> 18.75 | P6: =IF(D6="USD",O6,O6/N6) -> 18.75
A7: 6 | B7: 6529 | C7: baobhan sith | D7: USD | E7: Alipay ????????? (QR+APP) | F7: 45658.915 | G7: 1 | H7: Invoice Payment | I7: 41155 | J7: pi_3QcSQkRxxun8okeS0A51SRNY | K7: 20.25 | L7: 0 | M7: 0 | N7: 1 | O7: =K7-L7-M7 -> 20.25 | P7: =IF(D7="USD",O7,O7/N7) -> 20.25
A8: 7 | B8: 6528 | C8: mingjie sheng | D8: USD | E8: PayPal | F8: 45658.916 | G8: 1 | H8: Invoice Payment | I8: 41167 | J8: 7GU22998TH945710T | K8: 20.25 | L8: 1.5 | M8: 0 | N8: 1 | O8: =K8-L8-M8 -> 18.75 | P8: =IF(D8="USD",O8,O8/N8) -> 18.75
A9: 8 | B9: 6533 | C9: Ian Lee | D9: USD | E9: Alipay ????????? (QR+APP) | F9: 45658.985 | G9: 1 | H9: Invoice Payment | I9: 41191 | J9: pi_3QcU0nRxxun8okeS1cFOyUfG | K9: 20.25 | L9: 0 | M9: 0 | N9: 1 | O9: =K9-L9-M9 -> 20.25 | P9: =IF(D9="USD",O9,O9/N9) -> 20.25
A10: 9 | B10: 6535 | C10: tom Johnson | D10: USD | E10: Crypto ???????????? | F10: 45659.031 | G10: 1 | H10: Invoice Payment | I10: 41203 | J10: 03c1a42eca546d1679f1316533a7d2d3b1d889d177dad08559b670813480a994 | K10: 7.99 | L10: 0 | M10: 0 | N10: 1 | O10: =K10-L10-M10 -> 7.99 | P10: =IF(D10="USD",O10,O10/N10) -> 7.99
A11: 10 | B11: 6537 | C11: ShengChe Lin | D11: USD | E11: PayPal | F11: 45659.097 | G11: 1 | H11: Invoice Payment | I11: 41215 | J11: 0D416666A9629534V | K11: 20.25 | L11: 1.2 | M11: 0 | N11: 1 | O11: =K11-L11-M11 -> 19.05 | P11: =IF(D11="USD",O11,O11/N11) -> 19.05
A12: 11 | B12: 6553 | C12: ??? ??? | D12: USD | E12: PayPal | F12: 45659.284 | G12: 1 | H12: Invoice Payment | I12: 41227 | J12: 6DN09443A2395982X | K12: 20.25 | L12: 1.5 | M12: 0 | N12: 1 | O12: =K12-L12-M12 -> 18.75 | P12: =IF(D12="USD",O12,O12/N12) -> 18.75
A13: 12 | B13: 6461 | C13: default chen | D13: USD | E13: Alipay ????????? (QR+APP) | F13: 45659.458 | G13: 1 | H13: Invoice Payment | I13: 41263 | J13: pi_3QcecHRxxun8okeS0fPgWFff | K13: 20.25 | L13: 0 | M13: 0 | N13: 1 | O13: =K13-L13-M13 -> 20.25 | P13: =IF(D13="USD",O13,O13/N13) -> 20.25
... A28: 27 | B28: 1836 | C28: ?????? ??? | D28: CNY | E28: Alipay ????????? (QR+APP) | F28: 45661.528 | G28: 1 | H28: Invoice Payment | I28: 41491 | J28: pi_3QdPASRxxun8okeS1PwbaH2S | K28: 87.31 | L28: 0 | M28: 0 | N28: 7.31828 | O28: =K28-L28-M28 -> 87.31 | P28: =IF(D28="USD",O28,O28/N28) -> 11.930399
A29: 28 | B29: 1836 | C29: ?????? ??? | D29: CNY | E29: Alipay ????????? (QR+APP) | F29: 45661.549 | G29: 1 | H29: Invoice Payment | I29: 41491 | K29: 0.03 | L29: 0 | M29: 0 | N29: 7.31828 | O29: =K29-L29-M29 -> 0.03 | P29: =IF(D29="USD",O29,O29/N29) -> 0.0040993239
A30: 29 | B30: 4096 | C30: Elizabeth Russell | D30: USD | E30: PayPal | F30: 45661.821 | G30: 1 | H30: Invoice Payment | I30: 38131 | J30: 6RY063221M9508732 | K30: 11.99 | L30: 0.91 | M30: 0 | N30: 1 | O30: =K30-L30-M30 -> 11.08 | P30: =IF(D30="USD",O30,O30/N30) -> 11.08
A31: 30 | B31: 6392 | C31: Beverly Walsh | D31: USD | E31: PayPal | F31: 45661.874 | G31: 1 | H31: Invoice Payment | I31: 41611 | J31: 2JC26621MR463905F | K31: 23.99 | L31: 1.33 | M31: 0 | N31: 1 | O31: =K31-L31-M31 -> 22.66 | P31: =IF(D31="USD",O31,O31/N31) -> 22.66
A32: 31 | B32: 6705 | C32: MING MA | D32: USD | E32: Alipay ????????? (QR+APP) | F32: 45662.012 | G32: 1 | H32: Invoice Payment | I32: 41623 | J32: pi_3Qda2HRxxun8okeS1EtDfZdH | K32: 20.25 | L32: 0 | M32: 0 | N32: 1 | O32: =K32-L32-M32 -> 20.25 | P32: =IF(D32="USD",O32,O32/N32) -> 20.25
A33: 32 | B33: 3607 | C33: qinghuan huan | D33: USD | E33: Alipay ????????? (QR+APP) | F33: 45662.427 | G33: 1 | H33: Invoice Payment | I33: 41695 | J33: pi_3QdjMPRxxun8okeS19kKnupl | K33: 1.09 | L33: 0 | M33: 0 | N33: 1 | O33: =K33-L33-M33 -> 1.09 | P33: =IF(D33="USD",O33,O33/N33) -> 1.09
A34: 33 | B34: 6732 | C34: krono pol | D34: USD | E34: Alipay ????????? (QR+APP) | F34: 45662.496 | G34: 1 | H34: Invoice Payment | I34: 41707 | J34: pi_3QdkuQRxxun8okeS1FGOC5en | K34: 5.99 | L34: 0 | M34: 0 | N34: 1 | O34: =K34-L34-M34 -> 5.99 | P34: =IF(D34="USD",O34,O34/N34) -> 5.99
A35: 34 | B35: 6732 | C35: krono pol | D35: USD | E35: Alipay ????????? (QR+APP) | F35: 45662.531 | G35: 1 | H35: Invoice Payment | I35: 41719 | J35: pi_3QdlfSRxxun8okeS0brIaFYl | K35: 23.99 | L35: 0 | M35: 0 | N35: 1 | O35: =K35-L35-M35 -> 23.99 | P35: =IF(D35="USD",O35,O35/N35) -> 23.99
A36: 35 | B36: 2115 | C36: Ryan Kim | D36: USD | E36: PayPal | F36: 45662.814 | G36: 1 | H36: Invoice Payment | I36: 31219 | J36: 0S46609254646530E | K36: 4.99 | L36: 0.66 | M36: 0 | N36: 1 | O36: =K36-L36-M36 -> 4.33 | P36: =IF(D36="USD",O36,O36/N36) -> 4.33
A37: 36 | B37: 6633 | C37: liu liu | D37: USD | E37: Alipay ????????? (QR+APP) | F37: 45663.04 | G37: 1 | H37: Refund of Transaction ID pi_3Qd6SMRxxun8okeS1jQOq7Z1 | I37: 41371 | K37: 0 | L37: 0 | M37: 59.99 | N37: 1 | O37: =K37-L37-M37 -> -59.99 | P37: =IF(D37="USD",O37,O37/N37) -> -59.99
A38: 37 | B38: 6754 | C38: Vincent Young | D38: USD | E38: Crypto ???????????? | F38: 45663.068 | G38: 1 | H38: Invoice Payment | I38: 41767 | J38: 99a3d7cc86cbf6a550de2cf9e85fe24c24c1c17c4d3a0e11e5766114f91141fc | K38: 20.25 | L38: 0 | M38: 0 | N38: 1 | O38: =K38-L38-M38 -> 20.25 | P38: =IF(D38="USD",O38,O38/N38) -> 20.25
A39: 38 | B39: 6774 | C39: sola sola | D39: USD | E39: Alipay ????????? (QR+APP) | F39: 45663.347 | G39: 1 | H39: Invoice Payment | I39: 41815 | J39: pi_3Qe43IRxxun8okeS0Maf6cam | K39: 11.99 | L39: 0 | M39: 0 | N39: 1 | O39: =K39-L39-M39 -> 11.99 | P39: =IF(D39="USD",O39,O39/N39) -> 11.99
A40: 39 | B40: 6776 | C40: shell shell | D40: USD | E40: Alipay ????????? (QR+APP) | F40: 45663.371 | G40: 1 | H40: Invoice Payment | I40: 41827 | J40: pi_3Qe4YYRxxun8okeS1YxndoJz | K40: 11.99 | L40: 0 | M40: 0 | N40: 1 | O40: =K40-L40-M40 -> 11.99 | P40: =IF(D40="USD",O40,O40/N40) -> 11.99
A41: 40 | B41: 6294 | C41: Willy Willy | D41: USD | E41: Alipay ????????? (QR+APP) | F41: 45663.38 | G41: 1 | H41: Invoice Payment | I41: 41875 | J41: pi_3Qe4mwRxxun8okeS0OYEUJEX | K41: 8.26 | L41: 0 | M41: 0 | N41: 1 | O41: =K41-L41-M41 -> 8.26 | P41: =IF(D41="USD",O41,O41/N41) -> 8.26
A42: 41 | B42: 479 | C42: Buddy Finley | D42: USD | E42: Alipay ????????? (QR+APP) | F42: 45663.387 | G42: 1 | H42: Invoice Payment | I42: 41659 | J42: pi_3Qe4vcRxxun8okeS0ptDb6W0 | K42: 1.09 | L42: 0 | M42: 0 | N42: 1 | O42: =K42-L42-M42 -> 1.09 | P42: =IF(D42="USD",O42,O42/N42) -> 1.09
A43: 42 | B43: 1052 | D43: USD | E43: Alipay ????????? (QR+APP) | F43: 45663.485 | G43: 1 | H43: Invoice Payment | I43: 38647 | J43: pi_3Qe78TRxxun8okeS1LVQGas6 | K43: 1.09 | L43: 0 | M43: 0 | N43: 1 | O43: =K43-L43-M43 -> 1.09 | P43: =IF(D43="USD",O43,O43/N43) -> 1.09
A44: 43 | B44: 6794 | C44: 2131qeq dsdsaa | D44: USD | E44: Crypto ???????????? | F44: 45663.692 | G44: 1 | H44: Invoice Payment | I44: 41899 | K44: 2.49 | L44: 0 | M44: 0 | N44: 1 | O44: =K44-L44-M44 -> 2.49 | P44: =IF(D44="USD",O44,O44/N44) -> 2.49
A45: 44 | B45: 6797 | C45: ?????? ??? | D45: CNY | E45: Alipay ????????? (QR+APP) | F45: 45663.717 | G45: 1 | H45: Invoice Payment | I45: 41947 | J45: pi_3QeCLORxxun8okeS1K456Www | K45: 1383.15 | L45: 0 | M45: 0 | N45: 7.31828 | O45: =K45-L45-M45 -> 1383.15 | P45: =IF(D45="USD",O45,O45/N45) -> 188.99933
A46: 45 | B46: 3371 | C46: chen chen | D46: USD | E46: Alipay ????????? (QR+APP) | F46: 45663.721 | G46: 1 | H46: Invoice Payment | I46: 36223 | J46: pi_3QeCRiRxxun8okeS1gAxLwwM | K46: 1.09 | L46: 0 | M46: 0 | N46: 1 | O46: =K46-L46-M46 -> 1.09 | P46: =IF(D46="USD",O46,O46/N46) -> 1.09
A47: 46 | B47: 4030 | C47: Yu Chen | D47: CNY | E47: PayPal | F47: 45663.797 | G47: 1 | H47: Invoice Payment | I47: 38335 | J47: 7FC79867RW773361X | K47: 36.24 | L47: 5.42 | M47: 0 | N47: 7.31828 | O47: =K47-L47-M47 -> 30.82 | P47: =IF(D47="USD",O47,O47/N47) -> 4.2113721
A48: 47 | B48: 4030 | C48: Yu Chen | D48: CNY | E48: PayPal | F48: 45664.382 | G48: 1 | H48: Reversed Transaction ID: 7FC79867RW773361X | I48: 38335 | J48: 7.35E+16 | K48: 0 | L48: -5.42 | M48: 36.24 | N48: 7.31828 | O48: =K48-L48-M48 -> -30.82 | P48: =IF(D48="USD",O48,O48/N48) -> -4.2113721
A49: 48 | B49: 3265 | C49: chong yang | D49: USD | E49: PayPal | F49: 45664.525 | G49: 1 | H49: Invoice Payment | I49: 41995 | J49: 0A845910FC111801M | K49: 1.09 | L49: 0.53 | M49: 0 | N49: 1 | O49: =K49-L49-M49 -> 0.56 | P49: =IF(D49="USD",O49,O49/N49) -> 0.56
A50: 49 | B50: 1560 | C50: jinghai wang | D50: USD | E50: Alipay ????????? (QR+APP) | F50: 45664.634 | G50: 1 | H50: Invoice Payment | I50: 41863 | J50: pi_3QeWxFRxxun8okeS1EZP9GFK | K50: 2.99 | L50: 0 | M50: 0 | N50: 1 | O50: =K50-L50-M50 -> 2.99 | P50: =IF(D50="USD",O50,O50/N50) -> 2.99
A51: 50 | B51: 1560 | C51: jinghai wang | D51: USD | E51: Alipay ????????? (QR+APP) | F51: 45664.635 | G51: 1 | H51: Invoice Payment | I51: 40699 | J51: pi_3QeWz8Rxxun8okeS0oDWbLEA | K51: 5.98 | L51: 0 | M51: 0 | N51: 1 | O51: =K51-L51-M51 -> 5.98 | P51: =IF(D51="USD",O51,O51/N51) -> 5.98
A52: 51 | B52: 6794 | C52: 2131qeq dsdsaa | D52: USD | E52: Crypto ???????????? | F52: 45664.66 | G52: 1 | H52: Invoice Payment | I52: 42031 | J52: 49898854d3fd334694d26f9fc69f24b764d231652de9941221cee1896b7db168 | K52: 17.76 | L52: 0 | M52: 0 | N52: 1 | O52: =K52-L52-M52 -> 17.76 | P52: =IF(D52="USD",O52,O52/N52) -> 17.76
A53: 52 | B53: 6898 | C53: zhaowu cang | D53: CNY | E53: Alipay ????????? (QR+APP) | F53: 45664.835 | G53: 1 | H53: Invoice Payment | I53: 42043 | J53: pi_3QebRrRxxun8okeS0F978Tvn | K53: 184.75 | L53: 0 | M53: 0 | N53: 7.31671 | O53: =K53-L53-M53 -> 184.75 | P53: =IF(D53="USD",O53,O53/N53) -> 25.25042
A54: 53 | B54: 5974 | C54: Jesse shi | D54: USD | E54: Alipay ????????? (QR+APP) | F54: 45665.423 | G54: 1 | H54: Invoice Payment | I54: 42079 | J54: pi_3QeohORxxun8okeS0lsBMony | K54: 11.99 | L54: 0 | M54: 0 | N54: 1 | O54: =K54-L54-M54 -> 11.99 | P54: =IF(D54="USD",O54,O54/N54) -> 11.99
A55: 54 | B55: 1836 | C55: ?????? ??? | D55: CNY | E55: Alipay ????????? (QR+APP) | F55: 45665.563 | G55: 1 | H55: Invoice Payment | I55: 42091 | J55: pi_3Qerr1Rxxun8okeS0ctzriYn | K55: 148.36 | L55: 0 | M55: 0 | N55: 7.32628 | O55: =K55-L55-M55 -> 148.36 | P55: =IF(D55="USD",O55,O55/N55) -> 20.250386
A56: 55 | B56: 6992 | C56: Ryan li | D56: USD | E56: Alipay ????????? (QR+APP) | F56: 45665.743 | G56: 1 | H56: Invoice Payment | I56: 42103 | J56: pi_3QevrfRxxun8okeS0qFm5Bp2 | K56: 32.99 | L56: 0 | M56: 0 | N56: 1 | O56: =K56-L56-M56 -> 32.99 | P56: =IF(D56="USD",O56,O56/N56) -> 32.99
... A59: 58 | B59: 6991 | C59: Christopher Frost | D59: CNY | E59: Alipay ????????? (QR+APP) | F59: 45667.499 | G59: 1 | H59: Invoice Payment | I59: 42247 | J59: pi_3QfZMnRxxun8okeS1byKIjjq | K59: 175.9 | L59: 0 | M59: 0 | N59: 7.33217 | O59: =K59-L59-M59 -> 175.9 | P59: =IF(D59="USD",O59,O59/N59) -> 23.990169
A60: 59 | B60: 6991 | C60: Christopher Frost | D60: CNY | E60: Alipay ????????? (QR+APP) | F60: 45667.557 | G60: 1 | H60: Invoice Payment | I60: 42247 | K60: 0.03 | L60: 0 | M60: 0 | N60: 7.33217 | O60: =K60-L60-M60 -> 0.03 | P60: =IF(D60="USD",O60,O60/N60) -> 0.0040915582
A61: 60 | B61: 36 | C61: leton Car | D61: USD | E61: Crypto ???????????? | F61: 45667.585 | G61: 1 | H61: Invoice Payment | I61: 39799 | K61: 600 | L61: 0 | M61: 0 | N61: 1 | O61: =K61-L61-M61 -> 600 | P61: =IF(D61="USD",O61,O61/N61) -> 600
A62: 61 | B62: 7189 | C62: joey lee | D62: USD | E62: Alipay ????????? (QR+APP) | F62: 45667.611 | G62: 1 | H62: Invoice Payment | I62: 42307 | J62: pi_3Qfbs0Rxxun8okeS1miyUlSb | K62: 16.79 | L62: 0 | M62: 0 | N62: 1 | O62: =K62-L62-M62 -> 16.79 | P62: =IF(D62="USD",O62,O62/N62) -> 16.79
A63: 62 | B63: 6794 | C63: 2131qeq dsdsaa | D63: USD | E63: Crypto ???????????? | F63: 45667.617 | G63: 1 | H63: Invoice Payment | I63: 42295 | J63: 392141c7803868d1557046f83507a1ce360f1bbce258d3f34799fd7a59f4f464 | K63: 71.99 | L63: 0 | M63: 0 | N63: 1 | O63: =K63-L63-M63 -> 71.99 | P63: =IF(D63="USD",O63,O63/N63) -> 71.99
A64: 63 | B64: 7191 | C64: hao yu | D64: USD | E64: Alipay ????????? (QR+APP) | F64: 45667.642 | G64: 1 | H64: Invoice Payment | I64: 42331 | J64: pi_3QfcZQRxxun8okeS08sULVYK | K64: 8.39 | L64: 0 | M64: 0 | N64: 1 | O64: =K64-L64-M64 -> 8.39 | P64: =IF(D64="USD",O64,O64/N64) -> 8.39
A65: 64 | B65: 6421 | C65: xin huang | D65: USD | E65: Alipay ????????? (QR+APP) | F65: 45667.644 | G65: 1 | H65: Invoice Payment | I65: 42343 | J65: pi_3QfcddRxxun8okeS1egB1B6P | K65: 20.99 | L65: 0 | M65: 0 | N65: 1 | O65: =K65-L65-M65 -> 20.99 | P65: =IF(D65="USD",O65,O65/N65) -> 20.99
A66: 65 | B66: 7204 | C66: he xiao | D66: USD | E66: Alipay ????????? (QR+APP) | F66: 45667.869 | G66: 1 | H66: Invoice Payment | I66: 42403 | J66: pi_3QfhfzRxxun8okeS0vnTdxRX | K66: 8.39 | L66: 0 | M66: 0 | N66: 1 | O66: =K66-L66-M66 -> 8.39 | P66: =IF(D66="USD",O66,O66/N66) -> 8.39
A67: 66 | B67: 7212 | C67: weijie zhang | D67: CNY | E67: Alipay ????????? (QR+APP) | F67: 45667.921 | G67: 1 | H67: Invoice Payment | I67: 42439 | J67: pi_3QfiqNRxxun8okeS08E1XIml | K67: 92.39 | L67: 0 | M67: 0 | N67: 7.33217 | O67: =K67-L67-M67 -> 92.39 | P67: =IF(D67="USD",O67,O67/N67) -> 12.600635
A68: 67 | B68: 7243 | C68: ??? ??? | D68: CNY | E68: PayPal | F68: 45668.638 | G68: 1 | H68: Invoice Payment | I68: 42511 | J68: 1NA77863JL7311445 | K68: 61.55 | L68: 6.67 | M68: 0 | N68: 7.33133 | O68: =K68-L68-M68 -> 54.88 | P68: =IF(D68="USD",O68,O68/N68) -> 7.4856813
A69: 68 | B69: 7245 | C69: plus plus | D69: USD | E69: Alipay ????????? (QR+APP) | F69: 45668.656 | G69: 1 | H69: Invoice Payment | I69: 42523 | J69: pi_3QfzNeRxxun8okeS1dWgPHq5 | K69: 8.39 | L69: 0 | M69: 0 | N69: 1 | O69: =K69-L69-M69 -> 8.39 | P69: =IF(D69="USD",O69,O69/N69) -> 8.39
A70: 69 | B70: 7254 | C70: ??? MorrowMaria | D70: USD | E70: Alipay ????????? (QR+APP) | F70: 45668.757 | G70: 1 | H70: Invoice Payment | I70: 42547 | J70: pi_3Qg1e2Rxxun8okeS1YySiYRu | K70: 4.99 | L70: 0 | M70: 0 | N70: 1 | O70: =K70-L70-M70 -> 4.99 | P70: =IF(D70="USD",O70,O70/N70) -> 4.99
A71: 70 | B71: 1157 | C71: ?????? ??? | D71: USD | E71: Alipay ????????? (QR+APP) | F71: 45668.791 | G71: 1 | H71: Invoice Payment | I71: 42559 | J71: pi_3Qg2ORRxxun8okeS0or8cnUo | K71: 12.59 | L71: 0 | M71: 0 | N71: 1 | O71: =K71-L71-M71 -> 12.59 | P71: =IF(D71="USD",O71,O71/N71) -> 12.59
A72: 71 | B72: 7261 | C72: Qingyu Xing | D72: USD | E72: Alipay ????????? (QR+APP) | F72: 45668.88 | G72: 1 | H72: Invoice Payment | I72: 42583 | J72: pi_3Qg4OvRxxun8okeS0UKG2eNO | K72: 20.25 | L72: 0 | M72: 0 | N72: 1 | O72: =K72-L72-M72 -> 20.25 | P72: =IF(D72="USD",O72,O72/N72) -> 20.25
A73: 72 | B73: 7252 | C73: tuman ao | D73: USD | E73: Crypto ???????????? | F73: 45668.956 | G73: 1 | H73: Invoice Payment | I73: 42535 | J73: 9c468ab7b67d25c6dc6cc32967b90c676b579e751a38c0971ff73fafe263ba2e | K73: 2 | L73: 0 | M73: 0 | N73: 1 | O73: =K73-L73-M73 -> 2 | P73: =IF(D73="USD",O73,O73/N73) -> 2
... A93: 92 | B93: 90 | C93: ??? ??? | D93: CNY | E93: Alipay ????????? (QR+APP) | F93: 45671.849 | G93: 1 | H93: Invoice Payment | I93: 43111 | J93: pi_3Qh98bRxxun8okeS1sWbyf4i | K93: 14.66 | L93: 0 | M93: 0 | N93: 7.33193 | O93: =K93-L93-M93 -> 14.66 | P93: =IF(D93="USD",O93,O93/N93) -> 1.9994735
A94: 93 | B94: 7682 | C94: ??? ??? | D94: USD | E94: Alipay ????????? (QR+APP) | F94: 45672 | G94: 1 | H94: Invoice Payment | I94: 43339 | K94: 0 | L94: 0 | M94: 0 | N94: 1 | O94: =K94-L94-M94 -> 0 | P94: =IF(D94="USD",O94,O94/N94) -> 0
A95: 94 | B95: 1560 | C95: jinghai wang | D95: USD | E95: Alipay ????????? (QR+APP) | F95: 45672.6 | G95: 1 | H95: Invoice Payment | I95: 43171 | J95: pi_3QhQ0BRxxun8okeS06UvIY4k | K95: 8.97 | L95: 0 | M95: 0 | N95: 1 | O95: =K95-L95-M95 -> 8.97 | P95: =IF(D95="USD",O95,O95/N95) -> 8.97
A96: 95 | B96: 1560 | C96: jinghai wang | D96: USD | E96: Alipay ????????? (QR+APP) | F96: 45672.602 | G96: 1 | H96: Invoice Payment | I96: 43231 | J96: pi_3QhQ45Rxxun8okeS1tpeydpn | K96: 2.99 | L96: 0 | M96: 0 | N96: 1 | O96: =K96-L96-M96 -> 2.99 | P96: =IF(D96="USD",O96,O96/N96) -> 2.99
A97: 96 | B97: 7664 | C97: bo caibang | D97: USD | E97: Alipay ????????? (QR+APP) | F97: 45672.82 | G97: 1 | H97: Invoice Payment | I97: 43255 | J97: pi_3QhUwrRxxun8okeS0EISrLMX | K97: 23.99 | L97: 0 | M97: 0 | N97: 1 | O97: =K97-L97-M97 -> 23.99 | P97: =IF(D97="USD",O97,O97/N97) -> 23.99
A98: 97 | B98: 3307 | C98: wei sheng | D98: USD | E98: Alipay ????????? (QR+APP) | F98: 45672.866 | G98: 1 | H98: Invoice Payment | I98: 43279 | J98: pi_3QhVzBRxxun8okeS1zJbUmaA | K98: 1 | L98: 0 | M98: 0 | N98: 1 | O98: =K98-L98-M98 -> 1 | P98: =IF(D98="USD",O98,O98/N98) -> 1
A99: 98 | B99: 7681 | C99: leng yue | D99: USD | E99: Alipay ????????? (QR+APP) | F99: 45672.9 | G99: 1 | H99: Invoice Payment | I99: 43327 | J99: pi_3QhWkWRxxun8okeS0hT4URTm | K99: 20.25 | L99: 0 | M99: 0 | N99: 1 | O99: =K99-L99-M99 -> 20.25 | P99: =IF(D99="USD",O99,O99/N99) -> 20.25
A100: 99 | B100: 1652 | C100: dfga ada | D100: USD | E100: PayPal | F100: 45673 | G100: 1 | H100: Invoice Payment | I100: 43291 | K100: 0 | L100: 0 | M100: 0 | N100: 1 | O100: =K100-L100-M100 -> 0 | P100: =IF(D100="USD",O100,O100/N100) -> 0
A101: 100 | B101: 7677 | C101: Bear Smith | D101: USD | E101: Alipay ????????? (QR+APP) | F101: 45673.015 | G101: 1 | H101: Invoice Payment | I101: 43351 | J101: pi_3QhZK4Rxxun8okeS04PxTgWf | K101: 3.99 | L101: 0 | M101: 0 | N101: 1 | O101: =K101-L101-M101 -> 3.99 | P101: =IF(D101="USD",O101,O101/N101) -> 3.99
A102: 101 | B102: 351 | C102: xukun cai | D102: USD | E102: PayPal | F102: 45673.796 | G102: 1 | H102: Invoice Payment | I102: 38179 | J102: 57439214N0763002P | K102: 1.09 | L102: 0.54 | M102: 0 | N102: 1 | O102: =K102-L102-M102 -> 0.55 | P102: =IF(D102="USD",O102,O102/N102) -> 0.55
A103: 102 | B103: 6093 | C103: E S | D103: USD | E103: Alipay ????????? (QR+APP) | F103: 45673.819 | G103: 1 | H103: Invoice Payment | I103: 43459 | J103: pi_3QhrQZRxxun8okeS0kx1yn5l | K103: 17.99 | L103: 0 | M103: 0 | N103: 1 | O103: =K103-L103-M103 -> 17.99 | P103: =IF(D103="USD",O103,O103/N103) -> 17.99
A104: 103 | B104: 7698 | C104: ss qq | D104: USD | E104: Crypto ???????????? | F104: 45673.824 | G104: 1 | H104: Invoice Payment | I104: 43435 | J104: a3661e1258086583617581618f33941cd2a4b885156a38a523305ce6735fc272 | K104: 17.99 | L104: 0 | M104: 0 | N104: 1 | O104: =K104-L104-M104 -> 17.99 | P104: =IF(D104="USD",O104,O104/N104) -> 17.99
A105: 104 | B105: 7266 | C105: xiao hei | D105: USD | E105: Alipay ????????? (QR+APP) | F105: 45673.855 | G105: 1 | H105: Invoice Payment | I105: 43471 | J105: pi_3QhsCWRxxun8okeS1sHSOdrh | K105: 1 | L105: 0 | M105: 0 | N105: 1 | O105: =K105-L105-M105 -> 1 | P105: =IF(D105="USD",O105,O105/N105) -> 1
A106: 105 | B106: 7899 | C106: jams band | D106: USD | E106: Crypto ???????????? | F106: 45673.866 | G106: 1 | H106: Invoice Payment | I106: 43495 | J106: 6100a8f7b71809539647cad74d1cd503f51244189cb6b9e094b03f57f94f600b | K106: 69.99 | L106: 0 | M106: 0 | N106: 1 | O106: =K106-L106-M106 -> 69.99 | P106: =IF(D106="USD",O106,O106/N106) -> 69.99
A107: 106 | B107: 326 | C107: fan xi | D107: USD | E107: Alipay ????????? (QR+APP) | F107: 45673.883 | G107: 1 | H107: Invoice Payment | I107: 43483 | J107: pi_3QhsrZRxxun8okeS0Kq3E6C8 | K107: 17.99 | L107: 0 | M107: 0 | N107: 1 | O107: =K107-L107-M107 -> 17.99 | P107: =IF(D107="USD",O107,O107/N107) -> 17.99
A108: 107 | B108: 7901 | C108: lucky kkk | D108: CNY | E108: Alipay ????????? (QR+APP) | F108: 45673.931 | G108: 1 | H108: Invoice Payment | I108: 43507 | J108: pi_3Qhtw5Rxxun8okeS1AO88jMN | K108: 7.33 | L108: 0 | M108: 0 | N108: 7.33155 | O108: =K108-L108-M108 -> 7.33 | P108: =IF(D108="USD",O108,O108/N108) -> 0.99978858
A109: 108 | B109: 7729 | C109: Brian Guo | D109: USD | E109: Alipay ????????? (QR+APP) | F109: 45673.942 | G109: 1 | H109: Invoice Payment | I109: 43519 | J109: pi_3Qhu8fRxxun8okeS1WcYxHQM | K109: 20.25 | L109: 0 | M109: 0 | N109: 1 | O109: =K109-L109-M109 -> 20.25 | P109: =IF(D109="USD",O109,O109/N109) -> 20.25
A110: 109 | B110: 3309 | C110: Tang Joe | D110: USD | E110: Alipay ????????? (QR+APP) | F110: 45673.96 | G110: 1 | H110: Invoice Payment | I110: 43531 | J110: pi_3Qhua4Rxxun8okeS1tMqViPP | K110: 59.99 | L110: 0 | M110: 0 | N110: 1 | O110: =K110-L110-M110 -> 59.99 | P110: =IF(D110="USD",O110,O110/N110) -> 59.99
A111: 110 | B111: 8127 | C111: Emelia Abernathy | D111: USD | E111: Alipay ????????? (QR+APP) | F111: 45674 | G111: 1 | H111: Invoice Payment | I111: 43735 | K111: 0 | L111: 0 | M111: 0 | N111: 1 | O111: =K111-L111-M111 -> 0 | P111: =IF(D111="USD",O111,O111/N111) -> 0
A112: 111 | B112: 7974 | C112: gbu viie | D112: USD | E112: Alipay ????????? (QR+APP) | F112: 45674.162 | G112: 1 | H112: Invoice Payment | I112: 43567 | J112: pi_3Qhz5mRxxun8okeS1jwvRuCb | K112: 20.25 | L112: 0 | M112: 0 | N112: 1 | O112: =K112-L112-M112 -> 20.25 | P112: =IF(D112="USD",O112,O112/N112) -> 20.25
A113: 112 | B113: 8063 | C113: Ray Yang | D113: USD | E113: Alipay ????????? (QR+APP) | F113: 45674.459 | G113: 1 | H113: Invoice Payment | I113: 43639 | J113: pi_3Qi5o9Rxxun8okeS1fJOlsgZ | K113: 47.99 | L113: 0 | M113: 0 | N113: 1 | O113: =K113-L113-M113 -> 47.99 | P113: =IF(D113="USD",O113,O113/N113) -> 47.99
A114: 113 | B114: 8073 | C114: q q | D114: USD | E114: PayPal | F114: 45674.558 | G114: 1 | H114: Invoice Payment | I114: 43651 | J114: 42Y76699XR446992K | K114: 8.39 | L114: 0.91 | M114: 0 | N114: 1 | O114: =K114-L114-M114 -> 7.48 | P114: =IF(D114="USD",O114,O114/N114) -> 7.48
A115: 114 | B115: 8052 | C115: chenxin pan | D115: CNY | E115: Alipay ????????? (QR+APP) | F115: 45674.594 | G115: 1 | H115: Invoice Payment | I115: 43663 | J115: pi_3Qi8q8Rxxun8okeS0i4iK6rR | K115: 14.59 | L115: 0 | M115: 0 | N115: 7.33168 | O115: =K115-L115-M115 -> 14.59 | P115: =IF(D115="USD",O115,O115/N115) -> 1.9899941
A116: 115 | B116: 8052 | C116: chenxin pan | D116: CNY | E116: Alipay ????????? (QR+APP) | F116: 45674.596 | G116: 1 | H116: Invoice Payment | I116: 43663 | K116: 0.01 | L116: 0 | M116: 0 | N116: 7.33168 | O116: =K116-L116-M116 -> 0.01 | P116: =IF(D116="USD",O116,O116/N116) -> 0.0013639439
A117: 116 | B117: 326 | C117: fan xi | D117: USD | E117: Alipay ????????? (QR+APP) | F117: 45674.897 | G117: 1 | H117: Refund of Transaction ID pi_3QhsrZRxxun8okeS0Kq3E6C8 | I117: 43483 | K117: 0 | L117: 0 | M117: 17.99 | N117: 1 | O117: =K117-L117-M117 -> -17.99 | P117: =IF(D117="USD",O117,O117/N117) -> -17.99
A118: 117 | B118: 7274 | C118: k k | D118: USD | E118: Alipay ????????? (QR+APP) | F118: 45674.977 | G118: 1 | H118: Invoice Payment | I118: 43747 | J118: pi_3QiHReRxxun8okeS1Egkt9hN | K118: 20.25 | L118: 0 | M118: 0 | N118: 1 | O118: =K118-L118-M118 -> 20.25 | P118: =IF(D118="USD",O118,O118/N118) -> 20.25
A119: 118 | B119: 7664 | C119: bo caibang | D119: USD | E119: Alipay ????????? (QR+APP) | F119: 45674.993 | G119: 1 | H119: Invoice Payment | I119: 43771 | J119: pi_3QiHnpRxxun8okeS1alehclB | K119: 20.25 | L119: 0 | M119: 0 | N119: 1 | O119: =K119-L119-M119 -> 20.25 | P119: =IF(D119="USD",O119,O119/N119) -> 20.25
A120: 119 | B120: 8145 | C120: None Chan | D120: USD | E120: Alipay ????????? (QR+APP) | F120: 45675.007 | G120: 1 | H120: Invoice Payment | I120: 43783 | J120: pi_3QiI7TRxxun8okeS1cLOqqvx | K120: 20.25 | L120: 0 | M120: 0 | N120: 1 | O120: =K120-L120-M120 -> 20.25 | P120: =IF(D120="USD",O120,O120/N120) -> 20.25
A121: 120 | B121: 8174 | C121: bean cat | D121: USD | E121: PayPal | F121: 45675.08 | G121: 1 | H121: Invoice Payment | I121: 43807 | J121: 2VY73060GL141715U | K121: 20.25 | L121: 1.5 | M121: 0 | N121: 1 | O121: =K121-L121-M121 -> 18.75 | P121: =IF(D121="USD",O121,O121/N121) -> 18.75
A122: 121 | B122: 8202 | C122: s t | D122: USD | E122: PayPal | F122: 45675.158 | G122: 1 | H122: Invoice Payment | I122: 43855 | J122: 45X91744TE5491645 | K122: 8.39 | L122: 0.91 | M122: 0 | N122: 1 | O122: =K122-L122-M122 -> 7.48 | P122: =IF(D122="USD",O122,O122/N122) -> 7.48
A123: 122 | B123: 8106 | C123: nie wanting | D123: USD | E123: Alipay ????????? (QR+APP) | F123: 45675.397 | G123: 1 | H123: Invoice Payment | I123: 43723 | J123: pi_3QiQtFRxxun8okeS0RXb653t | K123: 20.25 | L123: 0 | M123: 0 | N123: 1 | O123: =K123-L123-M123 -> 20.25 | P123: =IF(D123="USD",O123,O123/N123) -> 20.25
A124: 123 | B124: 8276 | C124: WELL PLUSS | D124: USD | E124: Alipay ????????? (QR+APP) | F124: 45675.607 | G124: 1 | H124: Invoice Payment | I124: 43999 | J124: pi_3QiVbrRxxun8okeS1RlQoeeR | K124: 20.25 | L124: 0 | M124: 0 | N124: 1 | O124: =K124-L124-M124 -> 20.25 | P124: =IF(D124="USD",O124,O124/N124) -> 20.25
A125: 124 | B125: 8276 | C125: WELL PLUSS | D125: USD | E125: Alipay ????????? (QR+APP) | F125: 45675.691 | G125: 1 | H125: Invoice Payment | I125: 44047 | J125: pi_3QiXToRxxun8okeS0ZMc973p | K125: 20.25 | L125: 0 | M125: 0 | N125: 1 | O125: =K125-L125-M125 -> 20.25 | P125: =IF(D125="USD",O125,O125/N125) -> 20.25
A126: 125 | B126: 8285 | C126: Daniel Chien | D126: USD | E126: Alipay ????????? (QR+APP) | F126: 45675.705 | G126: 1 | H126: Invoice Payment | I126: 44095 | J126: pi_3QiXnnRxxun8okeS0wkoJb91 | K126: 20.25 | L126: 0 | M126: 0 | N126: 1 | O126: =K126-L126-M126 -> 20.25 | P126: =IF(D126="USD",O126,O126/N126) -> 20.25
A127: 126 | B127: 90 | C127: ??? ??? | D127: CNY | E127: Alipay ????????? (QR+APP) | F127: 45675.764 | G127: 1 | H127: Invoice Payment | I127: 44131 | J127: pi_3QiZ8DRxxun8okeS1eOEo6Sp | K127: 14.66 | L127: 0 | M127: 0 | N127: 7.329 | O127: =K127-L127-M127 -> 14.66 | P127: =IF(D127="USD",O127,O127/N127) -> 2.0002729
A128: 127 | B128: 8174 | C128: bean cat | D128: USD | E128: PayPal | F128: 45675.806 | G128: 1 | H128: Reversed Transaction ID: 2VY73060GL141715U | I128: 43807 | J128: 43886755B64209014 | K128: 0 | L128: -1.5 | M128: 20.25 | N128: 1 | O128: =K128-L128-M128 -> -18.75 | P128: =IF(D128="USD",O128,O128/N128) -> -18.75
A129: 128 | B129: 347 | C129: Steve Sun | D129: CNY | E129: Alipay ????????? (QR+APP) | F129: 45675.831 | G129: 1 | H129: Invoice Payment | I129: 44143 | J129: pi_3QiadPRxxun8okeS1hHfodv7 | K129: 14.58 | L129: 0 | M129: 0 | N129: 7.329 | O129: =K129-L129-M129 -> 14.58 | P129: =IF(D129="USD",O129,O129/N129) -> 1.9893573
... A134: 133 | B134: 1836 | C134: ?????? ??? | D134: CNY | E134: Alipay ????????? (QR+APP) | F134: 45677.815 | G134: 1 | H134: Invoice Payment | I134: 43591 | J134: pi_3QjJEHRxxun8okeS0MivC2eF | K134: 87.51 | L134: 0 | M134: 0 | N134: 7.329 | O134: =K134-L134-M134 -> 87.51 | P134: =IF(D134="USD",O134,O134/N134) -> 11.940237
A135: 134 | B135: 1836 | C135: ?????? ??? | D135: CNY | E135: Alipay ????????? (QR+APP) | F135: 45677.824 | G135: 1 | H135: Invoice Payment | I135: 43591 | K135: 0.01 | L135: 0 | M135: 0 | N135: 7.329 | O135: =K135-L135-M135 -> 0.01 | P135: =IF(D135="USD",O135,O135/N135) -> 0.0013644426
A136: 135 | B136: 8541 | C136: lyj ?????? | D136: USD | E136: PayPal | F136: 45678.031 | G136: 1 | H136: Invoice Payment | I136: 44503 | J136: 28L54835SX678730B | K136: 20.25 | L136: 1.5 | M136: 0 | N136: 1 | O136: =K136-L136-M136 -> 18.75 | P136: =IF(D136="USD",O136,O136/N136) -> 18.75
A137: 136 | B137: 8646 | C137: tik tok | D137: USD | E137: Alipay ????????? (QR+APP) | F137: 45678.376 | G137: 1 | H137: Invoice Payment | I137: 44563 | J137: pi_3QjVqDRxxun8okeS0D2bb50L | K137: 8.39 | L137: 0 | M137: 0 | N137: 1 | O137: =K137-L137-M137 -> 8.39 | P137: =IF(D137="USD",O137,O137/N137) -> 8.39
A138: 137 | B138: 3229 | C138: Waer san | D138: USD | E138: Alipay ????????? (QR+APP) | F138: 45678.463 | G138: 1 | H138: Invoice Payment | I138: 41851 | J138: pi_3QjXmxRxxun8okeS1KEqyfbR | K138: 1.99 | L138: 0 | M138: 0 | N138: 1 | O138: =K138-L138-M138 -> 1.99 | P138: =IF(D138="USD",O138,O138/N138) -> 1.99
A139: 138 | B139: 1836 | C139: ?????? ??? | D139: CNY | E139: Alipay ????????? (QR+APP) | F139: 45678.512 | G139: 1 | H139: Invoice Payment | I139: 44539 | J139: pi_3QjYunRxxun8okeS1iieie5n | K139: 87.74 | L139: 0 | M139: 0 | N139: 7.31204 | O139: =K139-L139-M139 -> 87.74 | P139: =IF(D139="USD",O139,O139/N139) -> 11.999387
...

Sheet 其它流水2025
A1: 序号 | B1: 类别 | C1: 对象 | D1: 详情 | E1: 日期 | F1: 账户 | G1: 经手人 | H1: 支出本币 | I1: 收入本币 | J1: 收入$ | K1: 支出$ | L1: 结算 | M1: 核实
A2: 1 | B2: 支出 | C2: Thuny | D2: Peter直接将上一笔款转给我个人 | E2: 45678 | F2: ZA Bank | G2: Peter | H2: 2925.99 | I2: 0 | J2: 0 | K2: 375.56 | L2: =J2-K2 -> -375.56 | M2: 已查收
A3: 2 | B3: 支出 | C3: Thuny | D3: 购买Vision电话卡 | E3: 45894 | F3: 水星-jiao xiang | G3: Thuny | H3: 275 | I3: 0 | J3: 0 | K3: 275 | L3: =J3-K3 -> -275 | M3: 已查收
A4: 3 | B4: 支出 | C4: Thuny | D4: 购买教材，统计学课程 | E4: 45899 | F4: 水星-jiao xiang | G4: Thuny | H4: 18.38 | I4: 0 | J4: 0 | K4: 18.38 | L4: =J4-K4 -> -18.38 | M4: 已查收
A5: 4 | B5: 支出 | C5: Thuny | D5: 交美国房租 | E5: 45900 | F5: wise-jiao xiang | G5: Thuny | H5: 660 | I5: 0 | J5: 0 | K5: 660 | L5: =J5-K5 -> -660 | M5: 已查收
A6: 5 | B6: 支出 | C6: Thuny | D6: eBay | E6: 45901 | F6: 水星-jiao xiang | G6: Thuny | H6: 11.9 | I6: 0 | J6: 0 | K6: 11.9 | L6: =J6-K6 -> -11.9 | M6: 已查收
A7: 6 | B7: 支出 | C7: Thuny | D7: eBay | E7: 45916 | F7: 水星-jiao xiang | G7: Thuny | H7: 17.14 | I7: 0 | J7: 0 | K7: 17.14 | L7: =J7-K7 -> -17.14 | M7: 已查收
A8: 7 | B8: 支出 | C8: Thuny | D8: Walmart | E8: 45916 | F8: 水星-jiao xiang | G8: Thuny | H8: 50.08 | I8: 0 | J8: 0 | K8: 50.08 | L8: =J8-K8 -> -50.08 | M8: 已查收
A9: 8 | B9: 支出 | C9: Thuny | D9: Qwaaq | E9: 45920 | F9: 水星-jiao xiang | G9: Thuny | H9: 39.07 | I9: 0 | J9: 0 | K9: 39.07 | L9: =J9-K9 -> -39.07 | M9: 已查收
A10: 9 | B10: 支出 | C10: Thuny | D10: Chase银行 | E10: 45921 | F10: USDT | G10: Thuny | H10: 500.74 | I10: 0 | J10: 0 | K10: 500.74 | L10: =J10-K10 -> -500.74 | M10: 已查收
A11: 10 | B11: 支出 | C11: Thuny | D11: 交美国房租 | E11: 45923 | F11: wise-jiao xiang | G11: Thuny | H11: 704 | I11: 0 | J11: 0 | K11: 704 | L11: =J11-K11 -> -704 | M11: 已查收
A12: 11 | B12: 支出 | C12: Thuny | D12: 交美国房租 | E12: 45933 | F12: wise-jiao xiang | G12: Thuny | H12: 670 | I12: 0 | J12: 0 | K12: 670 | L12: =J12-K12 -> -670 | M12: 已查收
A13: 12 | B13: 支出 | C13: Thuny | D13: 交美国房租 | E13: 45963 | F13: wise-jiao xiang | G13: Thuny | H13: 750 | I13: 0 | J13: 0 | K13: 750 | L13: =J13-K13 -> -750 | M13: 已查收
A14: 13 | B14: 支出 | C14: Thuny | D14: 交美国房租 | E14: 45988 | F14: wise-jiao xiang | G14: Thuny | H14: 10 | I14: 0 | J14: 0 | K14: 10 | L14: =J14-K14 -> -10 | M14: 已查收

Sheet 采购
A1: 序号 | B1: 类别 | C1: 对象 | D1: 详情 | E1: 日期 | F1: 账户 | G1: 经手人 | H1: 支出本币 | I1: 收入本币 | J1: 收入$ | K1: 支出$ | L1: 结算 | M1: 核实
A2: 1 | B2: 销售运营 | C2: 皮老板 | D2: 支付给皮老板台湾1，73341 | E2: 45555 | F2: Thuny | G2: Thuny | H2: 1500 | I2: 0 | J2: 0 | K2: =H2/7.21 -> 208.04438 | L2: =J2-K2 -> -208.04438 | M2: 已查收
A3: 2 | B3: 销售运营 | C3: 皮老板 | D3: 支付给皮老板台湾1，75927 | E3: 45598 | F3: Thuny | G3: Thuny | H3: 1500 | I3: 0 | J3: 0 | K3: =H3/7.21 -> 208.04438 | L3: =J3-K3 -> -208.04438 | M3: 已查收
A4: 3 | B4: 销售运营 | C4: 皮老板 | D4: 支付给皮老板台湾2，77753 | E4: 45621 | F4: Thuny | G4: Thuny | H4: 1800 | I4: 0 | J4: 0 | K4: =H4/7.21 -> 249.65326 | L4: =J4-K4 -> -249.65326 | M4: 已查收
A5: 4 | B5: 采购 | C5: 淘宝 | D5: 香港主机 | E5: 45421 | F5: Thuny | G5: Thuny | H5: 17250 | I5: 0 | J5: 0 | K5: =H5/7.21 -> 2392.5104 | L5: =J5-K5 -> -2392.5104 | M5: 已查收
A6: 5 | B6: 采购 | C6: 京东 | D6: 两块三星硬盘 | E6: 45434 | F6: Thuny | G6: Thuny | H6: 988 | I6: 0 | J6: 0 | K6: =H6/7.21 -> 137.0319 | L6: =J6-K6 -> -137.0319 | M6: 已查收
A7: 6 | B7: 采购 | C7: DMIT | D7: 支付宝W系统插件 | E7: 45460 | F7: Thuny | G7: Thuny | H7: 50 | I7: 0 | J7: 0 | K7: =H7/7.21 -> 6.9348128 | L7: =J7-K7 -> -6.9348128 | M7: 已查收
A8: 7 | B8: 采购 | C8: DMIT | D8: 支付宝W系统插件 | E8: 45460 | F8: Peter | G8: Peter | H8: 100 | I8: 0 | J8: 0 | K8: =H8/7.21 -> 13.869626 | L8: =J8-K8 -> -13.869626 | M8: 已查收
A9: 8 | B9: 采购 | C9: 淘宝 | D9: 日本主机 | E9: 45615 | F9: Thuny | G9: Peter | H9: 7020 | I9: 0 | J9: 0 | K9: =H9/7.21 -> 973.64771 | L9: =J9-K9 -> -973.64771 | M9: 已查收
A10: 9 | B10: 采购 | C10: 淘宝 | D10: 日本三块硬盘，2*1TB，1*4TB | E10: 45615 | F10: Thuny | G10: Peter | H10: 2565 | I10: 0 | J10: 0 | K10: =H10/7.21 -> 355.75589 | L10: =J10-K10 -> -355.75589 | M10: 已查收
A11: 10 | B11: 采购 | C11: 淘宝 | D11: 日本主机导轨 | E11: 45616 | F11: Thuny | G11: Thuny | H11: 200 | I11: 0 | J11: 0 | K11: =H11/7.21 -> 27.739251 | L11: =J11-K11 -> -27.739251 | M11: 已查收
A12: 11 | B12: 采购 | C12: 淘宝 | D12: U2硬盘线 | E12: 45618 | F12: Thuny | G12: Thuny | H12: 373 | I12: 0 | J12: 0 | K12: =H12/7.21 -> 51.733703 | L12: =J12-K12 -> -51.733703 | M12: 已查收
A13: 12 | B13: 采购 | C13: 淘宝 | D13: 日本主机电源 | E13: 45615 | F13: Peter | G13: Peter | H13: 350 | I13: 0 | J13: 0 | K13: =H13/7.21 -> 48.543689 | L13: =J13-K13 -> -48.543689 | M13: 已查收
A14: 13 | B14: 采购 | C14: 京东 | D14: SSD SATA 480G MLC | E14: 45615 | F14: Peter | G14: Peter | H14: 759 | I14: 0 | J14: 0 | K14: =H14/7.21 -> 105.27046 | L14: =J14-K14 -> -105.27046 | M14: 已查收
A15: 14 | B15: 销售运营 | C15: 皮老板 | D15: 支付给皮老板台湾2，80033 | E15: 45682 | F15: Thuny | G15: Thuny | H15: 1800 | I15: 0 | J15: 0 | K15: 248.48 | L15: =J15-K15 -> -248.48 | M15: 已查收
A16: 15 | B16: 销售运营 | C16: 皮老板 | D16: 支付给皮老板台湾1，80913 | E16: 45699 | F16: Thuny | G16: Thuny | H16: 1500 | I16: 0 | J16: 0 | K16: 205.33 | L16: =J16-K16 -> -205.33 | M16: 已查收
A17: 16 | B17: 销售运营 | C17: 皮老板 | D17: 支付给皮老板台湾2，81559 | E17: 45712 | F17: Thuny | G17: Thuny | H17: 1800 | I17: 0 | J17: 0 | K17: 248.69 | L17: =J17-K17 -> -248.69 | M17: 已查收
A18: 17 | B18: 销售运营 | C18: 皮老板 | D18: 支付给皮老板台湾2，82617 | E18: 45720 | F18: Thuny | G18: Thuny | H18: 866 | I18: 0 | J18: 0 | K18: 119.19 | L18: =J18-K18 -> -119.19 | M18: 已查收
A19: 18 | B19: 销售运营 | C19: 皮老板 | D19: 支付给皮老板台湾1，82251 | E19: 45728 | F19: Thuny | G19: Thuny | H19: 1500 | I19: 0 | J19: 0 | K19: 207.09 | L19: =J19-K19 -> -207.09 | M19: 已查收
A20: 19 | B20: 采购 | C20: 淘宝 | D20: 香港服务器和内存 | E20: 45730 | F20: Peter | G20: Peter | H20: 10393 | I20: 0 | J20: 0 | K20: =H20/7.21 -> 1441.4702 | L20: =J20-K20 -> -1441.4702 | M20: 已查收
A21: 20 | B21: 采购 | C21: 淘宝 | D21: 香港主机硬盘，2块960G，2块1.92T，2块3.84T | E21: 45734 | F21: Thuny | G21: Thuny | H21: 5270 | I21: 0 | J21: 0 | K21: =H21/7.21 -> 730.92926 | L21: =J21-K21 -> -730.92926 | M21: 已查收
A22: 21 | B22: 销售运营 | C22: 皮老板 | D22: 支付给皮老板台湾2，82947 | E22: 45741 | F22: Thuny | G22: Thuny | H22: 3100 | I22: 0 | J22: 0 | K22: 426.81 | L22: =J22-K22 -> -426.81 | M22: 已查收
A23: 22 | B23: 公司管理 | C23: 陈敏 | D23: 公司管理增加股东 | E23: 45747 | F23: Thuny | G23: Thuny | H23: 580 | I23: 0 | J23: 0 | K23: 80 | L23: =J23-K23 -> -80 | M23: 已查收
A24: 23 | B24: 销售运营 | C24: 皮老板 | D24: 支付给皮老板台湾1，83731 | E24: 45758 | F24: Thuny | G24: Thuny | H24: 1500 | I24: 0 | J24: 0 | K24: 206.64 | L24: =J24-K24 -> -206.64 | M24: 已查收
A25: 24 | B25: 销售运营 | C25: 皮老板 | D25: 支付给皮老板台湾2，84333 | E25: 45772 | F25: Thuny | G25: Thuny | H25: 3100 | I25: 0 | J25: 0 | K25: 426.29 | L25: =J25-K25 -> -426.29 | M25: 已查收
A26: 25 | B26: 销售运营 | C26: 皮老板 | D26: 支付给皮老板台湾1，83731 | E26: 45790 | F26: Thuny | G26: Thuny | H26: 1500 | I26: 0 | J26: 0 | K26: 207.53 | L26: =J26-K26 -> -207.53 | M26: 已查收
A27: 26 | B27: 销售运营 | C27: 三丰云 | D27: 北京BGP台湾机器DDNS检测（三年） | E27: 45615 | F27: Peter | G27: Peter | H27: 1999 | I27: 0 | J27: 0 | K27: 276.56 | L27: =J27-K27 -> -276.56 | M27: 已查收
